Workbook

Sheet 總覽
B2: ★ 波段股價預估試算 — 使用說明
B4: 用途:進場前檢核個股的基本面、籌碼面與估值。於「股價預估」頁 E1 輸入股票代號,由估值鏈推算預估EPS與目標價。
B5: 估值鏈:近月營收×3 → 預估季營收 → ×毛利率 − 營業費用 + 業外 → ×(1−稅率) → 預估稅後淨利 ÷ 股本 → 預估EPS × 高/中/低本益比 → 目標價
B6: 注意:本檔原為 Google Sheets,IMPORTHTML 自動抓取功能在 Excel 已失效,各頁資料為 2026/08/14 快照。要更新資料或換股票時,請直接請 Claude 上網抓官方最新資料填入。
B8: 分類 | C8: 分頁 | D8: 用途 | E8: 原資料來源
B9: 🟡 儀表板 | C9: 股價預估 | D9: 主儀表板:輸入代號→訊號燈+估值鏈+預估EPS+目標價+股利 | E9: 彙整各分頁
B10: 🔵 基本面 | C10: 股票資訊 | D10: 個股基本資料:股價、股本、市值、Beta、財報/營收發布日、ETF持股 | E10: 富邦證券
B11: 🔵 基本面 | C11: 營收 | D11: 月營收與長短期年增率訊號 | E11: 富邦證券
B12: 🔵 基本面 | C12: 毛利率&業外 | D12: 季度獲利能力、業外占比、毛利率標準差通道 | E12: 富邦證券
B13: 🔵 基本面 | C13: 營業費用 | D13: 損益表季度拆解(累計→單季)、稅率、費用率、週轉天數 | E13: money-link / histock
B14: 🔵 基本面 | C14: 每股盈餘(EPS) | D14: 歷史EPS、盈餘成長率、本益比高中低分位→目標價矩陣 | E14: 富邦證券
B15: 🔵 基本面 | C15: 股息&現金流 | D15: 歷年股利政策、殖利率、填息天數 | E15: Goodinfo等
B16: 🔵 基本面 | C16: 財報健檢 | D16: 資產負債表+現金流量表摘要與安全性指標(新增) | E16: 公開資訊觀測站
B17: 🟠 籌碼面 | C17: 籌碼 | D17: 法人買賣超、集中度、大戶比、融資券、券商分點 | E17: 富邦/histock
B18: 🟠 籌碼面 | C18: 期貨籌碼 | D18: 三大法人期貨未平倉(原「工作表54」) | E18: 期交所
B19: 🟢 市場面 | C19: 排行榜 | D19: 成交值排行、券資比排行(上市/上櫃) | E19: 富邦證券
... B22: ⚪ 參考 | C22: 減資一覽表 | D22: 減資股票調整用(現為手動填寫) | E22: money-link(停用)

Sheet 股價預估
A1: =證券編碼查詢!E2 -> 上市 | B1: 股票 | C1: =證券編碼查詢!D2 -> 台積電 | D1: 股本 | E1: 2330
A2: 市值 | D2: =股票資訊!B14 -> 2593.24
A3: =股票資訊!D6/100&"億" -> 621080.26億 | B3: 股價 | C3: =股票資訊!H2 -> 2395 | D3: =IF(ISBLANK(C3)," ",IF(I25<0,"衰退股",IF(I25<0.8,"估總報酬PE昂貴",IF(I25<1.2,"估總報酬PE合理",IF(I25>1.2,"估總報酬PE便宜","估總報酬PE昂貴"))))) -> 估總報酬PE便宜
D4: =IF(ISBLANK(C3)," ",IF(H38<0,"衰退股",IF(G38>1.33,"PEG估值昂貴",IF(G38>0.67,"PEG估值合理",IF(G38>0,"PEG估值便宜","衰退股"))))) -> PEG估值便宜
A5: =IF(ISBLANK(C3)," ",IF(E39<>"",IF(E39>D39,"研發費佔營收季增","研發費佔營收季減"),"")) -> 研發費佔營收季減 | B5: =IF(ISBLANK(C3)," ",IF(J45>G30,"估殖利率成長","估殖利率衰退")) -> 估殖利率衰退 | C5: =IF(ISBLANK(C3)," ",IF(營業費用!E26>營業費用!E27,"存貨週轉季增","存貨週轉季減")) -> 存貨週轉季減 | D5: =IF(ISBLANK(C3)," ",IF('毛利率&業外'!E4>'毛利率&業外'!E5,"毛利季增","毛利季減")) -> 毛利季增 | E5: =IF(ISBLANK(C3)," ",IF(F45>F35,"估本益比河流上升","估本益比河流下滑")) -> 估本益比河流上升 | F5: =IF(ISBLANK(C3)," ",營收!V3) -> 長短期營收擴大
A6: =IF(ISBLANK(C3)," ",IF(E39<>"",IF(E39>B39,"研發費佔營收年增","研發費佔營收年減"),"")) -> 研發費佔營收年減 | B6: =IF(ISBLANK(C3)," ",IF(F45>F35,"估盈餘成長","估盈餘衰退")) -> 估盈餘成長 | C6: =IF(ISBLANK(C3)," ",IF(營業費用!E26>營業費用!E29,"估存貨週轉年增","估存貨週轉年減")) -> 估存貨週轉年減 | D6: =IF(ISBLANK(C3)," ",IF('毛利率&業外'!E4>'毛利率&業外'!E7,"估毛利年增","估毛利年減")) -> 估毛利年增 | E6: =IF(ISBLANK(C3)," ",IF(營收!H3>0,"累積年增率>0","累積年增率<0")) -> 累積年增率>0 | F6: =IF(ISBLANK(C3)," ",營收!Q3) -> 長短期YOY擴大
A7: =籌碼!S52 -> 外資賣超1天 | B7: 營收預估
A8: =籌碼!S54 -> 投信賣超1天 | B8: 近1個月營收(積極) | D8: 預估單季營收(單月*3),(總月/4),(近3月)
A9: =IF(ISBLANK(C3)," ","券資比"&IF(籌碼!AG8>籌碼!AG9,"上升","下降")) -> 券資比下降 | B9: =IF(ISBLANK(營收!B3),IF(B8="近1個月營收(積極)",營收!B91,IF(B8="近12個月營收",SUM(營收!B91:B102),SUM(營收!B91:B93)))/1000,IF(B8="近1個月營收(積極)",營收!B3,IF(B8="近12個月營收",SUM(營收!B3:B14),SUM(營收!B3:B5)))/1000) -> 467580.54 | D9: =IF(B8="近1個月營收(積極)",B9*3,IF(B8="近12個月營收",ABS(B9/4),B9)) -> 1402741.6
A10: =籌碼!AG8 -> 0.0013
A11: =籌碼!S55 -> 融資增加1天 | B11: 毛利預估
A12: =籌碼!S56 -> 融券減少2天 | B12: 預計單季營收 | C12: 近1季毛利率 | D12: 預估毛利
A13: =IF(ISBLANK(C3)," ","融資使用率"&IF(籌碼!AA8>籌碼!AA9,"上升","下降")) -> 融資使用率下降 | B13: =D9 -> 1402741.6 | C13: =IF(C12="近1季毛利率",IF('毛利率&業外'!E4=0,'毛利率&業外'!E5,'毛利率&業外'!E4),IF('毛利率&業外'!E4=0,AVERAGEIF('毛利率&業外'!E5:E8,">0"),AVERAGEIF('毛利率&業外'!E4:E7,">0"))) -> 0.6772 | D13: =B13*C13 -> 949936.63
A14: =籌碼!AA8 -> 0.0043
A15: 投信持股比 | B15: 營業利益預估
A16: =籌碼!R8 -> 0.036636762 | B16: 預估毛利 | C16: 平均4季營業費 | D16: 預估營業利益
A17: =IF(ISBLANK(C1)," ",股票資訊!H29) -> 10檔ETF持股 | B17: =D13 -> 949936.63 | C17: =IF(C16="近1季營業費",營業費用!F7,營業費用!H7) -> 92236 | D17: =B17-C17 -> 857700.63
A18: 預估殖利率
A19: =J43/C3 -> 0.014245223 | B19: 業外收益預估
B20: 預估營業利益 | C20: 業外收支(季均) | D20: 預估稅前淨利 | F20: 預估稅後淨利(季均)
A21: Beta值 | B21: =D17 -> 857700.63 | C21: =IF(C20="業外收支(季均)", IFERROR(AVERAGE('毛利率&業外'!H4:H7),0),0) -> 44201.5 | D21: =B21+C21 -> 901902.13 | F21: =IF(F20="預估稅後淨利(季均)",D21*營業費用!H13,D21*營業費用!E13) -> 758821.16
A22: =股票資訊!H8 -> 1.1 | C22: =C21/D21 -> 0.049009198 | F22: =IF(F20="預估稅後淨利(季均)",營業費用!H13,營業費用!E13) -> 0.84135643
B23: EPS計算
A24: 標準差 | B24: 近季母公司稅後 | C24: 估母公司稅後 | D24: 近一季EPS | E24: 預估季EPS | F24: 估EPS季成長率 | G24: =H37 -> 預估盈餘成長率 | H24: 估年殖利率 | I24: 估總報酬PE
A25: =股票資訊!H9 -> 0.0208 | B25: =營業費用!F10 -> 706561.9 | C25: =F21-營業費用!H11 -> 758905.16 | D25: =E35 -> 27.25 | E25: =IF(ISBLANK(C3)," ",IF(E24="預估季EPS",C25*D25/B25,(C25*D25/B25)/(1-IF(C1="","",VLOOKUP(C1,減資一覽表!B:E,4,FALSE))))) -> 29.268725 | F25: =IF(D25<0,1-(E25/D25),(E25-D45)/D45) -> 0.074081634 | G25: =H38 -> 0.35691815 | H25: =IF(H37="預估盈餘成長率",IF(E45<0,0,E45*4*H29/C3),J45) -> 0.01699908 | I25: =IF(H37="預估盈餘成長率",IF(G47=0,0,(G25+H25)/G47*100),IF(G45=0,0,(G25+H25)/G45*100)) -> 1.8278214
A26: =W56 -> 平均殖利率 | B26: 非控制權益(季均) | C26: =營業費用!K11 -> -84 | H26: 停止融卷期間 | I26: =IF(ISBLANK(證券編碼查詢!C41),證券編碼查詢!B41,證券編碼查詢!C41) -> 115/09/10 ~ 115/09/15
A27: =V56 -> 0.011208102 | B27: ='股息&現金流'!A1 -> 年度 | C27: ='股息&現金流'!B1 -> 2022 | D27: ='股息&現金流'!C1 -> 2023 | E27: ='股息&現金流'!D1 -> 2024 | F27: ='股息&現金流'!E1 -> 2025 | G27: ='股息&現金流'!F1 -> 2026 | H27: =G27+1&"預估" -> 2027預估
A28: 平均配息率 | B28: ='股息&現金流'!A2 -> 現金股利 | C28: ='股息&現金流'!B2 -> 10.974 | D28: ='股息&現金流'!C2 -> 12.9987 | E28: ='股息&現金流'!D2 -> 17.04 | F28: ='股息&現金流'!E2 -> 22.099 | G28: ='股息&現金流'!F2 -> - | H28: =J43 -> 34.117309 | I28: 預估現金股利
A29: =IF(A28="平均配息率",IF(G29="無",AVERAGEIF(C29:F29,">=0")/100,AVERAGEIF(C29:G29,">=0")/100),IF(G29="無",F29/100,G29/100)) -> 0.34775 | B29: ='股息&現金流'!A3 -> 現金股利發放率 | C29: ='股息&現金流'!B3 -> 28.1 | D29: ='股息&現金流'!C3 -> 40.2 | E29: ='股息&現金流'!D3 -> 37.6 | F29: ='股息&現金流'!E3 -> 33.2 | G29: ='股息&現金流'!F3 -> - | H29: =A29 -> 0.34775 | I29: 預估發放率
C30: ='股息&現金流'!B4 -> 0.0186 | D30: ='股息&現金流'!C4 -> 0.0143 | E30: ='股息&現金流'!D4 -> 0.016 | F30: ='股息&現金流'!E4 -> 0.0098 | G30: ='股息&現金流'!F4 -> - | H30: =J45 -> 0.014245223 | I30: 預估殖利率
A31: =股票資訊!B21 -> 晶圓-5奈米30.98%、晶圓-3奈米20.85%、其他14.08%、晶圓-7奈米12.06%、晶圓-28奈米5.91%、晶圓-16奈米5.66%、晶圓-65奈米3.16%、晶圓-40及45奈米2.51%、晶圓-0.15及0.18微米2.32%、晶圓-0.11及0.13微米1.28%、晶圓-90奈米0.56%、晶圓-0.25微米以上0.51%、晶圓-20奈米0.11% (2025年)
J32: 股利
J33: =IF(F35<0,0,F35*A29) -> 30.00387
A34: 現有 | B34: ='每股盈餘(EPS)'!A6 -> 114.3Q | C34: ='每股盈餘(EPS)'!A5 -> 114.4Q | D34: ='每股盈餘(EPS)'!A4 -> 115.1Q | E34: ='每股盈餘(EPS)'!A3 -> 115.2Q | F34: EPS | G34: 目前本益比 | H34: 股價 | I34: 空間 | J34: 殖利率
B35: ='每股盈餘(EPS)'!H6 -> 17.44 | C35: ='每股盈餘(EPS)'!H5 -> 19.51 | D35: ='每股盈餘(EPS)'!H4 -> 22.08 | E35: ='每股盈餘(EPS)'!H3 -> 27.25 | F35: =IF(B35+C35+D35+E35=0,"",B35+C35+D35+E35) -> 86.28 | G35: =IF(F35<0,0,C3/F35) -> 27.758461 | H35: =C3 -> 2395 | I35: =(H35-C3)/C3 -> 0 | J35: =J33/C3 -> 0.012527712
A36: 業外占比 | B36: ='毛利率&業外'!L7 -> 0.04698412
A37: 稅率(%) | B37: =營業費用!B13 -> 0.85988199 | E37: =IF(D37="","",(D37/F45)-1) | G37: 估本益成長比(PEG) | H37: 預估盈餘成長率 | J37: =IF(H37="近1年盈餘成長率","預估盈餘成長率","近1年盈餘成長率") -> 近1年盈餘成長率
A38: 毛利率 | B38: ='毛利率&業外'!E7 -> 0.5945 | G38: =IF(H37="預估盈餘成長率",G47/H38/100,G45/H38/100) -> 0.57315633 | H38: =IF(D37>0,E37,IF(H37="近1年盈餘成長率",'每股盈餘(EPS)'!P3,IF(H37="近3年盈餘成長率",'每股盈餘(EPS)'!Q3,IF(H37="近4年盈餘成長率",'每股盈餘(EPS)'!R3,IF(F35<0,1-(E45*4/F35),(E45*4/F35)-1))))) -> 0.35691815 | J38: =IF(H37="近1年盈餘成長率",(E45*4-F35)/F35,'每股盈餘(EPS)'!P3) -> 0.60308373
A39: =營業費用!A17 -> 研發費用/營收 | B39: =營業費用!B17 -> 0.064391419 | C39: =營業費用!C17 -> 0.062000192 | D39: =營業費用!D17 -> 0.059744713 | E39: =營業費用!E17 -> 0.057578145
G40: ="營收發布剩"&股票資訊!L8&"天" -> 營收發布剩19天 | H40: ="財報發布剩"&股票資訊!L7&"天" -> 財報發布剩65天 | I40: 除息日 | J40: =證券編碼查詢!C37 -> 115/09/16
A41: 股淨比 | B41: 高本益比 | C41: 中位數本益比 | D41: 低本益比 | E41: 目前本益比 | F41: =IF(ISBLANK(C3)," ",IF(F45>F35,"預估成長","預估衰退")) -> 預估成長
A42: =股票資訊!D12 -> 9.59 | B42: ='每股盈餘(EPS)'!B45 -> 40.805856 | C42: ='每股盈餘(EPS)'!E45 -> 23.107385 | D42: ='每股盈餘(EPS)'!H45 -> 5.408913 | E42: =IF(F35<0,0,C3/F35) -> 27.758461 | J42: 預估股利
J43: =IF(F45<0,0,F45*A29) -> 34.117309
A44: 預估 | B44: ='每股盈餘(EPS)'!A5 -> 114.4Q | C44: ='每股盈餘(EPS)'!A4 -> 115.1Q | D44: ='每股盈餘(EPS)'!A3 -> 115.2Q | E44: 預估 | F44: 預估EPS | G44: 預估本益比 | H44: 目前PE預估股價 | I44: 空間 | J44: 預估殖利率
B45: ='每股盈餘(EPS)'!H5 -> 19.51 | C45: ='每股盈餘(EPS)'!H4 -> 22.08 | D45: ='每股盈餘(EPS)'!H3 -> 27.25 | E45: =E25 -> 29.268725 | F45: =IFERROR(F35+E25-B35,"") -> 98.108725 | G45: =IF(F45<0,0,C3/F45) -> 24.411692 | H45: =IF(F45<0,H35,F45*G35) -> 2723.3472 | I45: =(H45-C3)/C3 -> 0.13709695 | J45: =J43/C3 -> 0.014245223
A46: 業外占比 | B46: ='毛利率&業外'!L6 -> 0.046358398 | C46: ='毛利率&業外'!L5 -> 0.04192207 | D46: ='毛利率&業外'!L4 -> 0.11111279 | E46: =C22 -> 0.049009198 | F46: 年化EPS(季×4) | G46: 對應本益比 | H46: 年化推估股價 | I46: 空間
A47: 稅率(%) | B47: =營業費用!C13 -> 0.85321865 | C47: =營業費用!D13 -> 0.83280251 | D47: =營業費用!E13 -> 0.81952257 | E47: =F22 -> 0.84135643 | F47: =E45*4 -> 117.0749 | G47: =IF(E45<0,0,(C3/(E45*4))) -> 20.45699 | H47: =IF(F47<0,H35,F47*G35) -> 3249.819 | I47: =(H47-C3)/C3 -> 0.35691815
A48: 毛利率 | B48: ='毛利率&業外'!E6 -> 0.6233 | C48: ='毛利率&業外'!E5 -> 0.6625 | D48: ='毛利率&業外'!E4 -> 0.6772 | E48: =C13 -> 0.6772
B49: 新聞 | C49: 🔍 Google 新聞 | E49: 河流圖 | F49: 📈 CMoney 河流圖 | H49: 合約負債－流動 | I49: 📊 富邦-合約負債 | L49: ="+1" -> +1 | M49: ="+2" -> +2 | N49: ="+3" -> +3
B50: 網站 | C50: 🌐 公司官網 | E50: 河流圖 | F50: 📈 Goodinfo 週K河流圖 | L50: 34.1 | M50: 47.7 | N50: 49.8
V51: 股息 | Y51: 月增率MOM
V52: =AVERAGE(E28:G28) -> 19.5695 | W52: 近三年 | Y52: =營收!D3 -> 0.056 | Z52: 當月
V53: =G28 -> - | W53: 近年 | Y53: =營收!D4 -> 0.062 | Z53: 上月
V54: =H28 -> 34.117309 | W54: 預估 | Y54: =營收!D5 -> 0.015 | Z54: 前月
V55: =AVERAGE(V52:V54) -> 26.843404 | W55: 平均股息 | Y55: =AVERAGE(Y52:Y54) -> 0.044333333 | Z55: 平均月增率MOM
V56: =V55/C3 -> 0.011208102 | W56: 平均殖利率
V58: =籌碼!F51 -> 券商名稱 | W58: =籌碼!I51 -> 買超 | X58: =籌碼!J51 -> 均價 | AA58: =籌碼!A51 -> 券商名稱 | AB58: =籌碼!D51 -> 賣超 | AC58: =籌碼!E51 -> 均價
V59: =籌碼!F52 -> 港商麥格理 | W59: =籌碼!I52 -> 1810 | X59: =籌碼!J52 -> 2425.79 | Y59: =IFERROR(__xludf.DUMMYFUNCTION("SPARKLINE(W59*X59,{""color1"",""red"";""charttype"",""bar""; ""max"", 199999})"),"") | Z59: =IFERROR(__xludf.DUMMYFUNCTION("SPARKLINE(AB59*AC59,{""color1"",""green"";""charttype"",""bar""; ""max"", 199999})"),"") | AA59: =籌碼!A52 -> 台灣摩根士丹利 | AB59: =籌碼!D52 -> -1332 | AC59: =籌碼!E52 -> 2416.31
V60: =籌碼!F53 -> 國泰 | W60: =籌碼!I53 -> 757 | X60: =籌碼!J53 -> 2420 | Y60: =IFERROR(__xludf.DUMMYFUNCTION("SPARKLINE(W60*X60,{""color1"",""red"";""charttype"",""bar""; ""max"", 199999})"),"") | Z60: =IFERROR(__xludf.DUMMYFUNCTION("SPARKLINE(AB60*AC60,{""color1"",""green"";""charttype"",""bar""; ""max"", 199999})"),"") | AA60: =籌碼!A53 -> 美商高盛 | AB60: =籌碼!D53 -> -1064 | AC60: =籌碼!E53 -> 2413.21
V61: =籌碼!F54 -> 中國信託 | W61: =籌碼!I54 -> 490 | X61: =籌碼!J54 -> 2421.51 | Y61: =IFERROR(__xludf.DUMMYFUNCTION("SPARKLINE(W61*X61,{""color1"",""red"";""charttype"",""bar""; ""max"", 199999})"),"") | Z61: =IFERROR(__xludf.DUMMYFUNCTION("SPARKLINE(AB61*AC61,{""color1"",""green"";""charttype"",""bar""; ""max"", 199999})"),"") | AA61: =籌碼!A54 -> 法銀巴黎 | AB61: =籌碼!D54 -> -918 | AC61: =籌碼!E54 -> 2405.95
V62: =籌碼!F55 -> 新加坡商瑞銀 | W62: =籌碼!I55 -> 402 | X62: =籌碼!J55 -> 2414.16 | Y62: =IFERROR(__xludf.DUMMYFUNCTION("SPARKLINE(W62*X62,{""color1"",""red"";""charttype"",""bar""; ""max"", 199999})"),"") | Z62: =IFERROR(__xludf.DUMMYFUNCTION("SPARKLINE(AB62*AC62,{""color1"",""green"";""charttype"",""bar""; ""max"", 199999})"),"") | AA62: =籌碼!A55 -> 永豐金 | AB62: =籌碼!D55 -> -908 | AC62: =籌碼!E55 -> 2422.69
V63: =籌碼!F56 -> 群益金鼎-北高雄 | W63: =籌碼!I56 -> 203 | X63: =籌碼!J56 -> 2395.37 | Y63: =IFERROR(__xludf.DUMMYFUNCTION("SPARKLINE(W63*X63,{""color1"",""red"";""charttype"",""bar""; ""max"", 199999})"),"") | Z63: =IFERROR(__xludf.DUMMYFUNCTION("SPARKLINE(AB63*AC63,{""color1"",""green"";""charttype"",""bar""; ""max"", 199999})"),"") | AA63: =籌碼!A56 -> 元大 | AB63: =籌碼!D56 -> -841 | AC63: =籌碼!E56 -> 2416.38
A66: =TODAY() -> 46251 | B66: 上市成值排行 | D66: 上櫃成值排行 | F66: =TODAY() -> 46251 | G66: 上市週轉率排行 | J66: 上櫃週轉率排行 | S66: 標準差
A67: 1 | B67: =排行榜!B3 -> 2408 南亞科 | C67: =排行榜!G3 -> -0.0038910506 | D67: =排行榜!I3 -> 8299 群聯 | E67: =排行榜!N3 -> -0.087719298 | F67: 1 | G67: =排行榜!B56 -> 8039 台虹 | H67: =排行榜!H56 -> 0.092184369 | I67: =排行榜!G56 -> 0.2121 | J67: =排行榜!J56 -> 4541 晟田 | K67: =排行榜!P56 -> 0.017906336 | L67: =排行榜!O56 -> 0.2609 | S67: ='每股盈餘(EPS)'!E94 -> 5.8994905
A68: 2 | B68: =排行榜!B4 -> 2330 台積電 | C68: =排行榜!G4 -> -0.016427105 | D68: =排行榜!I4 -> 8358 金居 | E68: =排行榜!N4 -> 0.017814727 | F68: 2 | G68: =排行榜!B57 -> 6155 鈞寶 | H68: =排行榜!H57 -> 0.0031496063 | I68: =排行榜!G57 -> 0.1594 | J68: =排行榜!J57 -> 3441 聯一光 | K68: =排行榜!P57 -> -0.014117647 | L68: =排行榜!O57 -> 0.2524 | R68: 請手動排序(Z到A) | V68: ='每股盈餘(EPS)'!P2 -> 近1年EPS成長率 | W68: ='每股盈餘(EPS)'!Q2 -> 近3年平均EPS成長率 | X68: ='每股盈餘(EPS)'!R2 -> 近4年平均EPS成長率
A69: 3 | B69: =排行榜!B5 -> 2327 國巨* | C69: =排行榜!G5 -> -0.060422961 | D69: =排行榜!I5 -> 6488 環球晶 | E69: =排行榜!N5 -> -0.014634146 | F69: 3 | G69: =排行榜!B58 -> 2359 所羅門 | H69: =排行榜!H58 -> 0.015923567 | I69: =排行榜!G58 -> 0.1533 | J69: =排行榜!J58 -> 3490 單井 | K69: =排行榜!P58 -> 0.075983718 | L69: =排行榜!O58 -> 0.2318 | R69: 近年相對本益比 | T69: 預估股價 | V69: ='每股盈餘(EPS)'!P3 -> 0.60308373 | W69: ='每股盈餘(EPS)'!Q3 -> 0.43032525 | X69: ='每股盈餘(EPS)'!R3 -> 0.32522932
A70: 4 | B70: =排行榜!B6 -> 2454 聯發科 | C70: =排行榜!G6 -> -0.0035502959 | D70: =排行榜!I6 -> 6182 合晶 | E70: =排行榜!N6 -> -0.013274336 | F70: 4 | G70: =排行榜!B59 -> 6243 迅杰 | H70: =排行榜!H59 -> 0.066059226 | I70: =排行榜!G59 -> 0.1155 | J70: =排行榜!J59 -> 5475 德宏 | K70: =排行榜!P59 -> 0.04601227 | L70: =排行榜!O59 -> 0.219 | R70: ='每股盈餘(EPS)'!B45 -> 40.805856 | S70: 高本益比 | T70: ='每股盈餘(EPS)'!B46 -> 4003.4105 | V70: 本益比 | X70: 標準差倍數
A71: 5 | B71: =排行榜!B7 -> 2344 華邦電 | C71: =排行榜!G7 -> 0.036723164 | D71: =排行榜!I7 -> 3374 精材 | E71: =排行榜!N7 -> 0 | F71: 5 | G71: =排行榜!B60 -> 6770 力積電 | H71: =排行榜!H60 -> 0.046728972 | I71: =排行榜!G60 -> 0.1132 | J71: =排行榜!J60 -> 4939 亞電 | K71: =排行榜!P60 -> -0.039123631 | L71: =排行榜!O60 -> 0.2028 | R71: ='每股盈餘(EPS)'!C45 -> 34.906366 | T71: ='每股盈餘(EPS)'!C46 -> 3424.619 | V71: ='每股盈餘(EPS)'!H96 -> 40.805856 | W71: ='每股盈餘(EPS)'!H95 -> 3倍標準差
A72: 6 | B72: =排行榜!B8 -> 6770 力積電 | C72: =排行榜!G8 -> 0.046728972 | D72: =排行榜!I8 -> 6187 萬潤 | E72: =排行榜!N8 -> 0.0039370079 | F72: 6 | G72: =排行榜!B61 -> 3605 宏致 | H72: =排行榜!H61 -> -0.0037878788 | I72: =排行榜!G61 -> 0.1077 | J72: =排行榜!J61 -> 6182 合晶 | K72: =排行榜!P61 -> -0.013274336 | L72: =排行榜!O61 -> 0.198 | R72: ='每股盈餘(EPS)'!D45 -> 29.006875 | T72: ='每股盈餘(EPS)'!D46 -> 2845.8275 | V72: ='每股盈餘(EPS)'!G96 -> 34.906366 | W72: ='每股盈餘(EPS)'!G95 -> 2倍標準差
A73: 7 | B73: =排行榜!B9 -> 1303 南亞 | C73: =排行榜!G9 -> 0.097883598 | D73: =排行榜!I9 -> 6274 台燿 | E73: =排行榜!N9 -> 0.046875 | F73: 7 | G73: =排行榜!B62 -> 2375 凱美 | H73: =排行榜!H62 -> -0.064516129 | I73: =排行榜!G62 -> 0.1062 | J73: =排行榜!J62 -> 8358 金居 | K73: =排行榜!P62 -> 0.017814727 | L73: =排行榜!O62 -> 0.1787 | R73: ='每股盈餘(EPS)'!E45 -> 23.107385 | S73: 中位數本益比 | T73: ='每股盈餘(EPS)'!E46 -> 2267.036 | V73: ='每股盈餘(EPS)'!F96 -> 29.006875 | W73: ='每股盈餘(EPS)'!F95 -> 1倍標準差
A74: 8 | B74: =排行榜!B10 -> 4958 臻鼎-KY | C74: =排行榜!G10 -> 0.02513089 | D74: =排行榜!I10 -> 3105 穩懋 | E74: =排行榜!N10 -> -0.023255814 | F74: 8 | G74: =排行榜!B63 -> 8261 富鼎 | H74: =排行榜!H63 -> -0.084158416 | I74: =排行榜!G63 -> 0.1029 | J74: =排行榜!J63 -> 6538 倉和 | K74: =排行榜!P63 -> 0.036619718 | L74: =排行榜!O63 -> 0.1493 | R74: ='每股盈餘(EPS)'!J45 -> 27.758461 | S74: 目前本益比 | T74: ='每股盈餘(EPS)'!J46 -> 2723.3472 | V74: ='每股盈餘(EPS)'!J96 -> 24.411692 | W74: ='每股盈餘(EPS)'!J95 -> 預估本益比 | X74: ='每股盈餘(EPS)'!J99 -> 0.2210882
A75: 9 | B75: =排行榜!B11 -> 8046 南電 | C75: =排行榜!G11 -> 0.074074074 | D75: =排行榜!I11 -> 5274 信驊 | E75: =排行榜!N11 -> 0.011435106 | F75: 9 | G75: =排行榜!B64 -> 8033 雷虎 | H75: =排行榜!H64 -> 0.098092643 | I75: =排行榜!G64 -> 0.1026 | J75: =排行榜!J64 -> 00989B台新美國非投等債 | K75: =排行榜!P64 -> -0.0019417476 | L75: =排行榜!O64 -> 0.1295 | R75: ='每股盈餘(EPS)'!K45 -> 24.411692 | S75: 預估本益比 | T75: ='每股盈餘(EPS)'!K46 -> 2395 | V75: ='每股盈餘(EPS)'!I96 -> 27.758461 | W75: ='每股盈餘(EPS)'!I95 -> 目前本益比 | X75: ='每股盈餘(EPS)'!I99 -> 0.78838608
A76: 10 | B76: =排行榜!B12 -> 2308 台達電 | C76: =排行榜!G12 -> 0 | D76: =排行榜!I12 -> 5483 中美晶 | E76: =排行榜!N12 -> 0.0026666667 | F76: 10 | G76: =排行榜!B65 -> 2492 華新科 | H76: =排行榜!H65 -> -0.044233807 | I76: =排行榜!G65 -> 0.1017 | J76: =排行榜!J65 -> 00859B群益0-1年美債 | K76: =排行榜!P65 -> -0.0045761079 | L76: =排行榜!O65 -> 0.1281 | R76: ='每股盈餘(EPS)'!F45 -> 17.207894 | T76: ='每股盈餘(EPS)'!F46 -> 1688.2445 | V76: ='每股盈餘(EPS)'!E96 -> 23.107385 | W76: 平均本益比 | X76: 0
A77: 11 | B77: =排行榜!B13 -> 3017 奇鋐 | C77: =排行榜!G13 -> 0.0109375 | D77: =排行榜!I13 -> 5475 德宏 | E77: =排行榜!N13 -> 0.04601227 | F77: 11 | G77: =排行榜!B66 -> 00657K國泰日經225+U | H77: =排行榜!H66 -> 0.0019762846 | I77: =排行榜!G66 -> 0.1 | J77: =排行榜!J66 -> 6265 方土昶 | K77: =排行榜!P66 -> 0.061120543 | L77: =排行榜!O66 -> 0.1267 | R77: ='每股盈餘(EPS)'!G45 -> 11.308404 | T77: ='每股盈餘(EPS)'!G46 -> 1109.453 | V77: ='每股盈餘(EPS)'!D96 -> 17.207894 | W77: ='每股盈餘(EPS)'!D95 -> -1倍標準差
A78: 12 | B78: =排行榜!B14 -> 3231 緯創 | C78: =排行榜!G14 -> -0.017766497 | D78: =排行榜!I14 -> 5289 宜鼎 | E78: =排行榜!N14 -> -0.039087948 | F78: 12 | G78: =排行榜!B67 -> 2465 麗臺 | H78: =排行榜!H67 -> -0.086666667 | I78: =排行榜!G67 -> 0.0946 | J78: =排行榜!J67 -> 00847B中信美國市政債 | K78: =排行榜!P67 -> -0.0047524752 | L78: =排行榜!O67 -> 0.1215 | R78: ='每股盈餘(EPS)'!H45 -> 5.408913 | S78: 低本益比 | T78: ='每股盈餘(EPS)'!H46 -> 530.66156 | V78: ='每股盈餘(EPS)'!C96 -> 11.308404 | W78: ='每股盈餘(EPS)'!C95 -> -2倍標準差
A79: 13 | B79: =排行榜!B15 -> 2383 台光電 | C79: =排行榜!G15 -> 0.083479789 | D79: =排行榜!I15 -> 3260 威剛 | E79: =排行榜!N15 -> -0.017114914 | F79: 13 | G79: =排行榜!B68 -> 2324 仁寶 | H79: =排行榜!H68 -> 0.099236641 | I79: =排行榜!G68 -> 0.0913 | J79: =排行榜!J68 -> 6173 信昌電 | K79: =排行榜!P68 -> -0.060402685 | L79: =排行榜!O68 -> 0.1116 | V79: ='每股盈餘(EPS)'!B96 -> 5.408913 | W79: ='每股盈餘(EPS)'!B95 -> -3倍標準差
A80: 14 | B80: =排行榜!B16 -> 2324 仁寶 | C80: =排行榜!G16 -> 0.099236641 | D80: =排行榜!I16 -> 6173 信昌電 | E80: =排行榜!N16 -> -0.060402685 | F80: 14 | G80: =排行榜!B69 -> 2634 漢翔 | H80: =排行榜!H69 -> 0.099688474 | I80: =排行榜!G69 -> 0.0843 | J80: =排行榜!J69 -> 3498 陽程 | K80: =排行榜!P69 -> 0.097222222 | L80: =排行榜!O69 -> 0.1033
A81: 15 | B81: =排行榜!B17 -> 6669 緯穎 | C81: =排行榜!G17 -> 0.060131796 | D81: =排行榜!I17 -> 5347 世界 | E81: =排行榜!N17 -> -0.015337423 | F81: 15 | G81: =排行榜!B70 -> 2484 希華 | H81: =排行榜!H70 -> -0.040843215 | I81: =排行榜!G70 -> 0.0836 | J81: =排行榜!J70 -> 3624 光頡 | K81: =排行榜!P70 -> -0.058885384 | L81: =排行榜!O70 -> 0.0959
A82: 16 | B82: =排行榜!B18 -> 2357 華碩 | C82: =排行榜!G18 -> 0.062966916 | D82: =排行榜!I18 -> 3081 聯亞 | E82: =排行榜!N18 -> -0.046904315 | F82: 16 | G82: =排行榜!B71 -> 00686R群益臺灣加權反1 | H82: =排行榜!H71 -> 0 | I82: =排行榜!G71 -> 0.0834 | J82: =排行榜!J71 -> 5371 中光電 | K82: =排行榜!P71 -> 0.044032445 | L82: =排行榜!O71 -> 0.0942
A83: 17 | B83: =排行榜!B19 -> 3661 世芯-KY | C83: =排行榜!G19 -> 0.0047732697 | D83: =排行榜!I19 -> 3491 昇達科 | E83: =排行榜!N19 -> 0.022304833 | F83: 17 | G83: =排行榜!B72 -> 00961 FT臺灣永續高息 | H83: =排行榜!H72 -> 0.0097670924 | I83: =排行榜!G72 -> 0.0815 | J83: =排行榜!J72 -> 5328 華容 | K83: =排行榜!P72 -> -0.023255814 | L83: =排行榜!O72 -> 0.0866
A84: 18 | B84: =排行榜!B20 -> 2492 華新科 | C84: =排行榜!G20 -> -0.044233807 | D84: =排行榜!I20 -> 6147 頎邦 | E84: =排行榜!N20 -> -0.042553191 | F84: 18 | G84: =排行榜!B73 -> 1810 和成 | H84: =排行榜!H73 -> 0.099800399 | I84: =排行榜!G73 -> 0.0805 | J84: =排行榜!J73 -> 2061 風青 | K84: =排行榜!P73 -> -0.09946714 | L84: =排行榜!O73 -> 0.0846
A85: 19 | B85: =排行榜!B21 -> 3443 創意 | C85: =排行榜!G21 -> -0.013537906 | D85: =排行榜!I21 -> 5371 中光電 | E85: =排行榜!N21 -> 0.044032445 | F85: 19 | G85: =排行榜!B74 -> 6672 騰輝電子-KY | H85: =排行榜!H74 -> 0.020793951 | I85: =排行榜!G74 -> 0.0771 | J85: =排行榜!J74 -> 8299 群聯 | K85: =排行榜!P74 -> -0.087719298 | L85: =排行榜!O74 -> 0.0752
A86: 20 | B86: =排行榜!B22 -> 8039 台虹 | C86: =排行榜!G22 -> 0.092184369 | D86: =排行榜!I22 -> 8069 元太 | E86: =排行榜!N22 -> -0.032163743 | F86: 20 | G86: =排行榜!B75 -> 00668 國泰美國道瓊 | H86: =排行榜!H75 -> -0.0015847861 | I86: =排行榜!G75 -> 0.075 | J86: =排行榜!J75 -> 6840 東研信超 | K86: =排行榜!P75 -> 0.071428571 | L86: =排行榜!O75 -> 0.0751 | S86: =股票資訊!C8 -> 每股淨值(元)
A87: 21 | B87: =排行榜!B23 -> 2382 廣達 | C87: =排行榜!G23 -> 0.0076923077 | D87: =排行榜!I23 -> 6223 旺矽 | E87: =排行榜!N23 -> -0.0084680523 | F87: 21 | G87: =排行榜!B76 -> 8222 寶一 | H87: =排行榜!H76 -> 0.044247788 | I87: =排行榜!G76 -> 0.0715 | J87: =排行榜!J76 -> 6727 亞泰金屬 | K87: =排行榜!P76 -> 0.099236641 | L87: =排行榜!O76 -> 0.0724 | S87: =股票資訊!D8 -> 249.67
A88: 22 | B88: =排行榜!B24 -> 2303 聯電 | C88: =排行榜!G24 -> -0.02811245 | D88: =排行榜!I24 -> 3211 順達 | E88: =排行榜!N24 -> -0.038130381 | F88: 22 | G88: =排行榜!B77 -> 6753 龍德造船 | H88: =排行榜!H77 -> 0.097222222 | I88: =排行榜!G77 -> 0.0695 | J88: =排行榜!J77 -> 009825聯邦美國金融創新 | K88: =排行榜!P77 -> 0.013861386 | L88: =排行榜!O77 -> 0.0687
A89: 23 | B89: =排行榜!B25 -> 2317 鴻海 | C89: =排行榜!G25 -> -0.0095419847 | D89: =排行榜!I25 -> 3529 力旺 | E89: =排行榜!N25 -> -0.016666667 | F89: 23 | G89: =排行榜!B78 -> 8271 宇瞻 | H89: =排行榜!H78 -> 0.015250545 | I89: =排行榜!G78 -> 0.0686 | J89: =排行榜!J78 -> 6716 應廣 | K89: =排行榜!P78 -> 0.05106383 | L89: =排行榜!O78 -> 0.0687
A90: 24 | B90: =排行榜!B26 -> 2337 旺宏 | C90: =排行榜!G26 -> 0.0036630037 | D90: =排行榜!I26 -> 6510 精測 | E90: =排行榜!N26 -> 0.060283688 | F90: 24 | G90: =排行榜!B79 -> 4989 榮科 | H90: =排行榜!H79 -> -0.064935065 | I90: =排行榜!G79 -> 0.0675 | J90: =排行榜!J79 -> 3374 精材 | K90: =排行榜!P79 -> 0 | L90: =排行榜!O79 -> 0.0683
A91: 25 | B91: =排行榜!B27 -> 3481 群創 | C91: =排行榜!G27 -> 0.01417004 | D91: =排行榜!I27 -> 3324 雙鴻 | E91: =排行榜!N27 -> -0.024154589 | F91: 25 | G91: =排行榜!B80 -> 8996 高力 | H91: =排行榜!H80 -> -0.0038910506 | I91: =排行榜!G80 -> 0.0663 | J91: =排行榜!J80 -> 3287 廣寰科 | K91: =排行榜!P80 -> 0.050420168 | L91: =排行榜!O80 -> 0.0641
A92: 26 | B92: =排行榜!B28 -> 3711 日月光投控 | C92: =排行榜!G28 -> -0.015974441 | D92: =排行榜!I28 -> 4979 華星光 | E92: =排行榜!N28 -> -0.074468085 | F92: 26 | G92: =排行榜!B81 -> 2399 映泰 | H92: =排行榜!H81 -> 0.03490991 | I92: =排行榜!G81 -> 0.0643 | J92: =排行榜!J81 -> 6432 今展科 | K92: =排行榜!P81 -> -0.079487179 | L92: =排行榜!O81 -> 0.0628
A93: 27 | B93: =排行榜!B29 -> 3037 欣興 | C93: =排行榜!G29 -> 0.02 | D93: =排行榜!I29 -> 6584 南俊國際 | E93: =排行榜!N29 -> 0.013400335 | F93: 27 | G93: =排行榜!B82 -> 4916 事欣科 | H93: =排行榜!H82 -> 0.044334975 | I93: =排行榜!G82 -> 0.0619 | J93: =排行榜!J82 -> 7584 樂意 | K93: =排行榜!P82 -> 0.0094339623 | L93: =排行榜!O82 -> 0.0618
A94: 28 | B94: =排行榜!B30 -> 2368 金像電 | C94: =排行榜!G30 -> 0.004950495 | D94: =排行榜!I30 -> 6683 雍智科技 | E94: =排行榜!N30 -> -0.017921147 | F94: 28 | G94: =排行榜!B83 -> 00632R元大台灣50反1 | H94: =排行榜!H83 -> 0.0060301508 | I94: =排行榜!G83 -> 0.06 | J94: =排行榜!J83 -> 4127 天良 | K94: =排行榜!P83 -> 0.0036144578 | L94: =排行榜!O83 -> 0.0617
A95: 29 | B95: =排行榜!B31 -> 00981A主動統一台股增長 | C95: =排行榜!G31 -> 0.009015025 | D95: =排行榜!I31 -> 3363 上詮 | E95: =排行榜!N31 -> -0.023333333 | F95: 29 | G95: =排行榜!B84 -> 00984D主動聯博全球非投 | H95: =排行榜!H84 -> -0.002955665 | I95: =排行榜!G84 -> 0.0586 | J95: =排行榜!J84 -> 00860B群益1-5Y投資級債 | K95: =排行榜!P84 -> -0.0041269022 | L95: =排行榜!O84 -> 0.0588
A96: 30 | B96: =排行榜!B32 -> 0050 元大台灣50 | C96: =排行榜!G32 -> -0.0028116214 | D96: =排行榜!I32 -> 5351 鈺創 | E96: =排行榜!N32 -> 0.031007752 | F96: 30 | G96: =排行榜!B85 -> 00715L期街口布蘭特正2 | H96: =排行榜!H85 -> -0.03440367 | I96: =排行榜!G85 -> 0.0575 | J96: =排行榜!J85 -> 4760 勤凱 | K96: =排行榜!P85 -> -0.077738516 | L96: =排行榜!O85 -> 0.0572 | V96: 近一季稅後 | Y96: 填息率
A97: 31 | B97: =排行榜!B33 -> 3008 大立光 | C97: =排行榜!G33 -> -0.010729614 | D97: =排行榜!I33 -> 3131 弘塑 | E97: =排行榜!N33 -> -0.037950664 | F97: 31 | G97: =排行榜!B86 -> 8150 南茂 | H97: =排行榜!H86 -> -0.010764263 | I97: =排行榜!G86 -> 0.0568 | J97: =排行榜!J86 -> 3693 營邦 | K97: =排行榜!P86 -> -0.028985507 | L97: =排行榜!O86 -> 0.0557 | Y97: 毛利率年
A98: 32 | B98: =排行榜!B34 -> 3533 嘉澤 | C98: =排行榜!G34 -> -0.049723757 | D98: =排行榜!I34 -> 3264 欣銓 | E98: =排行榜!N34 -> -0.021691974 | F98: 32 | G98: =排行榜!B87 -> 4958 臻鼎-KY | H98: =排行榜!H87 -> 0.02513089 | I98: =排行榜!G87 -> 0.0565 | J98: =排行榜!J87 -> 8096 擎亞 | K98: =排行榜!P87 -> -0.071713147 | L98: =排行榜!O87 -> 0.0554 | Y98: 盈利率年
A99: 33 | B99: =排行榜!B35 -> 8996 高力 | C99: =排行榜!G35 -> -0.0038910506 | D99: =排行榜!I35 -> 3693 營邦 | E99: =排行榜!N35 -> -0.028985507 | F99: 33 | G99: =排行榜!B88 -> 00643K群益深証中小+R | H99: =排行榜!H88 -> -0.0073891626 | I99: =排行榜!G88 -> 0.0558 | J99: =排行榜!J88 -> 00988B玉山嚴選非投債 | K99: =排行榜!P88 -> -0.001002004 | L99: =排行榜!O88 -> 0.0535 | Y99: 長短期
A100: 34 | B100: =排行榜!B36 -> 2345 智邦 | C100: =排行榜!G36 -> 0.013215859 | D100: =排行榜!I36 -> 4541 晟田 | E100: =排行榜!N36 -> 0.017906336 | F100: 34 | G100: =排行榜!B89 -> 00676R富邦臺灣加權反1 | H100: =排行榜!H89 -> 0.0054545455 | I100: =排行榜!G89 -> 0.0549 | J100: =排行榜!J89 -> 5439 高技 | K100: =排行榜!P89 -> -0.012 | L100: =排行榜!O89 -> 0.0525 | Y100: 進四記營業利益 年
A101: 35 | B101: =排行榜!B37 -> 00631L元大台灣50正2 | C101: =排行榜!G37 -> -0.01653348 | D101: =排行榜!I37 -> 5904 寶雅* | E101: =排行榜!N37 -> -0.034229829 | F101: 35 | G101: =排行榜!B90 -> 4967 十銓 | H101: =排行榜!H90 -> -0.019607843 | I101: =排行榜!G90 -> 0.0548 | J101: =排行榜!J90 -> 8383 千附 | K101: =排行榜!P90 -> 0.060734463 | L101: =排行榜!O90 -> 0.0523 | Y101: 股息增
A102: 36 | B102: =排行榜!B38 -> 3653 健策 | C102: =排行榜!G38 -> 0.047464941 | D102: =排行榜!I38 -> 4939 亞電 | E102: =排行榜!N38 -> -0.039123631 | F102: 36 | G102: =排行榜!B91 -> 2483 百容 | H102: =排行榜!H91 -> -0.048689139 | I102: =排行榜!G91 -> 0.0541 | J102: =排行榜!J91 -> 4510 高鋒 | K102: =排行榜!P91 -> 0.016411379 | L102: =排行榜!O91 -> 0.0522
A103: 37 | B103: =排行榜!B39 -> 6446 藥華藥 | C103: =排行榜!G39 -> 0.038062284 | D103: =排行榜!I39 -> 5439 高技 | E103: =排行榜!N39 -> -0.012 | F103: 37 | G103: =排行榜!B92 -> 2344 華邦電 | H103: =排行榜!H92 -> 0.036723164 | I103: =排行榜!G92 -> 0.0536 | J103: =排行榜!J92 -> 6419 京晨科 | K103: =排行榜!P92 -> 0.0029850746 | L103: =排行榜!O92 -> 0.0515
...

Sheet 股票資訊
A1: =IFERROR(__xludf.DUMMYFUNCTION("IMPORTHTML(SUBSTITUTE(""https://fubon-ebrokerdj.fbs.com.tw/z/zc/zca/zca_股票代碼.djhtm"", ""股票代碼"",'股價預估'!E1),""table"",0)"),"台積電 (2330) 基本資料 最近交易日:08/14 市值單位:百萬") -> 台積電 (2330) 基本資料 最近交易日:08/14 市值單位:百萬
A2: =IFERROR(__xludf.DUMMYFUNCTION("""COMPUTED_VALUE"""),"開盤價") -> 開盤價 | B2: =IFERROR(__xludf.DUMMYFUNCTION("""COMPUTED_VALUE"""),2435) -> 2435 | C2: =IFERROR(__xludf.DUMMYFUNCTION("""COMPUTED_VALUE"""),"最高價") -> 最高價 | D2: =IFERROR(__xludf.DUMMYFUNCTION("""COMPUTED_VALUE"""),2440) -> 2440 | E2: =IFERROR(__xludf.DUMMYFUNCTION("""COMPUTED_VALUE"""),"最低價") -> 最低價 | F2: =IFERROR(__xludf.DUMMYFUNCTION("""COMPUTED_VALUE"""),2395) -> 2395 | G2: =IFERROR(__xludf.DUMMYFUNCTION("""COMPUTED_VALUE"""),"收盤價") -> 收盤價 | H2: =IFERROR(__xludf.DUMMYFUNCTION("""COMPUTED_VALUE"""),2395) -> 2395 | J2: 財報發布 | K2: 日期 | L2: 剩餘天數
A3: =IFERROR(__xludf.DUMMYFUNCTION("""COMPUTED_VALUE"""),"漲跌") -> 漲跌 | B3: =IFERROR(__xludf.DUMMYFUNCTION("""COMPUTED_VALUE"""),-40) -> -40 | C3: =IFERROR(__xludf.DUMMYFUNCTION("""COMPUTED_VALUE"""),"一年內最高價") -> 一年內最高價 | D3: =IFERROR(__xludf.DUMMYFUNCTION("""COMPUTED_VALUE"""),2535) -> 2535 | E3: =IFERROR(__xludf.DUMMYFUNCTION("""COMPUTED_VALUE"""),"一年內最低價") -> 一年內最低價 | F3: =IFERROR(__xludf.DUMMYFUNCTION("""COMPUTED_VALUE"""),1135) -> 1135 | J3: 第1季 | K3: =DATE(YEAR(TODAY()),5,15) -> 46157 | L3: =IF(NETWORKDAYS.INTL(TODAY(),K3)<0,"",NETWORKDAYS.INTL(TODAY(),K3))
A4: =IFERROR(__xludf.DUMMYFUNCTION("""COMPUTED_VALUE"""),"本益比") -> 本益比 | B4: =IFERROR(__xludf.DUMMYFUNCTION("""COMPUTED_VALUE"""),27.76) -> 27.76 | C4: =IFERROR(__xludf.DUMMYFUNCTION("""COMPUTED_VALUE"""),"一年內最大量") -> 一年內最大量 | D4: =IFERROR(__xludf.DUMMYFUNCTION("""COMPUTED_VALUE"""),104784) -> 104784 | E4: =IFERROR(__xludf.DUMMYFUNCTION("""COMPUTED_VALUE"""),"一年內最低量") -> 一年內最低量 | F4: =IFERROR(__xludf.DUMMYFUNCTION("""COMPUTED_VALUE"""),13707) -> 13707 | G4: =IFERROR(__xludf.DUMMYFUNCTION("""COMPUTED_VALUE"""),"成交量") -> 成交量 | H4: =IFERROR(__xludf.DUMMYFUNCTION("""COMPUTED_VALUE"""),21163) -> 21163 | J4: 第2季 | K4: =DATE(YEAR(TODAY()),8,14) -> 46248 | L4: =IF(NETWORKDAYS.INTL(TODAY(),K4)<0,"",NETWORKDAYS.INTL(TODAY(),K4))
A5: =IFERROR(__xludf.DUMMYFUNCTION("""COMPUTED_VALUE"""),"同業平均本益比") -> 同業平均本益比 | B5: =IFERROR(__xludf.DUMMYFUNCTION("""COMPUTED_VALUE"""),44.7) -> 44.7 | C5: =IFERROR(__xludf.DUMMYFUNCTION("""COMPUTED_VALUE"""),"一年來最高本益比") -> 一年來最高本益比 | D5: =IFERROR(__xludf.DUMMYFUNCTION("""COMPUTED_VALUE"""),34.87) -> 34.87 | E5: =IFERROR(__xludf.DUMMYFUNCTION("""COMPUTED_VALUE"""),"一年來最低本益比") -> 一年來最低本益比 | F5: =IFERROR(__xludf.DUMMYFUNCTION("""COMPUTED_VALUE"""),20.16) -> 20.16 | G5: =IFERROR(__xludf.DUMMYFUNCTION("""COMPUTED_VALUE"""),"盤後量") -> 盤後量 | H5: =IFERROR(__xludf.DUMMYFUNCTION("""COMPUTED_VALUE"""),2238) -> 2238 | J5: 第3季 | K5: =DATE(YEAR(TODAY()),11,14) -> 46340 | L5: =IF(NETWORKDAYS.INTL(TODAY(),K5)<0,"",NETWORKDAYS.INTL(TODAY(),K5)) -> 65
A6: =IFERROR(__xludf.DUMMYFUNCTION("""COMPUTED_VALUE"""),"殖利率") -> 殖利率 | B6: =IFERROR(__xludf.DUMMYFUNCTION("""COMPUTED_VALUE"""),0.0092) -> 0.0092 | C6: =IFERROR(__xludf.DUMMYFUNCTION("""COMPUTED_VALUE"""),"總市值") -> 總市值 | D6: =IFERROR(__xludf.DUMMYFUNCTION("""COMPUTED_VALUE"""),62108026) -> 62108026 | E6: =IFERROR(__xludf.DUMMYFUNCTION("""COMPUTED_VALUE"""),"85年來最高總市值") -> 85年來最高總市值 | F6: =IFERROR(__xludf.DUMMYFUNCTION("""COMPUTED_VALUE"""),65090249) -> 65090249 | G6: =IFERROR(__xludf.DUMMYFUNCTION("""COMPUTED_VALUE"""),"85年來最低總市值") -> 85年來最低總市值 | H6: =IFERROR(__xludf.DUMMYFUNCTION("""COMPUTED_VALUE"""),92816) -> 92816 | J6: 第4季 | K6: =IF(MONTH(TODAY())=12,DATE(YEAR(TODAY())+1,3, 31),DATE(YEAR(TODAY()),3, 31)) -> 46112 | L6: =IF(NETWORKDAYS.INTL(TODAY(),K6)<0,"",NETWORKDAYS.INTL(TODAY(),K6))
A7: =IFERROR(__xludf.DUMMYFUNCTION("""COMPUTED_VALUE"""),"投資報酬率(08/14)") -> 投資報酬率(08/14) | C7: =IFERROR(__xludf.DUMMYFUNCTION("""COMPUTED_VALUE"""),"財務比例(115.2Q)") -> 財務比例(115.2Q) | E7: =IFERROR(__xludf.DUMMYFUNCTION("""COMPUTED_VALUE"""),"獲利能力(115.2Q)") -> 獲利能力(115.2Q) | G7: =IFERROR(__xludf.DUMMYFUNCTION("""COMPUTED_VALUE"""),"投資風險(08/14)") -> 投資風險(08/14) | L7: =MIN(L3:L6) -> 65
A8: =IFERROR(__xludf.DUMMYFUNCTION("""COMPUTED_VALUE"""),"今年以來") -> 今年以來 | B8: =IFERROR(__xludf.DUMMYFUNCTION("""COMPUTED_VALUE"""),0.5803) -> 0.5803 | C8: =IFERROR(__xludf.DUMMYFUNCTION("""COMPUTED_VALUE"""),"每股淨值(元)") -> 每股淨值(元) | D8: =ROUND(財報健檢!B36,2) -> 249.67 | E8: =IFERROR(__xludf.DUMMYFUNCTION("""COMPUTED_VALUE"""),"營業毛利率") -> 營業毛利率 | F8: =IFERROR(__xludf.DUMMYFUNCTION("""COMPUTED_VALUE"""),0.6772) -> 0.6772 | G8: =IFERROR(__xludf.DUMMYFUNCTION("""COMPUTED_VALUE"""),"貝他值") -> 貝他值 | H8: =IFERROR(__xludf.DUMMYFUNCTION("""COMPUTED_VALUE"""),1.1) -> 1.1 | J8: 營收發布 | K8: =IF(MONTH(TODAY())=12,IF(DAY(TODAY())>10,DATE(YEAR(TODAY())+1, 1, 10),DATE(YEAR(TODAY()), 12, 10)),IF(DAY(TODAY())<10, DATE(YEAR(TODAY()), MONTH(TODAY()), 10),DATE(YEAR(TODAY()), MONTH(TODAY())+1, 10))) -> 46275 | L8: =IF(MONTH(TODAY())=12,IF(DAY(TODAY())>10,NETWORKDAYS.INTL(TODAY(), DATE(YEAR(TODAY())+1, 1, 10)),NETWORKDAYS.INTL(TODAY(), DATE(YEAR(TODAY()), 12, 10))),IF(DAY(TODAY())<10,NETWORKDAYS.INTL(TODAY(), DATE(YEAR(TODAY()), MONTH(TODAY()), 10)),NETWORKDAYS.INTL(TODAY(), DATE(YEAR(TODAY()), MONTH(TODAY())+1, 10)))) -> 19
A9: =IFERROR(__xludf.DUMMYFUNCTION("""COMPUTED_VALUE"""),"最近一週") -> 最近一週 | B9: =IFERROR(__xludf.DUMMYFUNCTION("""COMPUTED_VALUE"""),0.0274) -> 0.0274 | C9: =IFERROR(__xludf.DUMMYFUNCTION("""COMPUTED_VALUE"""),"每人營收(仟元)") -> 每人營收(仟元) | D9: =IFERROR(__xludf.DUMMYFUNCTION("""COMPUTED_VALUE"""),13906) -> 13906 | E9: =IFERROR(__xludf.DUMMYFUNCTION("""COMPUTED_VALUE"""),"營業利益率") -> 營業利益率 | F9: =IFERROR(__xludf.DUMMYFUNCTION("""COMPUTED_VALUE"""),0.6034) -> 0.6034 | G9: =IFERROR(__xludf.DUMMYFUNCTION("""COMPUTED_VALUE"""),"標準差") -> 標準差 | H9: =IFERROR(__xludf.DUMMYFUNCTION("""COMPUTED_VALUE"""),0.0208) -> 0.0208
A10: =IFERROR(__xludf.DUMMYFUNCTION("""COMPUTED_VALUE"""),"最近一個月") -> 最近一個月 | B10: =IFERROR(__xludf.DUMMYFUNCTION("""COMPUTED_VALUE"""),0.0062) -> 0.0062 | C10: =IFERROR(__xludf.DUMMYFUNCTION("""COMPUTED_VALUE"""),"每股營收(元)") -> 每股營收(元) | D10: =IFERROR(__xludf.DUMMYFUNCTION("""COMPUTED_VALUE"""),48.99) -> 48.99 | E10: =IFERROR(__xludf.DUMMYFUNCTION("""COMPUTED_VALUE"""),"稅前淨利率") -> 稅前淨利率 | F10: =IFERROR(__xludf.DUMMYFUNCTION("""COMPUTED_VALUE"""),0.6789) -> 0.6789
A11: =IFERROR(__xludf.DUMMYFUNCTION("""COMPUTED_VALUE"""),"最近二個月") -> 最近二個月 | B11: =IFERROR(__xludf.DUMMYFUNCTION("""COMPUTED_VALUE"""),0.0541) -> 0.0541 | C11: =IFERROR(__xludf.DUMMYFUNCTION("""COMPUTED_VALUE"""),"負債比例") -> 負債比例 | D11: =IFERROR(__xludf.DUMMYFUNCTION("""COMPUTED_VALUE"""),0.3094) -> 0.3094 | E11: =IFERROR(__xludf.DUMMYFUNCTION("""COMPUTED_VALUE"""),"資產報酬率") -> 資產報酬率 | F11: =IFERROR(__xludf.DUMMYFUNCTION("""COMPUTED_VALUE"""),0.0786) -> 0.0786
A12: =IFERROR(__xludf.DUMMYFUNCTION("""COMPUTED_VALUE"""),"最近三個月") -> 最近三個月 | B12: =IFERROR(__xludf.DUMMYFUNCTION("""COMPUTED_VALUE"""),0.0755) -> 0.0755 | C12: =IFERROR(__xludf.DUMMYFUNCTION("""COMPUTED_VALUE"""),"股價淨值比") -> 股價淨值比 | D12: =ROUND(財報健檢!B37,2) -> 9.59 | E12: =IFERROR(__xludf.DUMMYFUNCTION("""COMPUTED_VALUE"""),"股東權益報酬率") -> 股東權益報酬率 | F12: =IFERROR(__xludf.DUMMYFUNCTION("""COMPUTED_VALUE"""),0.1139) -> 0.1139
A13: =IFERROR(__xludf.DUMMYFUNCTION("""COMPUTED_VALUE"""),"基本資料") -> 基本資料 | C13: =IFERROR(__xludf.DUMMYFUNCTION("""COMPUTED_VALUE"""),"配股配息(115[累計至 第二季])") -> 配股配息(115[累計至 第二季])
A14: =IFERROR(__xludf.DUMMYFUNCTION("""COMPUTED_VALUE"""),"股本(億, 台幣)") -> 股本(億, 台幣) | B14: =IFERROR(__xludf.DUMMYFUNCTION("""COMPUTED_VALUE"""),2593.24) -> 2593.24 | C14: =IFERROR(__xludf.DUMMYFUNCTION("""COMPUTED_VALUE"""),"現金股利(元)") -> 現金股利(元) | D14: =IFERROR(__xludf.DUMMYFUNCTION("""COMPUTED_VALUE"""),14) -> 14
A15: =IFERROR(__xludf.DUMMYFUNCTION("""COMPUTED_VALUE"""),"成立時間") -> 成立時間 | B15: =IFERROR(__xludf.DUMMYFUNCTION("""COMPUTED_VALUE"""),27811) -> 27811 | C15: =IFERROR(__xludf.DUMMYFUNCTION("""COMPUTED_VALUE"""),"股票股利") -> 股票股利 | D15: =IFERROR(__xludf.DUMMYFUNCTION("""COMPUTED_VALUE"""),0) -> 0
A16: =IFERROR(__xludf.DUMMYFUNCTION("""COMPUTED_VALUE"""),"初次上市(櫃)日期") -> 初次上市(櫃)日期 | B16: =IFERROR(__xludf.DUMMYFUNCTION("""COMPUTED_VALUE"""),30564) -> 30564 | C16: =IFERROR(__xludf.DUMMYFUNCTION("""COMPUTED_VALUE"""),"盈餘配股") -> 盈餘配股 | D16: =IFERROR(__xludf.DUMMYFUNCTION("""COMPUTED_VALUE"""),0) -> 0
A17: =IFERROR(__xludf.DUMMYFUNCTION("""COMPUTED_VALUE"""),"股務代理") -> 股務代理 | B17: =IFERROR(__xludf.DUMMYFUNCTION("""COMPUTED_VALUE"""),"中信託 02-66365566") -> 中信託 02-66365566 | C17: =IFERROR(__xludf.DUMMYFUNCTION("""COMPUTED_VALUE"""),"公積配股") -> 公積配股 | D17: =IFERROR(__xludf.DUMMYFUNCTION("""COMPUTED_VALUE"""),0) -> 0
A18: =IFERROR(__xludf.DUMMYFUNCTION("""COMPUTED_VALUE"""),"董事長") -> 董事長 | B18: =IFERROR(__xludf.DUMMYFUNCTION("""COMPUTED_VALUE"""),"魏哲家") -> 魏哲家
A19: =IFERROR(__xludf.DUMMYFUNCTION("""COMPUTED_VALUE"""),"總經理") -> 總經理 | B19: =IFERROR(__xludf.DUMMYFUNCTION("""COMPUTED_VALUE"""),"魏哲家") -> 魏哲家
A20: =IFERROR(__xludf.DUMMYFUNCTION("""COMPUTED_VALUE"""),"發言人") -> 發言人 | B20: =IFERROR(__xludf.DUMMYFUNCTION("""COMPUTED_VALUE"""),"黃仁昭") -> 黃仁昭
A21: =IFERROR(__xludf.DUMMYFUNCTION("""COMPUTED_VALUE"""),"營收比重") -> 營收比重 | B21: =IFERROR(__xludf.DUMMYFUNCTION("""COMPUTED_VALUE"""),"晶圓-5奈米30.98%、晶圓-3奈米20.85%、其他14.08%、晶圓-7奈米12.06%、晶圓-28奈米5.91%、晶圓-16奈米5.66%、晶圓-65奈米3.16%、晶圓-40及45奈米2.51%、晶圓-0.15及0.18微米2.32%、晶圓-0.11及0.13微米1.28%、晶圓-90奈米0.56%、晶圓-0.25微米以上0.51%、晶圓-20奈米0.11% (2025年)") -> 晶圓-5奈米30.98%、晶圓-3奈米20.85%、其他14.08%、晶圓-7奈米12.06%、晶圓-28奈米5.91%、晶圓-16奈米5.66%、晶圓-65奈米3.16%、晶圓-40及45奈米2.51%、晶圓-0.15及0.18微米2.32%、晶圓-0.11及0.13微米1.28%、晶圓-90奈米0.56%、晶圓-0.25微米以上0.51%、晶圓-20奈米0.11% (2025年)
A22: =IFERROR(__xludf.DUMMYFUNCTION("""COMPUTED_VALUE"""),"公司電話") -> 公司電話 | B22: =IFERROR(__xludf.DUMMYFUNCTION("""COMPUTED_VALUE"""),"03-5636688") -> 03-5636688
A23: =IFERROR(__xludf.DUMMYFUNCTION("""COMPUTED_VALUE"""),"網址") -> 網址 | B23: =IFERROR(__xludf.DUMMYFUNCTION("""COMPUTED_VALUE"""),"https://www.tsmc.com") -> https://www.tsmc.com
A24: =IFERROR(__xludf.DUMMYFUNCTION("""COMPUTED_VALUE"""),"公司地址") -> 公司地址 | B24: =IFERROR(__xludf.DUMMYFUNCTION("""COMPUTED_VALUE"""),"新竹科學園區力行六路8號") -> 新竹科學園區力行六路8號
A25: =IFERROR(__xludf.DUMMYFUNCTION("""COMPUTED_VALUE"""),"[TABLE]") -> [TABLE]
A26: =IFERROR(__xludf.DUMMYFUNCTION("""COMPUTED_VALUE"""),"說明") -> 說明 | B26: =IFERROR(__xludf.DUMMYFUNCTION("""COMPUTED_VALUE"""),"上方""年度""表格中的最高與最低數據是年度內統計(01/01-12/31)資料。 本益比數據由交易所提供。 [TABLE]") -> 上方"年度"表格中的最高與最低數據是年度內統計(01/01-12/31)資料。 本益比數據由交易所提供。 [TABLE]
A28: =IFERROR(__xludf.DUMMYFUNCTION("IMPORTHTML(SUBSTITUTE(""https://www.cmoney.tw/forum/stock/股票代碼?s=fund-holdings"", ""股票代碼"",'股價預估'!E1),""table"",0)"),"基金名稱") -> 基金名稱 | B28: =IFERROR(__xludf.DUMMYFUNCTION("""COMPUTED_VALUE"""),"持股張數") -> 持股張數 | C28: =IFERROR(__xludf.DUMMYFUNCTION("""COMPUTED_VALUE"""),"持股金額(仟萬)") -> 持股金額(仟萬) | D28: =IFERROR(__xludf.DUMMYFUNCTION("""COMPUTED_VALUE"""),"持股比例") -> 持股比例 | E28: =IFERROR(__xludf.DUMMYFUNCTION("""COMPUTED_VALUE"""),"月持股比例增減") -> 月持股比例增減
A29: =IFERROR(__xludf.DUMMYFUNCTION("""COMPUTED_VALUE"""),"ETF0052 富邦台灣科技指數基金") -> ETF0052 富邦台灣科技指數基金 | B29: =IFERROR(__xludf.DUMMYFUNCTION("""COMPUTED_VALUE"""),42376) -> 42376 | C29: =IFERROR(__xludf.DUMMYFUNCTION("""COMPUTED_VALUE"""),10212.62) -> 10212.62 | D29: =IFERROR(__xludf.DUMMYFUNCTION("""COMPUTED_VALUE"""),0.6341) -> 0.6341 | E29: =IFERROR(__xludf.DUMMYFUNCTION("""COMPUTED_VALUE"""),-0.0065) -> -0.0065 | H29: =COUNTA(A29:A75)&"檔ETF持股" -> 10檔ETF持股
A30: =IFERROR(__xludf.DUMMYFUNCTION("""COMPUTED_VALUE"""),"ETF006208 富邦台灣釆吉50基金") -> ETF006208 富邦台灣釆吉50基金 | B30: =IFERROR(__xludf.DUMMYFUNCTION("""COMPUTED_VALUE"""),108008) -> 108008 | C30: =IFERROR(__xludf.DUMMYFUNCTION("""COMPUTED_VALUE"""),26029.94) -> 26029.94 | D30: =IFERROR(__xludf.DUMMYFUNCTION("""COMPUTED_VALUE"""),0.5739) -> 0.5739 | E30: =IFERROR(__xludf.DUMMYFUNCTION("""COMPUTED_VALUE"""),-0.0091) -> -0.0091
A31: =IFERROR(__xludf.DUMMYFUNCTION("""COMPUTED_VALUE"""),"ETF0050 元大台灣卓越50基金") -> ETF0050 元大台灣卓越50基金 | B31: =IFERROR(__xludf.DUMMYFUNCTION("""COMPUTED_VALUE"""),525991) -> 525991 | C31: =IFERROR(__xludf.DUMMYFUNCTION("""COMPUTED_VALUE"""),126763.92) -> 126763.92 | D31: =IFERROR(__xludf.DUMMYFUNCTION("""COMPUTED_VALUE"""),0.5737) -> 0.5737 | E31: =IFERROR(__xludf.DUMMYFUNCTION("""COMPUTED_VALUE"""),-0.0091) -> -0.0091
A32: =IFERROR(__xludf.DUMMYFUNCTION("""COMPUTED_VALUE"""),"ETF00692 富邦臺灣公司治理100基金") -> ETF00692 富邦臺灣公司治理100基金 | B32: =IFERROR(__xludf.DUMMYFUNCTION("""COMPUTED_VALUE"""),13200) -> 13200 | C32: =IFERROR(__xludf.DUMMYFUNCTION("""COMPUTED_VALUE"""),3181.22) -> 3181.22 | D32: =IFERROR(__xludf.DUMMYFUNCTION("""COMPUTED_VALUE"""),0.5624) -> 0.5624 | E32: =IFERROR(__xludf.DUMMYFUNCTION("""COMPUTED_VALUE"""),"+0.08%") -> +0.08%
A33: =IFERROR(__xludf.DUMMYFUNCTION("""COMPUTED_VALUE"""),"ETF006203 元大摩臺基金") -> ETF006203 元大摩臺基金 | B33: =IFERROR(__xludf.DUMMYFUNCTION("""COMPUTED_VALUE"""),452) -> 452 | C33: =IFERROR(__xludf.DUMMYFUNCTION("""COMPUTED_VALUE"""),109.05) -> 109.05 | D33: =IFERROR(__xludf.DUMMYFUNCTION("""COMPUTED_VALUE"""),0.5489) -> 0.5489 | E33: =IFERROR(__xludf.DUMMYFUNCTION("""COMPUTED_VALUE"""),-0.001) -> -0.001
A34: =IFERROR(__xludf.DUMMYFUNCTION("""COMPUTED_VALUE"""),"ETF0057 富邦台灣ETF傘型基金之富邦台灣摩根指數股票型基金") -> ETF0057 富邦台灣ETF傘型基金之富邦台灣摩根指數股票型基金 | B34: =IFERROR(__xludf.DUMMYFUNCTION("""COMPUTED_VALUE"""),110) -> 110 | C34: =IFERROR(__xludf.DUMMYFUNCTION("""COMPUTED_VALUE"""),26.54) -> 26.54 | D34: =IFERROR(__xludf.DUMMYFUNCTION("""COMPUTED_VALUE"""),0.5485) -> 0.5485 | E34: =IFERROR(__xludf.DUMMYFUNCTION("""COMPUTED_VALUE"""),-0.0022) -> -0.0022
A35: =IFERROR(__xludf.DUMMYFUNCTION("""COMPUTED_VALUE"""),"ETF0053 元大台灣電子科技基金") -> ETF0053 元大台灣電子科技基金 | B35: =IFERROR(__xludf.DUMMYFUNCTION("""COMPUTED_VALUE"""),276) -> 276 | C35: =IFERROR(__xludf.DUMMYFUNCTION("""COMPUTED_VALUE"""),66.6) -> 66.6 | D35: =IFERROR(__xludf.DUMMYFUNCTION("""COMPUTED_VALUE"""),0.4974) -> 0.4974 | E35: =IFERROR(__xludf.DUMMYFUNCTION("""COMPUTED_VALUE"""),"+0.27%") -> +0.27%
A36: =IFERROR(__xludf.DUMMYFUNCTION("""COMPUTED_VALUE"""),"ETF009809 富邦台灣淨零轉型ESG50ETF基金") -> ETF009809 富邦台灣淨零轉型ESG50ETF基金 | B36: =IFERROR(__xludf.DUMMYFUNCTION("""COMPUTED_VALUE"""),97) -> 97 | C36: =IFERROR(__xludf.DUMMYFUNCTION("""COMPUTED_VALUE"""),23.52) -> 23.52 | D36: =IFERROR(__xludf.DUMMYFUNCTION("""COMPUTED_VALUE"""),0.4276) -> 0.4276 | E36: =IFERROR(__xludf.DUMMYFUNCTION("""COMPUTED_VALUE"""),"+14.21%") -> +14.21%
A37: =IFERROR(__xludf.DUMMYFUNCTION("""COMPUTED_VALUE"""),"ETF00904 台新臺灣全市場半導體精選30ETF基金") -> ETF00904 台新臺灣全市場半導體精選30ETF基金 | B37: =IFERROR(__xludf.DUMMYFUNCTION("""COMPUTED_VALUE"""),1266) -> 1266 | C37: =IFERROR(__xludf.DUMMYFUNCTION("""COMPUTED_VALUE"""),305.11) -> 305.11 | D37: =IFERROR(__xludf.DUMMYFUNCTION("""COMPUTED_VALUE"""),0.4156) -> 0.4156 | E37: =IFERROR(__xludf.DUMMYFUNCTION("""COMPUTED_VALUE"""),"+5.40%") -> +5.40%
A38: =IFERROR(__xludf.DUMMYFUNCTION("""COMPUTED_VALUE"""),"ETF009803 玉山臺灣市值動能50ETF基金") -> ETF009803 玉山臺灣市值動能50ETF基金 | B38: =IFERROR(__xludf.DUMMYFUNCTION("""COMPUTED_VALUE"""),618) -> 618 | C38: =IFERROR(__xludf.DUMMYFUNCTION("""COMPUTED_VALUE"""),148.94) -> 148.94 | D38: =IFERROR(__xludf.DUMMYFUNCTION("""COMPUTED_VALUE"""),0.4114) -> 0.4114 | E38: =IFERROR(__xludf.DUMMYFUNCTION("""COMPUTED_VALUE"""),"+3.45%") -> +3.45%

Sheet 營收
A1: =IFERROR(__xludf.DUMMYFUNCTION("IMPORTHTML(SUBSTITUTE(""https://histock.tw/stock/股票代碼/%E8%B2%A1%E5%8B%99%E5%A0%B1%E8%A1%A8"", ""股票代碼"",'股價預估'!E1),""table"",0)"),"年度/月份") -> 年度/月份 | B1: =IFERROR(__xludf.DUMMYFUNCTION("""COMPUTED_VALUE"""),"營業收入（單位：千元）") -> 營業收入（單位：千元） | F1: =IFERROR(__xludf.DUMMYFUNCTION("""COMPUTED_VALUE"""),"累計營業收入（單位：千元）") -> 累計營業收入（單位：千元） | I1: ="★ 單月YOY "&TEXT(E3,"+0.0%;-0.0%")&" 累積YOY "&TEXT(H3,"+0.0%;-0.0%")&" "&Q3&" "&V3 -> ★ 單月YOY +44.7% 累積YOY +37.0% 長短期YOY擴大 長短期營收擴大
B2: =IFERROR(__xludf.DUMMYFUNCTION("""COMPUTED_VALUE"""),"單月營收") -> 單月營收 | C2: =IFERROR(__xludf.DUMMYFUNCTION("""COMPUTED_VALUE"""),"去年同月營收") -> 去年同月營收 | D2: =IFERROR(__xludf.DUMMYFUNCTION("""COMPUTED_VALUE"""),"單月月增率") -> 單月月增率 | E2: =IFERROR(__xludf.DUMMYFUNCTION("""COMPUTED_VALUE"""),"單月年增率") -> 單月年增率 | F2: =IFERROR(__xludf.DUMMYFUNCTION("""COMPUTED_VALUE"""),"累計營收") -> 累計營收 | G2: =IFERROR(__xludf.DUMMYFUNCTION("""COMPUTED_VALUE"""),"去年累計營收") -> 去年累計營收 | H2: =IFERROR(__xludf.DUMMYFUNCTION("""COMPUTED_VALUE"""),"累積年增率") -> 累積年增率 | J2: 近3個月營收 | K2: 去年近3個月營收 | L2: 近3個月營收YOY | M2: 近12個月營收 | N2: 去年近12個月營收 | O2: 近12個月營收YOY | P2: 長短期營收YOY間距 | S2: 近3個月平均營收 | T2: 近12個月平均營收 | U2: 長短期營收間距
A3: =IFERROR(__xludf.DUMMYFUNCTION("""COMPUTED_VALUE"""),46204) -> 46204 | B3: =IFERROR(__xludf.DUMMYFUNCTION("""COMPUTED_VALUE"""),467580544) -> 467580544 | C3: =IFERROR(__xludf.DUMMYFUNCTION("""COMPUTED_VALUE"""),323165696) -> 323165696 | D3: =IFERROR(__xludf.DUMMYFUNCTION("""COMPUTED_VALUE"""),0.056) -> 0.056 | E3: =IFERROR(__xludf.DUMMYFUNCTION("""COMPUTED_VALUE"""),0.447) -> 0.447 | F3: =IFERROR(__xludf.DUMMYFUNCTION("""COMPUTED_VALUE"""),2872064256) -> 2872064256 | G3: =IFERROR(__xludf.DUMMYFUNCTION("""COMPUTED_VALUE"""),2096211200) -> 2096211200 | H3: =IFERROR(__xludf.DUMMYFUNCTION("""COMPUTED_VALUE"""),0.37) -> 0.37 | I3: =A3 -> 46204 | J3: =IF(ISBLANK(B3),SUM(B91:B93),SUM(B3:B5)) -> 1327235680 | K3: =IF(ISBLANK(B3),SUM(B103:B105),SUM(B15:B17)) -> 907390592 | L3: =(J3-K3)/K3 -> 0.462695 | M3: =IF(ISBLANK(B3),SUM(B91:B102),SUM(B3:B14)) -> 4584907264 | N3: =IF(ISBLANK(B3),SUM(B103:B114),SUM(B15:B26)) -> 3467411424 | O3: =(M3-N3)/N3 -> 0.32228533 | P3: =L3-O3 -> 0.14040967 | Q3: =IF(P3>P4,"長短期YOY擴大","長短期YOY收斂") -> 長短期YOY擴大 | S3: =IF(ISBLANK(B3),AVERAGE(B91:B93),AVERAGE(B3:B5)) -> 4.4241189e+08 | T3: =IF(ISBLANK(B3),AVERAGE(B91:B102),AVERAGE(B3:B14)) -> 3.8207561e+08 | U3: =S3-T3 -> 60336288 | V3: =IF(U3>U4,"長短期營收擴大","長短期營收收斂") -> 長短期營收擴大 | AA3: =B3 -> 467580544 | AB3: =B15 -> 323165696 | AC3: =B27 -> 256953104
A4: =IFERROR(__xludf.DUMMYFUNCTION("""COMPUTED_VALUE"""),46174) -> 46174 | B4: =IFERROR(__xludf.DUMMYFUNCTION("""COMPUTED_VALUE"""),442679968) -> 442679968 | C4: =IFERROR(__xludf.DUMMYFUNCTION("""COMPUTED_VALUE"""),263708976) -> 263708976 | D4: =IFERROR(__xludf.DUMMYFUNCTION("""COMPUTED_VALUE"""),0.062) -> 0.062 | E4: =IFERROR(__xludf.DUMMYFUNCTION("""COMPUTED_VALUE"""),0.679) -> 0.679 | F4: =IFERROR(__xludf.DUMMYFUNCTION("""COMPUTED_VALUE"""),2404483584) -> 2404483584 | G4: =IFERROR(__xludf.DUMMYFUNCTION("""COMPUTED_VALUE"""),1773045504) -> 1773045504 | H4: =IFERROR(__xludf.DUMMYFUNCTION("""COMPUTED_VALUE"""),0.356) -> 0.356 | I4: =A4 -> 46174 | J4: =IF(ISBLANK(B4),SUM(B92:B94),SUM(B4:B6)) -> 1270380224 | K4: =IF(ISBLANK(B4),SUM(B104:B106),SUM(B16:B18)) -> 933791808 | L4: =(J4-K4)/K4 -> 0.36045338 | M4: =IF(ISBLANK(B4),SUM(B92:B103),SUM(B4:B15)) -> 4440492416 | N4: =IF(ISBLANK(B4),SUM(B104:B115),SUM(B16:B27)) -> 3401198832 | O4: =(M4-N4)/N4 -> 0.30556684 | P4: =L4-O4 -> 0.054886541 | Q4: =IF(P4>P5,"長短期YOY擴大","長短期YOY收斂") -> 長短期YOY擴大 | S4: =IF(ISBLANK(B4),AVERAGE(B92:B94),AVERAGE(B4:B6)) -> 4.2346007e+08 | T4: =IF(ISBLANK(B4),AVERAGE(B92:B103),AVERAGE(B4:B15)) -> 3.7004103e+08 | U4: =S4-T4 -> 53419040 | V4: =IF(U4>U5,"長短期營收擴大","長短期營收收斂") -> 長短期營收收斂 | AA4: =B4 -> 442679968 | AB4: =B16 -> 263708992 | AC4: =B28 -> 207868704
A5: =IFERROR(__xludf.DUMMYFUNCTION("""COMPUTED_VALUE"""),46143) -> 46143 | B5: =IFERROR(__xludf.DUMMYFUNCTION("""COMPUTED_VALUE"""),416975168) -> 416975168 | C5: =IFERROR(__xludf.DUMMYFUNCTION("""COMPUTED_VALUE"""),320515936) -> 320515936 | D5: =IFERROR(__xludf.DUMMYFUNCTION("""COMPUTED_VALUE"""),0.015) -> 0.015 | E5: =IFERROR(__xludf.DUMMYFUNCTION("""COMPUTED_VALUE"""),0.301) -> 0.301 | F5: =IFERROR(__xludf.DUMMYFUNCTION("""COMPUTED_VALUE"""),1961803776) -> 1961803776 | G5: =IFERROR(__xludf.DUMMYFUNCTION("""COMPUTED_VALUE"""),1509336576) -> 1509336576 | H5: =IFERROR(__xludf.DUMMYFUNCTION("""COMPUTED_VALUE"""),0.3) -> 0.3 | I5: =A5 -> 46143 | J5: =IF(ISBLANK(B5),SUM(B93:B95),SUM(B5:B7)) -> 1242891968 | K5: =IF(ISBLANK(B5),SUM(B105:B107),SUM(B17:B19)) -> 956039616 | L5: =(J5-K5)/K5 -> 0.30004233 | M5: =IF(ISBLANK(B5),SUM(B93:B104),SUM(B5:B16)) -> 4261521440 | N5: =IF(ISBLANK(B5),SUM(B105:B116),SUM(B17:B28)) -> 3345358544 | O5: =(M5-N5)/N5 -> 0.2738609 | P5: =L5-O5 -> 0.02618143 | Q5: =IF(P5>P6,"長短期YOY擴大","長短期YOY收斂") -> 長短期YOY擴大 | S5: =IF(ISBLANK(B5),AVERAGE(B93:B95),AVERAGE(B5:B7)) -> 4.1429732e+08 | T5: =IF(ISBLANK(B5),AVERAGE(B93:B104),AVERAGE(B5:B16)) -> 3.5512679e+08 | U5: =S5-T5 -> 59170536 | V5: =IF(U5>U6,"長短期營收擴大","長短期營收收斂") -> 長短期營收擴大 | AA5: =B5 -> 416975168 | AB5: =B17 -> 320515904 | AC5: =B29 -> 229620400
A6: =IFERROR(__xludf.DUMMYFUNCTION("""COMPUTED_VALUE"""),46113) -> 46113 | B6: =IFERROR(__xludf.DUMMYFUNCTION("""COMPUTED_VALUE"""),410725088) -> 410725088 | C6: =IFERROR(__xludf.DUMMYFUNCTION("""COMPUTED_VALUE"""),349566912) -> 349566912 | D6: =IFERROR(__xludf.DUMMYFUNCTION("""COMPUTED_VALUE"""),-0.011) -> -0.011 | E6: =IFERROR(__xludf.DUMMYFUNCTION("""COMPUTED_VALUE"""),0.175) -> 0.175 | F6: =IFERROR(__xludf.DUMMYFUNCTION("""COMPUTED_VALUE"""),1544829056) -> 1544829056 | G6: =IFERROR(__xludf.DUMMYFUNCTION("""COMPUTED_VALUE"""),1188820992) -> 1188820992 | H6: =IFERROR(__xludf.DUMMYFUNCTION("""COMPUTED_VALUE"""),0.299) -> 0.299 | I6: =A6 -> 46113 | J6: =IF(ISBLANK(B6),SUM(B94:B96),SUM(B6:B8)) -> 1143573408 | K6: =IF(ISBLANK(B6),SUM(B106:B108),SUM(B18:B20)) -> 895532512 | L6: =(J6-K6)/K6 -> 0.27697587 | M6: =IF(ISBLANK(B6),SUM(B94:B105),SUM(B6:B17)) -> 4165062176 | N6: =IF(ISBLANK(B6),SUM(B106:B117),SUM(B18:B29)) -> 3254463040 | O6: =(M6-N6)/N6 -> 0.27980012 | P6: =L6-O6 -> -0.0028242467 | Q6: =IF(P6>P7,"長短期YOY擴大","長短期YOY收斂") -> 長短期YOY收斂 | S6: =IF(ISBLANK(B6),AVERAGE(B94:B96),AVERAGE(B6:B8)) -> 381191136 | T6: =IF(ISBLANK(B6),AVERAGE(B94:B105),AVERAGE(B6:B17)) -> 3.4708851e+08 | U6: =S6-T6 -> 34102621 | V6: =IF(U6>U7,"長短期營收擴大","長短期營收收斂") -> 長短期營收收斂 | AA6: =B6 -> 410725088 | AB6: =B18 -> 349566912 | AC6: =B30 -> 236021104
A7: =IFERROR(__xludf.DUMMYFUNCTION("""COMPUTED_VALUE"""),46082) -> 46082 | B7: =IFERROR(__xludf.DUMMYFUNCTION("""COMPUTED_VALUE"""),415191712) -> 415191712 | C7: =IFERROR(__xludf.DUMMYFUNCTION("""COMPUTED_VALUE"""),285956800) -> 285956800 | D7: =IFERROR(__xludf.DUMMYFUNCTION("""COMPUTED_VALUE"""),0.307) -> 0.307 | E7: =IFERROR(__xludf.DUMMYFUNCTION("""COMPUTED_VALUE"""),0.452) -> 0.452 | F7: =IFERROR(__xludf.DUMMYFUNCTION("""COMPUTED_VALUE"""),1134103040) -> 1134103040 | G7: =IFERROR(__xludf.DUMMYFUNCTION("""COMPUTED_VALUE"""),839253632) -> 839253632 | H7: =IFERROR(__xludf.DUMMYFUNCTION("""COMPUTED_VALUE"""),0.351) -> 0.351 | I7: =A7 -> 46082 | J7: =IF(ISBLANK(B7),SUM(B95:B97),SUM(B7:B9)) -> 1134103424 | K7: =IF(ISBLANK(B7),SUM(B107:B109),SUM(B19:B21)) -> 839253600 | L7: =(J7-K7)/K7 -> 0.35132387 | M7: =IF(ISBLANK(B7),SUM(B95:B106),SUM(B7:B18)) -> 4103904000 | N7: =IF(ISBLANK(B7),SUM(B107:B118),SUM(B19:B30)) -> 3140917232 | O7: =(M7-N7)/N7 -> 0.30659412 | P7: =L7-O7 -> 0.044729747 | Q7: =IF(P7>P8,"長短期YOY擴大","長短期YOY收斂") -> 長短期YOY擴大 | S7: =IF(ISBLANK(B7),AVERAGE(B95:B97),AVERAGE(B7:B9)) -> 3.7803447e+08 | T7: =IF(ISBLANK(B7),AVERAGE(B95:B106),AVERAGE(B7:B18)) -> 341992000 | U7: =S7-T7 -> 36042475 | V7: =IF(U7>U8,"長短期營收擴大","長短期營收收斂") -> 長短期營收擴大 | AA7: =B7 -> 415191712 | AB7: =B19 -> 285956800 | AC7: =B31 -> 195210800
A8: =IFERROR(__xludf.DUMMYFUNCTION("""COMPUTED_VALUE"""),46054) -> 46054 | B8: =IFERROR(__xludf.DUMMYFUNCTION("""COMPUTED_VALUE"""),317656608) -> 317656608 | C8: =IFERROR(__xludf.DUMMYFUNCTION("""COMPUTED_VALUE"""),260008800) -> 260008800 | D8: =IFERROR(__xludf.DUMMYFUNCTION("""COMPUTED_VALUE"""),-0.208) -> -0.208 | E8: =IFERROR(__xludf.DUMMYFUNCTION("""COMPUTED_VALUE"""),0.222) -> 0.222 | F8: =IFERROR(__xludf.DUMMYFUNCTION("""COMPUTED_VALUE"""),718911680) -> 718911680 | G8: =IFERROR(__xludf.DUMMYFUNCTION("""COMPUTED_VALUE"""),553296768) -> 553296768 | H8: =IFERROR(__xludf.DUMMYFUNCTION("""COMPUTED_VALUE"""),0.299) -> 0.299 | I8: =A8 -> 46054 | J8: =IF(ISBLANK(B8),SUM(B96:B98),SUM(B8:B10)) -> 1053915296 | K8: =IF(ISBLANK(B8),SUM(B108:B110),SUM(B20:B22)) -> 831459904 | L8: =(J8-K8)/K8 -> 0.26754795 | M8: =IF(ISBLANK(B8),SUM(B96:B107),SUM(B8:B19)) -> 3974669088 | N8: =IF(ISBLANK(B8),SUM(B108:B119),SUM(B20:B31)) -> 3050171232 | O8: =(M8-N8)/N8 -> 0.30309703 | P8: =L8-O8 -> -0.035549086 | Q8: =IF(P8>P9,"長短期YOY擴大","長短期YOY收斂") -> 長短期YOY擴大 | S8: =IF(ISBLANK(B8),AVERAGE(B96:B98),AVERAGE(B8:B10)) -> 3.513051e+08 | T8: =IF(ISBLANK(B8),AVERAGE(B96:B107),AVERAGE(B8:B19)) -> 331222424 | U8: =S8-T8 -> 20082675 | V8: =IF(U8>U9,"長短期營收擴大","長短期營收收斂") -> 長短期營收收斂 | AA8: =B8 -> 317656608 | AB8: =B20 -> 260008800 | AC8: =B32 -> 181648304
A9: =IFERROR(__xludf.DUMMYFUNCTION("""COMPUTED_VALUE"""),46023) -> 46023 | B9: =IFERROR(__xludf.DUMMYFUNCTION("""COMPUTED_VALUE"""),401255104) -> 401255104 | C9: =IFERROR(__xludf.DUMMYFUNCTION("""COMPUTED_VALUE"""),293288000) -> 293288000 | D9: =IFERROR(__xludf.DUMMYFUNCTION("""COMPUTED_VALUE"""),0.198) -> 0.198 | E9: =IFERROR(__xludf.DUMMYFUNCTION("""COMPUTED_VALUE"""),0.368) -> 0.368 | F9: =IFERROR(__xludf.DUMMYFUNCTION("""COMPUTED_VALUE"""),401255104) -> 401255104 | G9: =IFERROR(__xludf.DUMMYFUNCTION("""COMPUTED_VALUE"""),293288000) -> 293288000 | H9: =IFERROR(__xludf.DUMMYFUNCTION("""COMPUTED_VALUE"""),0.368) -> 0.368 | I9: =A9 -> 46023 | J9: =IF(ISBLANK(B9),SUM(B97:B99),SUM(B9:B11)) -> 1079872480 | K9: =IF(ISBLANK(B9),SUM(B109:B111),SUM(B21:B23)) -> 847509504 | L9: =(J9-K9)/K9 -> 0.27417153 | M9: =IF(ISBLANK(B9),SUM(B97:B108),SUM(B9:B20)) -> 3917021280 | N9: =IF(ISBLANK(B9),SUM(B109:B120),SUM(B21:B32)) -> 2971810736 | O9: =(M9-N9)/N9 -> 0.3180588 | P9: =L9-O9 -> -0.043887267 | Q9: =IF(P9>P10,"長短期YOY擴大","長短期YOY收斂") -> 長短期YOY擴大 | S9: =IF(ISBLANK(B9),AVERAGE(B97:B99),AVERAGE(B9:B11)) -> 3.5995749e+08 | T9: =IF(ISBLANK(B9),AVERAGE(B97:B108),AVERAGE(B9:B20)) -> 326418440 | U9: =S9-T9 -> 33539053 | V9: =IF(U9>U10,"長短期營收擴大","長短期營收收斂") -> 長短期營收擴大 | AA9: =B9 -> 401255104 | AB9: =B21 -> 293288000 | AC9: =B33 -> 215785104
A10: =IFERROR(__xludf.DUMMYFUNCTION("""COMPUTED_VALUE"""),45992) -> 45992 | B10: =IFERROR(__xludf.DUMMYFUNCTION("""COMPUTED_VALUE"""),335003584) -> 335003584 | C10: =IFERROR(__xludf.DUMMYFUNCTION("""COMPUTED_VALUE"""),278163104) -> 278163104 | D10: =IFERROR(__xludf.DUMMYFUNCTION("""COMPUTED_VALUE"""),-0.025) -> -0.025 | E10: =IFERROR(__xludf.DUMMYFUNCTION("""COMPUTED_VALUE"""),0.204) -> 0.204 | F10: =IFERROR(__xludf.DUMMYFUNCTION("""COMPUTED_VALUE"""),3809053952) -> 3809053952 | G10: =IFERROR(__xludf.DUMMYFUNCTION("""COMPUTED_VALUE"""),2894308096) -> 2894308096 | H10: =IFERROR(__xludf.DUMMYFUNCTION("""COMPUTED_VALUE"""),0.316) -> 0.316 | I10: =A10 -> 45992 | J10: =IF(ISBLANK(B10),SUM(B98:B100),SUM(B10:B12)) -> 1046090464 | K10: =IF(ISBLANK(B10),SUM(B110:B112),SUM(B22:B24)) -> 868461216 | L10: =(J10-K10)/K10 -> 0.20453331 | M10: =IF(ISBLANK(B10),SUM(B98:B109),SUM(B10:B21)) -> 3809054176 | N10: =IF(ISBLANK(B10),SUM(B110:B121),SUM(B22:B33)) -> 2894307840 | O10: =(M10-N10)/N10 -> 0.31605012 | P10: =L10-O10 -> -0.11151681 | Q10: =IF(P10>P11,"長短期YOY擴大","長短期YOY收斂") -> 長短期YOY收斂 | S10: =IF(ISBLANK(B10),AVERAGE(B98:B100),AVERAGE(B10:B12)) -> 3.4869682e+08 | T10: =IF(ISBLANK(B10),AVERAGE(B98:B109),AVERAGE(B10:B21)) -> 3.1742118e+08 | U10: =S10-T10 -> 31275640 | V10: =IF(U10>U11,"長短期營收擴大","長短期營收收斂") -> 長短期營收收斂 | AA10: =B10 -> 335003584 | AB10: =B22 -> 278163104 | AC10: =B34 -> 176299904
A11: =IFERROR(__xludf.DUMMYFUNCTION("""COMPUTED_VALUE"""),45962) -> 45962 | B11: =IFERROR(__xludf.DUMMYFUNCTION("""COMPUTED_VALUE"""),343613792) -> 343613792 | C11: =IFERROR(__xludf.DUMMYFUNCTION("""COMPUTED_VALUE"""),276058400) -> 276058400 | D11: =IFERROR(__xludf.DUMMYFUNCTION("""COMPUTED_VALUE"""),-0.065) -> -0.065 | E11: =IFERROR(__xludf.DUMMYFUNCTION("""COMPUTED_VALUE"""),0.245) -> 0.245 | F11: =IFERROR(__xludf.DUMMYFUNCTION("""COMPUTED_VALUE"""),3474051072) -> 3474051072 | G11: =IFERROR(__xludf.DUMMYFUNCTION("""COMPUTED_VALUE"""),2616144896) -> 2616144896 | H11: =IFERROR(__xludf.DUMMYFUNCTION("""COMPUTED_VALUE"""),0.328) -> 0.328 | I11: =A11 -> 45962 | J11: =IF(ISBLANK(B11),SUM(B99:B101),SUM(B11:B13)) -> 1042067776 | K11: =IF(ISBLANK(B11),SUM(B111:B113),SUM(B23:B25)) -> 842170816 | L11: =(J11-K11)/K11 -> 0.23735916 | M11: =IF(ISBLANK(B11),SUM(B99:B110),SUM(B11:B22)) -> 3752213696 | N11: =IF(ISBLANK(B11),SUM(B111:B122),SUM(B23:B34)) -> 2792444640 | O11: =(M11-N11)/N11 -> 0.34370209 | P11: =L11-O11 -> -0.10634293 | Q11: =IF(P11>P12,"長短期YOY擴大","長短期YOY收斂") -> 長短期YOY收斂 | S11: =IF(ISBLANK(B11),AVERAGE(B99:B101),AVERAGE(B11:B13)) -> 3.4735593e+08 | T11: =IF(ISBLANK(B11),AVERAGE(B99:B110),AVERAGE(B11:B22)) -> 3.1268447e+08 | U11: =S11-T11 -> 34671451 | V11: =IF(U11>U12,"長短期營收擴大","長短期營收收斂") -> 長短期營收收斂 | AA11: =B11 -> 343613792 | AB11: =B23 -> 276058400 | AC11: =B35 -> 206026208
A12: =IFERROR(__xludf.DUMMYFUNCTION("""COMPUTED_VALUE"""),45931) -> 45931 | B12: =IFERROR(__xludf.DUMMYFUNCTION("""COMPUTED_VALUE"""),367473088) -> 367473088 | C12: =IFERROR(__xludf.DUMMYFUNCTION("""COMPUTED_VALUE"""),314239712) -> 314239712 | D12: =IFERROR(__xludf.DUMMYFUNCTION("""COMPUTED_VALUE"""),0.11) -> 0.11 | E12: =IFERROR(__xludf.DUMMYFUNCTION("""COMPUTED_VALUE"""),0.169) -> 0.169 | F12: =IFERROR(__xludf.DUMMYFUNCTION("""COMPUTED_VALUE"""),3130437120) -> 3130437120 | G12: =IFERROR(__xludf.DUMMYFUNCTION("""COMPUTED_VALUE"""),2340086016) -> 2340086016 | H12: =IFERROR(__xludf.DUMMYFUNCTION("""COMPUTED_VALUE"""),0.338) -> 0.338 | I12: =A12 -> 45931 | J12: =IF(ISBLANK(B12),SUM(B100:B102),SUM(B12:B14)) -> 1034225696 | K12: =IF(ISBLANK(B12),SUM(B112:B114),SUM(B24:B26)) -> 816978816 | L12: =(J12-K12)/K12 -> 0.26591495 | M12: =IF(ISBLANK(B12),SUM(B100:B111),SUM(B12:B23)) -> 3684658304 | N12: =IF(ISBLANK(B12),SUM(B112:B123),SUM(B24:B35)) -> 2722412448 | O12: =(M12-N12)/N12 -> 0.35345337 | P12: =L12-O12 -> -0.087538422 | Q12: =IF(P12>P13,"長短期YOY擴大","長短期YOY收斂") -> 長短期YOY收斂 | S12: =IF(ISBLANK(B12),AVERAGE(B100:B102),AVERAGE(B12:B14)) -> 3.447419e+08 | T12: =IF(ISBLANK(B12),AVERAGE(B100:B111),AVERAGE(B12:B23)) -> 3.0705486e+08 | U12: =S12-T12 -> 37687040 | V12: =IF(U12>U13,"長短期營收擴大","長短期營收收斂") -> 長短期營收擴大 | AA12: =B12 -> 367473088 | AB12: =B24 -> 314239712 | AC12: =B36 -> 243202800
A13: =IFERROR(__xludf.DUMMYFUNCTION("""COMPUTED_VALUE"""),45901) -> 45901 | B13: =IFERROR(__xludf.DUMMYFUNCTION("""COMPUTED_VALUE"""),330980896) -> 330980896 | C13: =IFERROR(__xludf.DUMMYFUNCTION("""COMPUTED_VALUE"""),251872704) -> 251872704 | D13: =IFERROR(__xludf.DUMMYFUNCTION("""COMPUTED_VALUE"""),-0.014) -> -0.014 | E13: =IFERROR(__xludf.DUMMYFUNCTION("""COMPUTED_VALUE"""),0.314) -> 0.314 | F13: =IFERROR(__xludf.DUMMYFUNCTION("""COMPUTED_VALUE"""),2762963968) -> 2762963968 | G13: =IFERROR(__xludf.DUMMYFUNCTION("""COMPUTED_VALUE"""),2025847040) -> 2025847040 | H13: =IFERROR(__xludf.DUMMYFUNCTION("""COMPUTED_VALUE"""),0.364) -> 0.364 | I13: =A13 -> 45901 | J13: =IF(ISBLANK(B13),SUM(B101:B103),SUM(B13:B15)) -> 989918304 | K13: =IF(ISBLANK(B13),SUM(B113:B115),SUM(B25:B27)) -> 759692208 | L13: =(J13-K13)/K13 -> 0.30305181 | M13: =IF(ISBLANK(B13),SUM(B101:B112),SUM(B13:B24)) -> 3631424928 | N13: =IF(ISBLANK(B13),SUM(B113:B124),SUM(B25:B36)) -> 2651375536 | O13: =(M13-N13)/N13 -> 0.36963809 | P13: =L13-O13 -> -0.066586285 | Q13: =IF(P13>P14,"長短期YOY擴大","長短期YOY收斂") -> 長短期YOY擴大 | S13: =IF(ISBLANK(B13),AVERAGE(B101:B103),AVERAGE(B13:B15)) -> 329972768 | T13: =IF(ISBLANK(B13),AVERAGE(B101:B112),AVERAGE(B13:B24)) -> 302618744 | U13: =S13-T13 -> 27354024 | V13: =IF(U13>U14,"長短期營收擴大","長短期營收收斂") -> 長短期營收擴大 | AA13: =B13 -> 330980896 | AB13: =B25 -> 251872704 | AC13: =B37 -> 180430304
A14: =IFERROR(__xludf.DUMMYFUNCTION("""COMPUTED_VALUE"""),45870) -> 45870 | B14: =IFERROR(__xludf.DUMMYFUNCTION("""COMPUTED_VALUE"""),335771712) -> 335771712 | C14: =IFERROR(__xludf.DUMMYFUNCTION("""COMPUTED_VALUE"""),250866400) -> 250866400 | D14: =IFERROR(__xludf.DUMMYFUNCTION("""COMPUTED_VALUE"""),0.039) -> 0.039 | E14: =IFERROR(__xludf.DUMMYFUNCTION("""COMPUTED_VALUE"""),0.338) -> 0.338 | F14: =IFERROR(__xludf.DUMMYFUNCTION("""COMPUTED_VALUE"""),2431983104) -> 2431983104 | G14: =IFERROR(__xludf.DUMMYFUNCTION("""COMPUTED_VALUE"""),1773974016) -> 1773974016 | H14: =IFERROR(__xludf.DUMMYFUNCTION("""COMPUTED_VALUE"""),0.371) -> 0.371 | I14: =A14 -> 45870 | J14: =IF(ISBLANK(B14),SUM(B102:B104),SUM(B14:B16)) -> 922646400 | K14: =IF(ISBLANK(B14),SUM(B114:B116),SUM(B26:B28)) -> 715688208 | L14: =(J14-K14)/K14 -> 0.28917368 | M14: =IF(ISBLANK(B14),SUM(B102:B113),SUM(B14:B25)) -> 3552316736 | N14: =IF(ISBLANK(B14),SUM(B114:B125),SUM(B26:B37)) -> 2579933136 | O14: =(M14-N14)/N14 -> 0.37690264 | P14: =L14-O14 -> -0.087728957 | Q14: =IF(P14>P15,"長短期YOY擴大","長短期YOY收斂") -> 長短期YOY收斂 | S14: =IF(ISBLANK(B14),AVERAGE(B102:B104),AVERAGE(B14:B16)) -> 307548800 | T14: =IF(ISBLANK(B14),AVERAGE(B102:B113),AVERAGE(B14:B25)) -> 2.9602639e+08 | U14: =S14-T14 -> 11522405 | V14: =IF(U14>U15,"長短期營收擴大","長短期營收收斂") -> 長短期營收收斂 | AA14: =B14 -> 335771712 | AB14: =B26 -> 250866400 | AC14: =B38 -> 188686304
A15: =IFERROR(__xludf.DUMMYFUNCTION("""COMPUTED_VALUE"""),45839) -> 45839 | B15: =IFERROR(__xludf.DUMMYFUNCTION("""COMPUTED_VALUE"""),323165696) -> 323165696 | C15: =IFERROR(__xludf.DUMMYFUNCTION("""COMPUTED_VALUE"""),256953104) -> 256953104 | D15: =IFERROR(__xludf.DUMMYFUNCTION("""COMPUTED_VALUE"""),0.225) -> 0.225 | E15: =IFERROR(__xludf.DUMMYFUNCTION("""COMPUTED_VALUE"""),0.258) -> 0.258 | F15: =IFERROR(__xludf.DUMMYFUNCTION("""COMPUTED_VALUE"""),2096210944) -> 2096210944 | G15: =IFERROR(__xludf.DUMMYFUNCTION("""COMPUTED_VALUE"""),1523106944) -> 1523106944 | H15: =IFERROR(__xludf.DUMMYFUNCTION("""COMPUTED_VALUE"""),0.376) -> 0.376 | I15: =A15 -> 45839 | J15: =IF(ISBLANK(B15),SUM(B103:B105),SUM(B15:B17)) -> 907390592 | K15: =IF(ISBLANK(B15),SUM(B115:B117),SUM(B27:B29)) -> 694442208 | L15: =(J15-K15)/K15 -> 0.30664666 | M15: =IF(ISBLANK(B15),SUM(B103:B114),SUM(B15:B26)) -> 3467411424 | N15: =IF(ISBLANK(B15),SUM(B115:B126),SUM(B27:B38)) -> 2517753040 | O15: =(M15-N15)/N15 -> 0.37718488 | P15: =L15-O15 -> -0.070538222 | Q15: =IF(P15>P16,"長短期YOY擴大","長短期YOY收斂") -> 長短期YOY收斂 | S15: =IF(ISBLANK(B15),AVERAGE(B103:B105),AVERAGE(B15:B17)) -> 3.0246353e+08 | T15: =IF(ISBLANK(B15),AVERAGE(B103:B114),AVERAGE(B15:B26)) -> 288950952 | U15: =S15-T15 -> 13512579 | V15: =IF(U15>S16,"長短期營收擴大","長短期營收收斂") -> 長短期營收擴大
A16: =IFERROR(__xludf.DUMMYFUNCTION("""COMPUTED_VALUE"""),45809) -> 45809 | B16: =IFERROR(__xludf.DUMMYFUNCTION("""COMPUTED_VALUE"""),263708992) -> 263708992 | C16: =IFERROR(__xludf.DUMMYFUNCTION("""COMPUTED_VALUE"""),207868704) -> 207868704 | D16: =IFERROR(__xludf.DUMMYFUNCTION("""COMPUTED_VALUE"""),-0.177) -> -0.177 | E16: =IFERROR(__xludf.DUMMYFUNCTION("""COMPUTED_VALUE"""),0.269) -> 0.269 | F16: =IFERROR(__xludf.DUMMYFUNCTION("""COMPUTED_VALUE"""),1773046016) -> 1773046016 | G16: =IFERROR(__xludf.DUMMYFUNCTION("""COMPUTED_VALUE"""),1266153984) -> 1266153984 | H16: =IFERROR(__xludf.DUMMYFUNCTION("""COMPUTED_VALUE"""),0.4) -> 0.4
A17: =IFERROR(__xludf.DUMMYFUNCTION("""COMPUTED_VALUE"""),45778) -> 45778 | B17: =IFERROR(__xludf.DUMMYFUNCTION("""COMPUTED_VALUE"""),320515904) -> 320515904 | C17: =IFERROR(__xludf.DUMMYFUNCTION("""COMPUTED_VALUE"""),229620400) -> 229620400 | D17: =IFERROR(__xludf.DUMMYFUNCTION("""COMPUTED_VALUE"""),-0.083) -> -0.083 | E17: =IFERROR(__xludf.DUMMYFUNCTION("""COMPUTED_VALUE"""),0.396) -> 0.396 | F17: =IFERROR(__xludf.DUMMYFUNCTION("""COMPUTED_VALUE"""),1509336960) -> 1509336960 | G17: =IFERROR(__xludf.DUMMYFUNCTION("""COMPUTED_VALUE"""),1058286016) -> 1058286016 | H17: =IFERROR(__xludf.DUMMYFUNCTION("""COMPUTED_VALUE"""),0.426) -> 0.426
A18: =IFERROR(__xludf.DUMMYFUNCTION("""COMPUTED_VALUE"""),45748) -> 45748 | B18: =IFERROR(__xludf.DUMMYFUNCTION("""COMPUTED_VALUE"""),349566912) -> 349566912 | C18: =IFERROR(__xludf.DUMMYFUNCTION("""COMPUTED_VALUE"""),236021104) -> 236021104 | D18: =IFERROR(__xludf.DUMMYFUNCTION("""COMPUTED_VALUE"""),0.222) -> 0.222 | E18: =IFERROR(__xludf.DUMMYFUNCTION("""COMPUTED_VALUE"""),0.481) -> 0.481 | F18: =IFERROR(__xludf.DUMMYFUNCTION("""COMPUTED_VALUE"""),1188820992) -> 1188820992 | G18: =IFERROR(__xludf.DUMMYFUNCTION("""COMPUTED_VALUE"""),828665280) -> 828665280 | H18: =IFERROR(__xludf.DUMMYFUNCTION("""COMPUTED_VALUE"""),0.435) -> 0.435
A19: =IFERROR(__xludf.DUMMYFUNCTION("""COMPUTED_VALUE"""),45717) -> 45717 | B19: =IFERROR(__xludf.DUMMYFUNCTION("""COMPUTED_VALUE"""),285956800) -> 285956800 | C19: =IFERROR(__xludf.DUMMYFUNCTION("""COMPUTED_VALUE"""),195210800) -> 195210800 | D19: =IFERROR(__xludf.DUMMYFUNCTION("""COMPUTED_VALUE"""),0.1) -> 0.1 | E19: =IFERROR(__xludf.DUMMYFUNCTION("""COMPUTED_VALUE"""),0.465) -> 0.465 | F19: =IFERROR(__xludf.DUMMYFUNCTION("""COMPUTED_VALUE"""),839253632) -> 839253632 | G19: =IFERROR(__xludf.DUMMYFUNCTION("""COMPUTED_VALUE"""),592644224) -> 592644224 | H19: =IFERROR(__xludf.DUMMYFUNCTION("""COMPUTED_VALUE"""),0.416) -> 0.416
A20: =IFERROR(__xludf.DUMMYFUNCTION("""COMPUTED_VALUE"""),45689) -> 45689 | B20: =IFERROR(__xludf.DUMMYFUNCTION("""COMPUTED_VALUE"""),260008800) -> 260008800 | C20: =IFERROR(__xludf.DUMMYFUNCTION("""COMPUTED_VALUE"""),181648304) -> 181648304 | D20: =IFERROR(__xludf.DUMMYFUNCTION("""COMPUTED_VALUE"""),-0.113) -> -0.113 | E20: =IFERROR(__xludf.DUMMYFUNCTION("""COMPUTED_VALUE"""),0.431) -> 0.431 | F20: =IFERROR(__xludf.DUMMYFUNCTION("""COMPUTED_VALUE"""),553296768) -> 553296768 | G20: =IFERROR(__xludf.DUMMYFUNCTION("""COMPUTED_VALUE"""),397433408) -> 397433408 | H20: =IFERROR(__xludf.DUMMYFUNCTION("""COMPUTED_VALUE"""),0.392) -> 0.392
A21: =IFERROR(__xludf.DUMMYFUNCTION("""COMPUTED_VALUE"""),45658) -> 45658 | B21: =IFERROR(__xludf.DUMMYFUNCTION("""COMPUTED_VALUE"""),293288000) -> 293288000 | C21: =IFERROR(__xludf.DUMMYFUNCTION("""COMPUTED_VALUE"""),215785104) -> 215785104 | D21: =IFERROR(__xludf.DUMMYFUNCTION("""COMPUTED_VALUE"""),0.054) -> 0.054 | E21: =IFERROR(__xludf.DUMMYFUNCTION("""COMPUTED_VALUE"""),0.359) -> 0.359 | F21: =IFERROR(__xludf.DUMMYFUNCTION("""COMPUTED_VALUE"""),293288000) -> 293288000 | G21: =IFERROR(__xludf.DUMMYFUNCTION("""COMPUTED_VALUE"""),215785104) -> 215785104 | H21: =IFERROR(__xludf.DUMMYFUNCTION("""COMPUTED_VALUE"""),0.359) -> 0.359
A22: =IFERROR(__xludf.DUMMYFUNCTION("""COMPUTED_VALUE"""),45627) -> 45627 | B22: =IFERROR(__xludf.DUMMYFUNCTION("""COMPUTED_VALUE"""),278163104) -> 278163104 | C22: =IFERROR(__xludf.DUMMYFUNCTION("""COMPUTED_VALUE"""),176299904) -> 176299904 | D22: =IFERROR(__xludf.DUMMYFUNCTION("""COMPUTED_VALUE"""),0.008) -> 0.008 | E22: =IFERROR(__xludf.DUMMYFUNCTION("""COMPUTED_VALUE"""),0.578) -> 0.578 | F22: =IFERROR(__xludf.DUMMYFUNCTION("""COMPUTED_VALUE"""),2894308096) -> 2894308096 | G22: =IFERROR(__xludf.DUMMYFUNCTION("""COMPUTED_VALUE"""),2161735936) -> 2161735936 | H22: =IFERROR(__xludf.DUMMYFUNCTION("""COMPUTED_VALUE"""),0.339) -> 0.339
A23: =IFERROR(__xludf.DUMMYFUNCTION("""COMPUTED_VALUE"""),45597) -> 45597 | B23: =IFERROR(__xludf.DUMMYFUNCTION("""COMPUTED_VALUE"""),276058400) -> 276058400 | C23: =IFERROR(__xludf.DUMMYFUNCTION("""COMPUTED_VALUE"""),206026208) -> 206026208 | D23: =IFERROR(__xludf.DUMMYFUNCTION("""COMPUTED_VALUE"""),-0.121) -> -0.121 | E23: =IFERROR(__xludf.DUMMYFUNCTION("""COMPUTED_VALUE"""),0.34) -> 0.34 | F23: =IFERROR(__xludf.DUMMYFUNCTION("""COMPUTED_VALUE"""),2616144896) -> 2616144896 | G23: =IFERROR(__xludf.DUMMYFUNCTION("""COMPUTED_VALUE"""),1985436032) -> 1985436032 | H23: =IFERROR(__xludf.DUMMYFUNCTION("""COMPUTED_VALUE"""),0.318) -> 0.318
A24: =IFERROR(__xludf.DUMMYFUNCTION("""COMPUTED_VALUE"""),45566) -> 45566 | B24: =IFERROR(__xludf.DUMMYFUNCTION("""COMPUTED_VALUE"""),314239712) -> 314239712 | C24: =IFERROR(__xludf.DUMMYFUNCTION("""COMPUTED_VALUE"""),243202800) -> 243202800 | D24: =IFERROR(__xludf.DUMMYFUNCTION("""COMPUTED_VALUE"""),0.248) -> 0.248 | E24: =IFERROR(__xludf.DUMMYFUNCTION("""COMPUTED_VALUE"""),0.292) -> 0.292 | F24: =IFERROR(__xludf.DUMMYFUNCTION("""COMPUTED_VALUE"""),2340086016) -> 2340086016 | G24: =IFERROR(__xludf.DUMMYFUNCTION("""COMPUTED_VALUE"""),1779410048) -> 1779410048 | H24: =IFERROR(__xludf.DUMMYFUNCTION("""COMPUTED_VALUE"""),0.315) -> 0.315
A25: =IFERROR(__xludf.DUMMYFUNCTION("""COMPUTED_VALUE"""),45536) -> 45536 | B25: =IFERROR(__xludf.DUMMYFUNCTION("""COMPUTED_VALUE"""),251872704) -> 251872704 | C25: =IFERROR(__xludf.DUMMYFUNCTION("""COMPUTED_VALUE"""),180430304) -> 180430304 | D25: =IFERROR(__xludf.DUMMYFUNCTION("""COMPUTED_VALUE"""),0.004) -> 0.004 | E25: =IFERROR(__xludf.DUMMYFUNCTION("""COMPUTED_VALUE"""),0.396) -> 0.396 | F25: =IFERROR(__xludf.DUMMYFUNCTION("""COMPUTED_VALUE"""),2025847040) -> 2025847040 | G25: =IFERROR(__xludf.DUMMYFUNCTION("""COMPUTED_VALUE"""),1536206976) -> 1536206976 | H25: =IFERROR(__xludf.DUMMYFUNCTION("""COMPUTED_VALUE"""),0.319) -> 0.319
A26: =IFERROR(__xludf.DUMMYFUNCTION("""COMPUTED_VALUE"""),45505) -> 45505 | B26: =IFERROR(__xludf.DUMMYFUNCTION("""COMPUTED_VALUE"""),250866400) -> 250866400 | C26: =IFERROR(__xludf.DUMMYFUNCTION("""COMPUTED_VALUE"""),188686304) -> 188686304 | D26: =IFERROR(__xludf.DUMMYFUNCTION("""COMPUTED_VALUE"""),-0.024) -> -0.024 | E26: =IFERROR(__xludf.DUMMYFUNCTION("""COMPUTED_VALUE"""),0.33) -> 0.33 | F26: =IFERROR(__xludf.DUMMYFUNCTION("""COMPUTED_VALUE"""),1773974016) -> 1773974016 | G26: =IFERROR(__xludf.DUMMYFUNCTION("""COMPUTED_VALUE"""),1355777024) -> 1355777024 | H26: =IFERROR(__xludf.DUMMYFUNCTION("""COMPUTED_VALUE"""),0.308) -> 0.308
A27: =IFERROR(__xludf.DUMMYFUNCTION("""COMPUTED_VALUE"""),45474) -> 45474 | B27: =IFERROR(__xludf.DUMMYFUNCTION("""COMPUTED_VALUE"""),256953104) -> 256953104 | C27: =IFERROR(__xludf.DUMMYFUNCTION("""COMPUTED_VALUE"""),177616192) -> 177616192 | D27: =IFERROR(__xludf.DUMMYFUNCTION("""COMPUTED_VALUE"""),0.236) -> 0.236 | E27: =IFERROR(__xludf.DUMMYFUNCTION("""COMPUTED_VALUE"""),0.447) -> 0.447 | F27: =IFERROR(__xludf.DUMMYFUNCTION("""COMPUTED_VALUE"""),1523106944) -> 1523106944 | G27: =IFERROR(__xludf.DUMMYFUNCTION("""COMPUTED_VALUE"""),1167090048) -> 1167090048 | H27: =IFERROR(__xludf.DUMMYFUNCTION("""COMPUTED_VALUE"""),0.305) -> 0.305
A28: =IFERROR(__xludf.DUMMYFUNCTION("""COMPUTED_VALUE"""),45444) -> 45444 | B28: =IFERROR(__xludf.DUMMYFUNCTION("""COMPUTED_VALUE"""),207868704) -> 207868704 | C28: =IFERROR(__xludf.DUMMYFUNCTION("""COMPUTED_VALUE"""),156404192) -> 156404192 | D28: =IFERROR(__xludf.DUMMYFUNCTION("""COMPUTED_VALUE"""),-0.095) -> -0.095 | E28: =IFERROR(__xludf.DUMMYFUNCTION("""COMPUTED_VALUE"""),0.329) -> 0.329 | F28: =IFERROR(__xludf.DUMMYFUNCTION("""COMPUTED_VALUE"""),1266153984) -> 1266153984 | G28: =IFERROR(__xludf.DUMMYFUNCTION("""COMPUTED_VALUE"""),989474176) -> 989474176 | H28: =IFERROR(__xludf.DUMMYFUNCTION("""COMPUTED_VALUE"""),0.28) -> 0.28
A29: =IFERROR(__xludf.DUMMYFUNCTION("""COMPUTED_VALUE"""),45413) -> 45413 | B29: =IFERROR(__xludf.DUMMYFUNCTION("""COMPUTED_VALUE"""),229620400) -> 229620400 | C29: =IFERROR(__xludf.DUMMYFUNCTION("""COMPUTED_VALUE"""),176537296) -> 176537296 | D29: =IFERROR(__xludf.DUMMYFUNCTION("""COMPUTED_VALUE"""),-0.027) -> -0.027 | E29: =IFERROR(__xludf.DUMMYFUNCTION("""COMPUTED_VALUE"""),0.301) -> 0.301 | F29: =IFERROR(__xludf.DUMMYFUNCTION("""COMPUTED_VALUE"""),1058286016) -> 1058286016 | G29: =IFERROR(__xludf.DUMMYFUNCTION("""COMPUTED_VALUE"""),833070080) -> 833070080 | H29: =IFERROR(__xludf.DUMMYFUNCTION("""COMPUTED_VALUE"""),0.27) -> 0.27
A30: =IFERROR(__xludf.DUMMYFUNCTION("""COMPUTED_VALUE"""),45383) -> 45383 | B30: =IFERROR(__xludf.DUMMYFUNCTION("""COMPUTED_VALUE"""),236021104) -> 236021104 | C30: =IFERROR(__xludf.DUMMYFUNCTION("""COMPUTED_VALUE"""),147899696) -> 147899696 | D30: =IFERROR(__xludf.DUMMYFUNCTION("""COMPUTED_VALUE"""),0.209) -> 0.209 | E30: =IFERROR(__xludf.DUMMYFUNCTION("""COMPUTED_VALUE"""),0.596) -> 0.596 | F30: =IFERROR(__xludf.DUMMYFUNCTION("""COMPUTED_VALUE"""),828665280) -> 828665280 | G30: =IFERROR(__xludf.DUMMYFUNCTION("""COMPUTED_VALUE"""),656532672) -> 656532672 | H30: =IFERROR(__xludf.DUMMYFUNCTION("""COMPUTED_VALUE"""),0.262) -> 0.262
A31: =IFERROR(__xludf.DUMMYFUNCTION("""COMPUTED_VALUE"""),45352) -> 45352 | B31: =IFERROR(__xludf.DUMMYFUNCTION("""COMPUTED_VALUE"""),195210800) -> 195210800 | C31: =IFERROR(__xludf.DUMMYFUNCTION("""COMPUTED_VALUE"""),145408304) -> 145408304 | D31: =IFERROR(__xludf.DUMMYFUNCTION("""COMPUTED_VALUE"""),0.075) -> 0.075 | E31: =IFERROR(__xludf.DUMMYFUNCTION("""COMPUTED_VALUE"""),0.343) -> 0.343 | F31: =IFERROR(__xludf.DUMMYFUNCTION("""COMPUTED_VALUE"""),592644224) -> 592644224 | G31: =IFERROR(__xludf.DUMMYFUNCTION("""COMPUTED_VALUE"""),508632992) -> 508632992 | H31: =IFERROR(__xludf.DUMMYFUNCTION("""COMPUTED_VALUE"""),0.165) -> 0.165
A32: =IFERROR(__xludf.DUMMYFUNCTION("""COMPUTED_VALUE"""),45323) -> 45323 | B32: =IFERROR(__xludf.DUMMYFUNCTION("""COMPUTED_VALUE"""),181648304) -> 181648304 | C32: =IFERROR(__xludf.DUMMYFUNCTION("""COMPUTED_VALUE"""),163174096) -> 163174096 | D32: =IFERROR(__xludf.DUMMYFUNCTION("""COMPUTED_VALUE"""),-0.158) -> -0.158 | E32: =IFERROR(__xludf.DUMMYFUNCTION("""COMPUTED_VALUE"""),0.113) -> 0.113 | F32: =IFERROR(__xludf.DUMMYFUNCTION("""COMPUTED_VALUE"""),397433408) -> 397433408 | G32: =IFERROR(__xludf.DUMMYFUNCTION("""COMPUTED_VALUE"""),363224608) -> 363224608 | H32: =IFERROR(__xludf.DUMMYFUNCTION("""COMPUTED_VALUE"""),0.094) -> 0.094
A33: =IFERROR(__xludf.DUMMYFUNCTION("""COMPUTED_VALUE"""),45292) -> 45292 | B33: =IFERROR(__xludf.DUMMYFUNCTION("""COMPUTED_VALUE"""),215785104) -> 215785104 | C33: =IFERROR(__xludf.DUMMYFUNCTION("""COMPUTED_VALUE"""),200050496) -> 200050496 | D33: =IFERROR(__xludf.DUMMYFUNCTION("""COMPUTED_VALUE"""),0.224) -> 0.224 | E33: =IFERROR(__xludf.DUMMYFUNCTION("""COMPUTED_VALUE"""),0.079) -> 0.079 | F33: =IFERROR(__xludf.DUMMYFUNCTION("""COMPUTED_VALUE"""),215785104) -> 215785104 | G33: =IFERROR(__xludf.DUMMYFUNCTION("""COMPUTED_VALUE"""),200050496) -> 200050496 | H33: =IFERROR(__xludf.DUMMYFUNCTION("""COMPUTED_VALUE"""),0.079) -> 0.079
A34: =IFERROR(__xludf.DUMMYFUNCTION("""COMPUTED_VALUE"""),45261) -> 45261 | B34: =IFERROR(__xludf.DUMMYFUNCTION("""COMPUTED_VALUE"""),176299904) -> 176299904 | C34: =IFERROR(__xludf.DUMMYFUNCTION("""COMPUTED_VALUE"""),192560192) -> 192560192 | D34: =IFERROR(__xludf.DUMMYFUNCTION("""COMPUTED_VALUE"""),-0.144) -> -0.144 | E34: =IFERROR(__xludf.DUMMYFUNCTION("""COMPUTED_VALUE"""),-0.084) -> -0.084 | F34: =IFERROR(__xludf.DUMMYFUNCTION("""COMPUTED_VALUE"""),2161735936) -> 2161735936 | G34: =IFERROR(__xludf.DUMMYFUNCTION("""COMPUTED_VALUE"""),2263890944) -> 2263890944 | H34: =IFERROR(__xludf.DUMMYFUNCTION("""COMPUTED_VALUE"""),-0.045) -> -0.045
A35: =IFERROR(__xludf.DUMMYFUNCTION("""COMPUTED_VALUE"""),45231) -> 45231 | B35: =IFERROR(__xludf.DUMMYFUNCTION("""COMPUTED_VALUE"""),206026208) -> 206026208 | C35: =IFERROR(__xludf.DUMMYFUNCTION("""COMPUTED_VALUE"""),222706000) -> 222706000 | D35: =IFERROR(__xludf.DUMMYFUNCTION("""COMPUTED_VALUE"""),-0.153) -> -0.153 | E35: =IFERROR(__xludf.DUMMYFUNCTION("""COMPUTED_VALUE"""),-0.075) -> -0.075 | F35: =IFERROR(__xludf.DUMMYFUNCTION("""COMPUTED_VALUE"""),1985436032) -> 1985436032 | G35: =IFERROR(__xludf.DUMMYFUNCTION("""COMPUTED_VALUE"""),2071330944) -> 2071330944 | H35: =IFERROR(__xludf.DUMMYFUNCTION("""COMPUTED_VALUE"""),-0.041) -> -0.041
A36: =IFERROR(__xludf.DUMMYFUNCTION("""COMPUTED_VALUE"""),45200) -> 45200 | B36: =IFERROR(__xludf.DUMMYFUNCTION("""COMPUTED_VALUE"""),243202800) -> 243202800 | C36: =IFERROR(__xludf.DUMMYFUNCTION("""COMPUTED_VALUE"""),210265600) -> 210265600 | D36: =IFERROR(__xludf.DUMMYFUNCTION("""COMPUTED_VALUE"""),0.348) -> 0.348 | E36: =IFERROR(__xludf.DUMMYFUNCTION("""COMPUTED_VALUE"""),0.157) -> 0.157 | F36: =IFERROR(__xludf.DUMMYFUNCTION("""COMPUTED_VALUE"""),1779410048) -> 1779410048 | G36: =IFERROR(__xludf.DUMMYFUNCTION("""COMPUTED_VALUE"""),1848625024) -> 1848625024 | H36: =IFERROR(__xludf.DUMMYFUNCTION("""COMPUTED_VALUE"""),-0.037) -> -0.037
A37: =IFERROR(__xludf.DUMMYFUNCTION("""COMPUTED_VALUE"""),45170) -> 45170 | B37: =IFERROR(__xludf.DUMMYFUNCTION("""COMPUTED_VALUE"""),180430304) -> 180430304 | C37: =IFERROR(__xludf.DUMMYFUNCTION("""COMPUTED_VALUE"""),208247696) -> 208247696 | D37: =IFERROR(__xludf.DUMMYFUNCTION("""COMPUTED_VALUE"""),-0.044) -> -0.044 | E37: =IFERROR(__xludf.DUMMYFUNCTION("""COMPUTED_VALUE"""),-0.134) -> -0.134 | F37: =IFERROR(__xludf.DUMMYFUNCTION("""COMPUTED_VALUE"""),1536206976) -> 1536206976 | G37: =IFERROR(__xludf.DUMMYFUNCTION("""COMPUTED_VALUE"""),1638359040) -> 1638359040 | H37: =IFERROR(__xludf.DUMMYFUNCTION("""COMPUTED_VALUE"""),-0.062) -> -0.062
A38: =IFERROR(__xludf.DUMMYFUNCTION("""COMPUTED_VALUE"""),45139) -> 45139 | B38: =IFERROR(__xludf.DUMMYFUNCTION("""COMPUTED_VALUE"""),188686304) -> 188686304 | C38: =IFERROR(__xludf.DUMMYFUNCTION("""COMPUTED_VALUE"""),218132400) -> 218132400 | D38: =IFERROR(__xludf.DUMMYFUNCTION("""COMPUTED_VALUE"""),0.062) -> 0.062 | E38: =IFERROR(__xludf.DUMMYFUNCTION("""COMPUTED_VALUE"""),-0.135) -> -0.135 | F38: =IFERROR(__xludf.DUMMYFUNCTION("""COMPUTED_VALUE"""),1355777024) -> 1355777024 | G38: =IFERROR(__xludf.DUMMYFUNCTION("""COMPUTED_VALUE"""),1430112000) -> 1430112000 | H38: =IFERROR(__xludf.DUMMYFUNCTION("""COMPUTED_VALUE"""),-0.052) -> -0.052
O42: 月份 | P42: =YEAR(A3) -> 2026 | Q42: =YEAR(A3)-1 -> 2025 | R42: =YEAR(A3)-2 -> 2024
A43: =IFERROR(__xludf.DUMMYFUNCTION("IMPORTHTML(SUBSTITUTE(""https://histock.tw/stock/financial.aspx?no=股票代碼&t=5&st=4&q=2"", ""股票代碼"",'股價預估'!E1),""table"",0)"),"年度/季別") -> 年度/季別 | B43: =IFERROR(__xludf.DUMMYFUNCTION("""COMPUTED_VALUE"""),"營收年增率") -> 營收年增率 | C43: =IFERROR(__xludf.DUMMYFUNCTION("""COMPUTED_VALUE"""),"近4季營收年增率") -> 近4季營收年增率 | D43: =IFERROR(__xludf.DUMMYFUNCTION("""COMPUTED_VALUE"""),"年度/季別") -> 年度/季別 | E43: =IFERROR(__xludf.DUMMYFUNCTION("""COMPUTED_VALUE"""),"營收年增率") -> 營收年增率 | F43: =IFERROR(__xludf.DUMMYFUNCTION("""COMPUTED_VALUE"""),"近4季營收年增率") -> 近4季營收年增率 | O43: =MONTH(A3) -> 7 | P43: =B3 -> 467580544 | Q43: =B15 -> 323165696 | R43: =B27 -> 256953104
A44: =IFERROR(__xludf.DUMMYFUNCTION("""COMPUTED_VALUE"""),"2026Q2") -> 2026Q2 | B44: =IFERROR(__xludf.DUMMYFUNCTION("""COMPUTED_VALUE"""),0.3605) -> 0.3605 | C44: =IFERROR(__xludf.DUMMYFUNCTION("""COMPUTED_VALUE"""),0.3056) -> 0.3056 | D44: =IFERROR(__xludf.DUMMYFUNCTION("""COMPUTED_VALUE"""),"2023Q3") -> 2023Q3 | E44: =IFERROR(__xludf.DUMMYFUNCTION("""COMPUTED_VALUE"""),-0.1083) -> -0.1083 | F44: =IFERROR(__xludf.DUMMYFUNCTION("""COMPUTED_VALUE"""),0.041) -> 0.041 | O44: =MONTH(A4) -> 6 | P44: =B4 -> 442679968 | Q44: =B16 -> 263708992 | R44: =B28 -> 207868704
A45: =IFERROR(__xludf.DUMMYFUNCTION("""COMPUTED_VALUE"""),"2026Q1") -> 2026Q1 | B45: =IFERROR(__xludf.DUMMYFUNCTION("""COMPUTED_VALUE"""),0.3513) -> 0.3513 | C45: =IFERROR(__xludf.DUMMYFUNCTION("""COMPUTED_VALUE"""),0.3066) -> 0.3066 | D45: =IFERROR(__xludf.DUMMYFUNCTION("""COMPUTED_VALUE"""),"2023Q2") -> 2023Q2 | E45: =IFERROR(__xludf.DUMMYFUNCTION("""COMPUTED_VALUE"""),-0.0998) -> -0.0998 | F45: =IFERROR(__xludf.DUMMYFUNCTION("""COMPUTED_VALUE"""),0.1864) -> 0.1864 | O45: =MONTH(A5) -> 5 | P45: =B5 -> 416975168 | Q45: =B17 -> 320515904 | R45: =B29 -> 229620400
A46: =IFERROR(__xludf.DUMMYFUNCTION("""COMPUTED_VALUE"""),"2025Q4") -> 2025Q4 | B46: =IFERROR(__xludf.DUMMYFUNCTION("""COMPUTED_VALUE"""),0.2045) -> 0.2045 | C46: =IFERROR(__xludf.DUMMYFUNCTION("""COMPUTED_VALUE"""),0.3161) -> 0.3161 | D46: =IFERROR(__xludf.DUMMYFUNCTION("""COMPUTED_VALUE"""),"2023Q1") -> 2023Q1 | E46: =IFERROR(__xludf.DUMMYFUNCTION("""COMPUTED_VALUE"""),0.0358) -> 0.0358 | F46: =IFERROR(__xludf.DUMMYFUNCTION("""COMPUTED_VALUE"""),0.3295) -> 0.3295 | O46: =MONTH(A6) -> 4 | P46: =B6 -> 410725088 | Q46: =B18 -> 349566912 | R46: =B30 -> 236021104
A47: =IFERROR(__xludf.DUMMYFUNCTION("""COMPUTED_VALUE"""),"2025Q3") -> 2025Q3 | B47: =IFERROR(__xludf.DUMMYFUNCTION("""COMPUTED_VALUE"""),0.3031) -> 0.3031 | C47: =IFERROR(__xludf.DUMMYFUNCTION("""COMPUTED_VALUE"""),0.3696) -> 0.3696 | D47: =IFERROR(__xludf.DUMMYFUNCTION("""COMPUTED_VALUE"""),"2022Q4") -> 2022Q4 | E47: =IFERROR(__xludf.DUMMYFUNCTION("""COMPUTED_VALUE"""),0.4275) -> 0.4275 | F47: =IFERROR(__xludf.DUMMYFUNCTION("""COMPUTED_VALUE"""),0.4261) -> 0.4261 | O47: =MONTH(A7) -> 3 | P47: =B7 -> 415191712 | Q47: =B19 -> 285956800 | R47: =B31 -> 195210800
A48: =IFERROR(__xludf.DUMMYFUNCTION("""COMPUTED_VALUE"""),"2025Q2") -> 2025Q2 | B48: =IFERROR(__xludf.DUMMYFUNCTION("""COMPUTED_VALUE"""),0.3865) -> 0.3865 | C48: =IFERROR(__xludf.DUMMYFUNCTION("""COMPUTED_VALUE"""),0.3948) -> 0.3948 | D48: =IFERROR(__xludf.DUMMYFUNCTION("""COMPUTED_VALUE"""),"2022Q3") -> 2022Q3 | E48: =IFERROR(__xludf.DUMMYFUNCTION("""COMPUTED_VALUE"""),0.4786) -> 0.4786 | F48: =IFERROR(__xludf.DUMMYFUNCTION("""COMPUTED_VALUE"""),0.3745) -> 0.3745 | O48: =MONTH(A8) -> 2 | P48: =B8 -> 317656608 | Q48: =B20 -> 260008800 | R48: =B32 -> 181648304
A49: =IFERROR(__xludf.DUMMYFUNCTION("""COMPUTED_VALUE"""),"2025Q1") -> 2025Q1 | B49: =IFERROR(__xludf.DUMMYFUNCTION("""COMPUTED_VALUE"""),0.4161) -> 0.4161 | C49: =IFERROR(__xludf.DUMMYFUNCTION("""COMPUTED_VALUE"""),0.3986) -> 0.3986 | D49: =IFERROR(__xludf.DUMMYFUNCTION("""COMPUTED_VALUE"""),"2022Q2") -> 2022Q2 | E49: =IFERROR(__xludf.DUMMYFUNCTION("""COMPUTED_VALUE"""),0.4353) -> 0.4353 | F49: =IFERROR(__xludf.DUMMYFUNCTION("""COMPUTED_VALUE"""),0.293) -> 0.293 | O49: =MONTH(A9) -> 1 | P49: =B9 -> 401255104 | Q49: =B21 -> 293288000 | R49: =B33 -> 215785104
A50: =IFERROR(__xludf.DUMMYFUNCTION("""COMPUTED_VALUE"""),"2024Q4") -> 2024Q4 | B50: =IFERROR(__xludf.DUMMYFUNCTION("""COMPUTED_VALUE"""),0.3884) -> 0.3884 | C50: =IFERROR(__xludf.DUMMYFUNCTION("""COMPUTED_VALUE"""),0.3389) -> 0.3389 | D50: =IFERROR(__xludf.DUMMYFUNCTION("""COMPUTED_VALUE"""),"2022Q1") -> 2022Q1 | E50: =IFERROR(__xludf.DUMMYFUNCTION("""COMPUTED_VALUE"""),0.355) -> 0.355 | F50: =IFERROR(__xludf.DUMMYFUNCTION("""COMPUTED_VALUE"""),0.2336) -> 0.2336 | O50: =MONTH(A10) -> 12 | P50: =B10 -> 335003584 | Q50: =B22 -> 278163104 | R50: =B34 -> 176299904
A51: =IFERROR(__xludf.DUMMYFUNCTION("""COMPUTED_VALUE"""),"2024Q3") -> 2024Q3 | B51: =IFERROR(__xludf.DUMMYFUNCTION("""COMPUTED_VALUE"""),0.3895) -> 0.3895 | C51: =IFERROR(__xludf.DUMMYFUNCTION("""COMPUTED_VALUE"""),0.2265) -> 0.2265 | D51: =IFERROR(__xludf.DUMMYFUNCTION("""COMPUTED_VALUE"""),"2021Q4") -> 2021Q4 | E51: =IFERROR(__xludf.DUMMYFUNCTION("""COMPUTED_VALUE"""),0.212) -> 0.212 | F51: =IFERROR(__xludf.DUMMYFUNCTION("""COMPUTED_VALUE"""),0.1853) -> 0.1853 | O51: =MONTH(A11) -> 11 | P51: =B11 -> 343613792 | Q51: =B23 -> 276058400 | R51: =B35 -> 206026208
A52: =IFERROR(__xludf.DUMMYFUNCTION("""COMPUTED_VALUE"""),"2024Q2") -> 2024Q2 | B52: =IFERROR(__xludf.DUMMYFUNCTION("""COMPUTED_VALUE"""),0.4007) -> 0.4007 | C52: =IFERROR(__xludf.DUMMYFUNCTION("""COMPUTED_VALUE"""),0.0944) -> 0.0944 | D52: =IFERROR(__xludf.DUMMYFUNCTION("""COMPUTED_VALUE"""),"2021Q3") -> 2021Q3 | E52: =IFERROR(__xludf.DUMMYFUNCTION("""COMPUTED_VALUE"""),0.1634) -> 0.1634 | F52: =IFERROR(__xludf.DUMMYFUNCTION("""COMPUTED_VALUE"""),0.1666) -> 0.1666 | O52: =MONTH(A12) -> 10 | P52: =B12 -> 367473088 | Q52: =B24 -> 314239712 | R52: =B36 -> 243202800
A53: =IFERROR(__xludf.DUMMYFUNCTION("""COMPUTED_VALUE"""),"2024Q1") -> 2024Q1 | B53: =IFERROR(__xludf.DUMMYFUNCTION("""COMPUTED_VALUE"""),0.1652) -> 0.1652 | C53: =IFERROR(__xludf.DUMMYFUNCTION("""COMPUTED_VALUE"""),-0.0156) -> -0.0156 | D53: =IFERROR(__xludf.DUMMYFUNCTION("""COMPUTED_VALUE"""),"2021Q2") -> 2021Q2 | E53: =IFERROR(__xludf.DUMMYFUNCTION("""COMPUTED_VALUE"""),0.1978) -> 0.1978 | F53: =IFERROR(__xludf.DUMMYFUNCTION("""COMPUTED_VALUE"""),0.1794) -> 0.1794 | O53: =MONTH(A13) -> 9 | P53: =B13 -> 330980896 | Q53: =B25 -> 251872704 | R53: =B37 -> 180430304
A54: =IFERROR(__xludf.DUMMYFUNCTION("""COMPUTED_VALUE"""),"2023Q4") -> 2023Q4 | B54: =IFERROR(__xludf.DUMMYFUNCTION("""COMPUTED_VALUE"""),0) -> 0 | C54: =IFERROR(__xludf.DUMMYFUNCTION("""COMPUTED_VALUE"""),-0.0451) -> -0.0451 | D54: =IFERROR(__xludf.DUMMYFUNCTION("""COMPUTED_VALUE"""),"2021Q1") -> 2021Q1 | E54: =IFERROR(__xludf.DUMMYFUNCTION("""COMPUTED_VALUE"""),0.1668) -> 0.1668 | F54: =IFERROR(__xludf.DUMMYFUNCTION("""COMPUTED_VALUE"""),0.1973) -> 0.1973 | O54: =MONTH(A14) -> 8 | P54: =B14 -> 335771712 | Q54: =B26 -> 250866400 | R54: =B38 -> 188686304
A56: =D44 -> 2023Q3 | B56: =E44 -> -0.1083 | C56: =F44 -> 0.041
A57: =D45 -> 2023Q2 | B57: =E45 -> -0.0998 | C57: =F45 -> 0.1864
A58: =D46 -> 2023Q1 | B58: =E46 -> 0.0358 | C58: =F46 -> 0.3295
A85: =IFERROR(__xludf.DUMMYFUNCTION("IMPORTHTML(SUBSTITUTE(""https://fubon-ebrokerdj.fbs.com.tw/z/zc/zch/zch_股票代碼.djhtm"", ""股票代碼"",'股價預估'!E1),""table"",0)"),"台積電(2330) 月營收季盈餘") -> 台積電(2330) 月營收季盈餘
A87: =IFERROR(__xludf.DUMMYFUNCTION("""COMPUTED_VALUE"""),"台積電(2330) 年度營收走勢圖") -> 台積電(2330) 年度營收走勢圖
A89: =IFERROR(__xludf.DUMMYFUNCTION("""COMPUTED_VALUE"""),"台積電(2330)月營收明細 單位：仟元") -> 台積電(2330)月營收明細 單位：仟元
A90: =IFERROR(__xludf.DUMMYFUNCTION("""COMPUTED_VALUE"""),"年/月") -> 年/月 | B90: =IFERROR(__xludf.DUMMYFUNCTION("""COMPUTED_VALUE"""),"營收") -> 營收 | C90: =IFERROR(__xludf.DUMMYFUNCTION("""COMPUTED_VALUE"""),"月增率") -> 月增率 | D90: =IFERROR(__xludf.DUMMYFUNCTION("""COMPUTED_VALUE"""),"去年同期") -> 去年同期 | E90: =IFERROR(__xludf.DUMMYFUNCTION("""COMPUTED_VALUE"""),"年增率") -> 年增率 | F90: =IFERROR(__xludf.DUMMYFUNCTION("""COMPUTED_VALUE"""),"累計營收") -> 累計營收 | G90: =IFERROR(__xludf.DUMMYFUNCTION("""COMPUTED_VALUE"""),"年增率") -> 年增率
A91: =IFERROR(__xludf.DUMMYFUNCTION("""COMPUTED_VALUE"""),"115/07") -> 115/07 | B91: =IFERROR(__xludf.DUMMYFUNCTION("""COMPUTED_VALUE"""),467580548) -> 467580548 | C91: =IFERROR(__xludf.DUMMYFUNCTION("""COMPUTED_VALUE"""),0.0562) -> 0.0562 | D91: =IFERROR(__xludf.DUMMYFUNCTION("""COMPUTED_VALUE"""),323165707) -> 323165707 | E91: =IFERROR(__xludf.DUMMYFUNCTION("""COMPUTED_VALUE"""),0.4469) -> 0.4469 | F91: =IFERROR(__xludf.DUMMYFUNCTION("""COMPUTED_VALUE"""),2872064238) -> 2872064238 | G91: =IFERROR(__xludf.DUMMYFUNCTION("""COMPUTED_VALUE"""),0.3701) -> 0.3701
A92: =IFERROR(__xludf.DUMMYFUNCTION("""COMPUTED_VALUE"""),"115/06") -> 115/06 | B92: =IFERROR(__xludf.DUMMYFUNCTION("""COMPUTED_VALUE"""),442679969) -> 442679969 | C92: =IFERROR(__xludf.DUMMYFUNCTION("""COMPUTED_VALUE"""),0.0616) -> 0.0616 | D92: =IFERROR(__xludf.DUMMYFUNCTION("""COMPUTED_VALUE"""),263708978) -> 263708978 | E92: =IFERROR(__xludf.DUMMYFUNCTION("""COMPUTED_VALUE"""),0.6787) -> 0.6787 | F92: =IFERROR(__xludf.DUMMYFUNCTION("""COMPUTED_VALUE"""),2404483690) -> 2404483690 | G92: =IFERROR(__xludf.DUMMYFUNCTION("""COMPUTED_VALUE"""),0.3561) -> 0.3561
A93: =IFERROR(__xludf.DUMMYFUNCTION("""COMPUTED_VALUE"""),"115/05") -> 115/05 | B93: =IFERROR(__xludf.DUMMYFUNCTION("""COMPUTED_VALUE"""),416975163) -> 416975163 | C93: =IFERROR(__xludf.DUMMYFUNCTION("""COMPUTED_VALUE"""),0.0152) -> 0.0152 | D93: =IFERROR(__xludf.DUMMYFUNCTION("""COMPUTED_VALUE"""),320515951) -> 320515951 | E93: =IFERROR(__xludf.DUMMYFUNCTION("""COMPUTED_VALUE"""),0.3009) -> 0.3009 | F93: =IFERROR(__xludf.DUMMYFUNCTION("""COMPUTED_VALUE"""),1961803721) -> 1961803721 | G93: =IFERROR(__xludf.DUMMYFUNCTION("""COMPUTED_VALUE"""),0.2998) -> 0.2998
A94: =IFERROR(__xludf.DUMMYFUNCTION("""COMPUTED_VALUE"""),"115/04") -> 115/04 | B94: =IFERROR(__xludf.DUMMYFUNCTION("""COMPUTED_VALUE"""),410725118) -> 410725118 | C94: =IFERROR(__xludf.DUMMYFUNCTION("""COMPUTED_VALUE"""),-0.0108) -> -0.0108 | D94: =IFERROR(__xludf.DUMMYFUNCTION("""COMPUTED_VALUE"""),349566940) -> 349566940 | E94: =IFERROR(__xludf.DUMMYFUNCTION("""COMPUTED_VALUE"""),0.175) -> 0.175 | F94: =IFERROR(__xludf.DUMMYFUNCTION("""COMPUTED_VALUE"""),1544828558) -> 1544828558 | G94: =IFERROR(__xludf.DUMMYFUNCTION("""COMPUTED_VALUE"""),0.2995) -> 0.2995
A95: =IFERROR(__xludf.DUMMYFUNCTION("""COMPUTED_VALUE"""),"115/03") -> 115/03 | B95: =IFERROR(__xludf.DUMMYFUNCTION("""COMPUTED_VALUE"""),415191699) -> 415191699 | C95: =IFERROR(__xludf.DUMMYFUNCTION("""COMPUTED_VALUE"""),0.307) -> 0.307 | D95: =IFERROR(__xludf.DUMMYFUNCTION("""COMPUTED_VALUE"""),285956830) -> 285956830 | E95: =IFERROR(__xludf.DUMMYFUNCTION("""COMPUTED_VALUE"""),0.4519) -> 0.4519 | F95: =IFERROR(__xludf.DUMMYFUNCTION("""COMPUTED_VALUE"""),1134103440) -> 1134103440 | G95: =IFERROR(__xludf.DUMMYFUNCTION("""COMPUTED_VALUE"""),0.3513) -> 0.3513
A96: =IFERROR(__xludf.DUMMYFUNCTION("""COMPUTED_VALUE"""),"115/02") -> 115/02 | B96: =IFERROR(__xludf.DUMMYFUNCTION("""COMPUTED_VALUE"""),317656613) -> 317656613 | C96: =IFERROR(__xludf.DUMMYFUNCTION("""COMPUTED_VALUE"""),-0.2083) -> -0.2083 | D96: =IFERROR(__xludf.DUMMYFUNCTION("""COMPUTED_VALUE"""),260008796) -> 260008796 | E96: =IFERROR(__xludf.DUMMYFUNCTION("""COMPUTED_VALUE"""),0.2217) -> 0.2217 | F96: =IFERROR(__xludf.DUMMYFUNCTION("""COMPUTED_VALUE"""),718911741) -> 718911741 | G96: =IFERROR(__xludf.DUMMYFUNCTION("""COMPUTED_VALUE"""),0.2993) -> 0.2993
A97: =IFERROR(__xludf.DUMMYFUNCTION("""COMPUTED_VALUE"""),"115/01") -> 115/01 | B97: =IFERROR(__xludf.DUMMYFUNCTION("""COMPUTED_VALUE"""),401255128) -> 401255128 | C97: =IFERROR(__xludf.DUMMYFUNCTION("""COMPUTED_VALUE"""),0.1978) -> 0.1978 | D97: =IFERROR(__xludf.DUMMYFUNCTION("""COMPUTED_VALUE"""),293288038) -> 293288038 | E97: =IFERROR(__xludf.DUMMYFUNCTION("""COMPUTED_VALUE"""),0.3681) -> 0.3681 | F97: =IFERROR(__xludf.DUMMYFUNCTION("""COMPUTED_VALUE"""),401255128) -> 401255128 | G97: =IFERROR(__xludf.DUMMYFUNCTION("""COMPUTED_VALUE"""),0.3681) -> 0.3681
A98: =IFERROR(__xludf.DUMMYFUNCTION("""COMPUTED_VALUE"""),"114/12") -> 114/12 | B98: =IFERROR(__xludf.DUMMYFUNCTION("""COMPUTED_VALUE"""),335003568) -> 335003568 | C98: =IFERROR(__xludf.DUMMYFUNCTION("""COMPUTED_VALUE"""),-0.0251) -> -0.0251 | D98: =IFERROR(__xludf.DUMMYFUNCTION("""COMPUTED_VALUE"""),278163107) -> 278163107 | E98: =IFERROR(__xludf.DUMMYFUNCTION("""COMPUTED_VALUE"""),0.2043) -> 0.2043 | F98: =IFERROR(__xludf.DUMMYFUNCTION("""COMPUTED_VALUE"""),3809054272) -> 3809054272 | G98: =IFERROR(__xludf.DUMMYFUNCTION("""COMPUTED_VALUE"""),0.3161) -> 0.3161
A99: =IFERROR(__xludf.DUMMYFUNCTION("""COMPUTED_VALUE"""),"114/11") -> 114/11 | B99: =IFERROR(__xludf.DUMMYFUNCTION("""COMPUTED_VALUE"""),343613802) -> 343613802 | C99: =IFERROR(__xludf.DUMMYFUNCTION("""COMPUTED_VALUE"""),-0.0649) -> -0.0649 | D99: =IFERROR(__xludf.DUMMYFUNCTION("""COMPUTED_VALUE"""),276058358) -> 276058358 | E99: =IFERROR(__xludf.DUMMYFUNCTION("""COMPUTED_VALUE"""),0.2447) -> 0.2447 | F99: =IFERROR(__xludf.DUMMYFUNCTION("""COMPUTED_VALUE"""),3474050704) -> 3474050704 | G99: =IFERROR(__xludf.DUMMYFUNCTION("""COMPUTED_VALUE"""),0.3279) -> 0.3279
A100: =IFERROR(__xludf.DUMMYFUNCTION("""COMPUTED_VALUE"""),"114/10") -> 114/10 | B100: =IFERROR(__xludf.DUMMYFUNCTION("""COMPUTED_VALUE"""),367473051) -> 367473051 | C100: =IFERROR(__xludf.DUMMYFUNCTION("""COMPUTED_VALUE"""),0.1103) -> 0.1103 | D100: =IFERROR(__xludf.DUMMYFUNCTION("""COMPUTED_VALUE"""),314239713) -> 314239713 | E100: =IFERROR(__xludf.DUMMYFUNCTION("""COMPUTED_VALUE"""),0.1694) -> 0.1694 | F100: =IFERROR(__xludf.DUMMYFUNCTION("""COMPUTED_VALUE"""),3130436902) -> 3130436902 | G100: =IFERROR(__xludf.DUMMYFUNCTION("""COMPUTED_VALUE"""),0.3377) -> 0.3377
A101: =IFERROR(__xludf.DUMMYFUNCTION("""COMPUTED_VALUE"""),"114/09") -> 114/09 | B101: =IFERROR(__xludf.DUMMYFUNCTION("""COMPUTED_VALUE"""),330980920) -> 330980920 | C101: =IFERROR(__xludf.DUMMYFUNCTION("""COMPUTED_VALUE"""),-0.0143) -> -0.0143 | D101: =IFERROR(__xludf.DUMMYFUNCTION("""COMPUTED_VALUE"""),251872717) -> 251872717 | E101: =IFERROR(__xludf.DUMMYFUNCTION("""COMPUTED_VALUE"""),0.3141) -> 0.3141 | F101: =IFERROR(__xludf.DUMMYFUNCTION("""COMPUTED_VALUE"""),2762963851) -> 2762963851 | G101: =IFERROR(__xludf.DUMMYFUNCTION("""COMPUTED_VALUE"""),0.3639) -> 0.3639
A102: =IFERROR(__xludf.DUMMYFUNCTION("""COMPUTED_VALUE"""),"114/08") -> 114/08 | B102: =IFERROR(__xludf.DUMMYFUNCTION("""COMPUTED_VALUE"""),335771691) -> 335771691 | C102: =IFERROR(__xludf.DUMMYFUNCTION("""COMPUTED_VALUE"""),0.039) -> 0.039 | D102: =IFERROR(__xludf.DUMMYFUNCTION("""COMPUTED_VALUE"""),250866368) -> 250866368 | E102: =IFERROR(__xludf.DUMMYFUNCTION("""COMPUTED_VALUE"""),0.3384) -> 0.3384 | F102: =IFERROR(__xludf.DUMMYFUNCTION("""COMPUTED_VALUE"""),2431982931) -> 2431982931 | G102: =IFERROR(__xludf.DUMMYFUNCTION("""COMPUTED_VALUE"""),0.3709) -> 0.3709
A103: =IFERROR(__xludf.DUMMYFUNCTION("""COMPUTED_VALUE"""),"114/07") -> 114/07 | B103: =IFERROR(__xludf.DUMMYFUNCTION("""COMPUTED_VALUE"""),323165707) -> 323165707 | C103: =IFERROR(__xludf.DUMMYFUNCTION("""COMPUTED_VALUE"""),0.2255) -> 0.2255 | D103: =IFERROR(__xludf.DUMMYFUNCTION("""COMPUTED_VALUE"""),256953058) -> 256953058 | E103: =IFERROR(__xludf.DUMMYFUNCTION("""COMPUTED_VALUE"""),0.2577) -> 0.2577 | F103: =IFERROR(__xludf.DUMMYFUNCTION("""COMPUTED_VALUE"""),2096211240) -> 2096211240 | G103: =IFERROR(__xludf.DUMMYFUNCTION("""COMPUTED_VALUE"""),0.3763) -> 0.3763
A104: =IFERROR(__xludf.DUMMYFUNCTION("""COMPUTED_VALUE"""),"114/06") -> 114/06 | B104: =IFERROR(__xludf.DUMMYFUNCTION("""COMPUTED_VALUE"""),263708978) -> 263708978 | C104: =IFERROR(__xludf.DUMMYFUNCTION("""COMPUTED_VALUE"""),-0.1772) -> -0.1772 | D104: =IFERROR(__xludf.DUMMYFUNCTION("""COMPUTED_VALUE"""),207868693) -> 207868693 | E104: =IFERROR(__xludf.DUMMYFUNCTION("""COMPUTED_VALUE"""),0.2686) -> 0.2686 | F104: =IFERROR(__xludf.DUMMYFUNCTION("""COMPUTED_VALUE"""),1773045533) -> 1773045533 | G104: =IFERROR(__xludf.DUMMYFUNCTION("""COMPUTED_VALUE"""),0.4003) -> 0.4003
A105: =IFERROR(__xludf.DUMMYFUNCTION("""COMPUTED_VALUE"""),"114/05") -> 114/05 | B105: =IFERROR(__xludf.DUMMYFUNCTION("""COMPUTED_VALUE"""),320515951) -> 320515951 | C105: =IFERROR(__xludf.DUMMYFUNCTION("""COMPUTED_VALUE"""),-0.0831) -> -0.0831 | D105: =IFERROR(__xludf.DUMMYFUNCTION("""COMPUTED_VALUE"""),229620372) -> 229620372 | E105: =IFERROR(__xludf.DUMMYFUNCTION("""COMPUTED_VALUE"""),0.3959) -> 0.3959 | F105: =IFERROR(__xludf.DUMMYFUNCTION("""COMPUTED_VALUE"""),1509336555) -> 1509336555 | G105: =IFERROR(__xludf.DUMMYFUNCTION("""COMPUTED_VALUE"""),0.4262) -> 0.4262
A106: =IFERROR(__xludf.DUMMYFUNCTION("""COMPUTED_VALUE"""),"114/04") -> 114/04 | B106: =IFERROR(__xludf.DUMMYFUNCTION("""COMPUTED_VALUE"""),349566940) -> 349566940 | C106: =IFERROR(__xludf.DUMMYFUNCTION("""COMPUTED_VALUE"""),0.2224) -> 0.2224 | D106: =IFERROR(__xludf.DUMMYFUNCTION("""COMPUTED_VALUE"""),236021112) -> 236021112 | E106: =IFERROR(__xludf.DUMMYFUNCTION("""COMPUTED_VALUE"""),0.4811) -> 0.4811 | F106: =IFERROR(__xludf.DUMMYFUNCTION("""COMPUTED_VALUE"""),1188820604) -> 1188820604 | G106: =IFERROR(__xludf.DUMMYFUNCTION("""COMPUTED_VALUE"""),0.4346) -> 0.4346
A107: =IFERROR(__xludf.DUMMYFUNCTION("""COMPUTED_VALUE"""),"114/03") -> 114/03 | B107: =IFERROR(__xludf.DUMMYFUNCTION("""COMPUTED_VALUE"""),285956830) -> 285956830 | C107: =IFERROR(__xludf.DUMMYFUNCTION("""COMPUTED_VALUE"""),0.0998) -> 0.0998 | D107: =IFERROR(__xludf.DUMMYFUNCTION("""COMPUTED_VALUE"""),195210804) -> 195210804 | E107: =IFERROR(__xludf.DUMMYFUNCTION("""COMPUTED_VALUE"""),0.4649) -> 0.4649 | F107: =IFERROR(__xludf.DUMMYFUNCTION("""COMPUTED_VALUE"""),839253664) -> 839253664 | G107: =IFERROR(__xludf.DUMMYFUNCTION("""COMPUTED_VALUE"""),0.4161) -> 0.4161
A108: =IFERROR(__xludf.DUMMYFUNCTION("""COMPUTED_VALUE"""),"114/02") -> 114/02 | B108: =IFERROR(__xludf.DUMMYFUNCTION("""COMPUTED_VALUE"""),260008796) -> 260008796 | C108: =IFERROR(__xludf.DUMMYFUNCTION("""COMPUTED_VALUE"""),-0.1135) -> -0.1135 | D108: =IFERROR(__xludf.DUMMYFUNCTION("""COMPUTED_VALUE"""),181648270) -> 181648270 | E108: =IFERROR(__xludf.DUMMYFUNCTION("""COMPUTED_VALUE"""),0.4314) -> 0.4314 | F108: =IFERROR(__xludf.DUMMYFUNCTION("""COMPUTED_VALUE"""),553296834) -> 553296834 | G108: =IFERROR(__xludf.DUMMYFUNCTION("""COMPUTED_VALUE"""),0.3922) -> 0.3922
A109: =IFERROR(__xludf.DUMMYFUNCTION("""COMPUTED_VALUE"""),"114/01") -> 114/01 | B109: =IFERROR(__xludf.DUMMYFUNCTION("""COMPUTED_VALUE"""),293288038) -> 293288038 | C109: =IFERROR(__xludf.DUMMYFUNCTION("""COMPUTED_VALUE"""),0.0544) -> 0.0544 | D109: =IFERROR(__xludf.DUMMYFUNCTION("""COMPUTED_VALUE"""),215785127) -> 215785127 | E109: =IFERROR(__xludf.DUMMYFUNCTION("""COMPUTED_VALUE"""),0.3592) -> 0.3592 | F109: =IFERROR(__xludf.DUMMYFUNCTION("""COMPUTED_VALUE"""),293288038) -> 293288038 | G109: =IFERROR(__xludf.DUMMYFUNCTION("""COMPUTED_VALUE"""),0.3592) -> 0.3592
A110: =IFERROR(__xludf.DUMMYFUNCTION("""COMPUTED_VALUE"""),"113/12") -> 113/12 | B110: =IFERROR(__xludf.DUMMYFUNCTION("""COMPUTED_VALUE"""),278163107) -> 278163107 | C110: =IFERROR(__xludf.DUMMYFUNCTION("""COMPUTED_VALUE"""),0.0076) -> 0.0076 | D110: =IFERROR(__xludf.DUMMYFUNCTION("""COMPUTED_VALUE"""),176299866) -> 176299866 | E110: =IFERROR(__xludf.DUMMYFUNCTION("""COMPUTED_VALUE"""),0.5778) -> 0.5778 | F110: =IFERROR(__xludf.DUMMYFUNCTION("""COMPUTED_VALUE"""),2894307699) -> 2894307699 | G110: =IFERROR(__xludf.DUMMYFUNCTION("""COMPUTED_VALUE"""),0.3389) -> 0.3389
A111: =IFERROR(__xludf.DUMMYFUNCTION("""COMPUTED_VALUE"""),"113/11") -> 113/11 | B111: =IFERROR(__xludf.DUMMYFUNCTION("""COMPUTED_VALUE"""),276058358) -> 276058358 | C111: =IFERROR(__xludf.DUMMYFUNCTION("""COMPUTED_VALUE"""),-0.1215) -> -0.1215 | D111: =IFERROR(__xludf.DUMMYFUNCTION("""COMPUTED_VALUE"""),206026179) -> 206026179 | E111: =IFERROR(__xludf.DUMMYFUNCTION("""COMPUTED_VALUE"""),0.3399) -> 0.3399 | F111: =IFERROR(__xludf.DUMMYFUNCTION("""COMPUTED_VALUE"""),2616144592) -> 2616144592 | G111: =IFERROR(__xludf.DUMMYFUNCTION("""COMPUTED_VALUE"""),0.3177) -> 0.3177
A112: =IFERROR(__xludf.DUMMYFUNCTION("""COMPUTED_VALUE"""),"113/10") -> 113/10 | B112: =IFERROR(__xludf.DUMMYFUNCTION("""COMPUTED_VALUE"""),314239713) -> 314239713 | C112: =IFERROR(__xludf.DUMMYFUNCTION("""COMPUTED_VALUE"""),0.2476) -> 0.2476 | D112: =IFERROR(__xludf.DUMMYFUNCTION("""COMPUTED_VALUE"""),243202811) -> 243202811 | E112: =IFERROR(__xludf.DUMMYFUNCTION("""COMPUTED_VALUE"""),0.2921) -> 0.2921 | F112: =IFERROR(__xludf.DUMMYFUNCTION("""COMPUTED_VALUE"""),2340086234) -> 2340086234 | G112: =IFERROR(__xludf.DUMMYFUNCTION("""COMPUTED_VALUE"""),0.3151) -> 0.3151
A113: =IFERROR(__xludf.DUMMYFUNCTION("""COMPUTED_VALUE"""),"113/09") -> 113/09 | B113: =IFERROR(__xludf.DUMMYFUNCTION("""COMPUTED_VALUE"""),251872717) -> 251872717 | C113: =IFERROR(__xludf.DUMMYFUNCTION("""COMPUTED_VALUE"""),0.004) -> 0.004 | D113: =IFERROR(__xludf.DUMMYFUNCTION("""COMPUTED_VALUE"""),180430282) -> 180430282 | E113: =IFERROR(__xludf.DUMMYFUNCTION("""COMPUTED_VALUE"""),0.396) -> 0.396 | F113: =IFERROR(__xludf.DUMMYFUNCTION("""COMPUTED_VALUE"""),2025846521) -> 2025846521 | G113: =IFERROR(__xludf.DUMMYFUNCTION("""COMPUTED_VALUE"""),0.3187) -> 0.3187
A114: =IFERROR(__xludf.DUMMYFUNCTION("""COMPUTED_VALUE"""),"113/08") -> 113/08 | B114: =IFERROR(__xludf.DUMMYFUNCTION("""COMPUTED_VALUE"""),250866368) -> 250866368 | C114: =IFERROR(__xludf.DUMMYFUNCTION("""COMPUTED_VALUE"""),-0.0237) -> -0.0237 | D114: =IFERROR(__xludf.DUMMYFUNCTION("""COMPUTED_VALUE"""),188686256) -> 188686256 | E114: =IFERROR(__xludf.DUMMYFUNCTION("""COMPUTED_VALUE"""),0.3295) -> 0.3295 | F114: =IFERROR(__xludf.DUMMYFUNCTION("""COMPUTED_VALUE"""),1773973804) -> 1773973804 | G114: =IFERROR(__xludf.DUMMYFUNCTION("""COMPUTED_VALUE"""),0.3085) -> 0.3085
A115: =IFERROR(__xludf.DUMMYFUNCTION("""COMPUTED_VALUE"""),"113/07") -> 113/07 | B115: =IFERROR(__xludf.DUMMYFUNCTION("""COMPUTED_VALUE"""),256953058) -> 256953058 | C115: =IFERROR(__xludf.DUMMYFUNCTION("""COMPUTED_VALUE"""),0.2361) -> 0.2361 | D115: =IFERROR(__xludf.DUMMYFUNCTION("""COMPUTED_VALUE"""),177616220) -> 177616220 | E115: =IFERROR(__xludf.DUMMYFUNCTION("""COMPUTED_VALUE"""),0.4467) -> 0.4467 | F115: =IFERROR(__xludf.DUMMYFUNCTION("""COMPUTED_VALUE"""),1523107436) -> 1523107436 | G115: =IFERROR(__xludf.DUMMYFUNCTION("""COMPUTED_VALUE"""),0.305) -> 0.305
A116: =IFERROR(__xludf.DUMMYFUNCTION("""COMPUTED_VALUE"""),"113/06") -> 113/06 | B116: =IFERROR(__xludf.DUMMYFUNCTION("""COMPUTED_VALUE"""),207868693) -> 207868693 | C116: =IFERROR(__xludf.DUMMYFUNCTION("""COMPUTED_VALUE"""),-0.0947) -> -0.0947 | D116: =IFERROR(__xludf.DUMMYFUNCTION("""COMPUTED_VALUE"""),156404174) -> 156404174 | E116: =IFERROR(__xludf.DUMMYFUNCTION("""COMPUTED_VALUE"""),0.329) -> 0.329 | F116: =IFERROR(__xludf.DUMMYFUNCTION("""COMPUTED_VALUE"""),1266154378) -> 1266154378 | G116: =IFERROR(__xludf.DUMMYFUNCTION("""COMPUTED_VALUE"""),0.2796) -> 0.2796
A117: =IFERROR(__xludf.DUMMYFUNCTION("""COMPUTED_VALUE"""),"113/05") -> 113/05 | B117: =IFERROR(__xludf.DUMMYFUNCTION("""COMPUTED_VALUE"""),229620372) -> 229620372 | C117: =IFERROR(__xludf.DUMMYFUNCTION("""COMPUTED_VALUE"""),-0.0271) -> -0.0271 | D117: =IFERROR(__xludf.DUMMYFUNCTION("""COMPUTED_VALUE"""),176537345) -> 176537345 | E117: =IFERROR(__xludf.DUMMYFUNCTION("""COMPUTED_VALUE"""),0.3007) -> 0.3007 | F117: =IFERROR(__xludf.DUMMYFUNCTION("""COMPUTED_VALUE"""),1058285685) -> 1058285685 | G117: =IFERROR(__xludf.DUMMYFUNCTION("""COMPUTED_VALUE"""),0.2703) -> 0.2703
A118: =IFERROR(__xludf.DUMMYFUNCTION("""COMPUTED_VALUE"""),"113/04") -> 113/04 | B118: =IFERROR(__xludf.DUMMYFUNCTION("""COMPUTED_VALUE"""),236021112) -> 236021112 | C118: =IFERROR(__xludf.DUMMYFUNCTION("""COMPUTED_VALUE"""),0.2091) -> 0.2091 | D118: =IFERROR(__xludf.DUMMYFUNCTION("""COMPUTED_VALUE"""),147899735) -> 147899735 | E118: =IFERROR(__xludf.DUMMYFUNCTION("""COMPUTED_VALUE"""),0.5958) -> 0.5958 | F118: =IFERROR(__xludf.DUMMYFUNCTION("""COMPUTED_VALUE"""),828665313) -> 828665313 | G118: =IFERROR(__xludf.DUMMYFUNCTION("""COMPUTED_VALUE"""),0.2622) -> 0.2622
A119: =IFERROR(__xludf.DUMMYFUNCTION("""COMPUTED_VALUE"""),"113/03") -> 113/03 | B119: =IFERROR(__xludf.DUMMYFUNCTION("""COMPUTED_VALUE"""),195210804) -> 195210804 | C119: =IFERROR(__xludf.DUMMYFUNCTION("""COMPUTED_VALUE"""),0.0747) -> 0.0747 | D119: =IFERROR(__xludf.DUMMYFUNCTION("""COMPUTED_VALUE"""),145408332) -> 145408332 | E119: =IFERROR(__xludf.DUMMYFUNCTION("""COMPUTED_VALUE"""),0.3425) -> 0.3425 | F119: =IFERROR(__xludf.DUMMYFUNCTION("""COMPUTED_VALUE"""),592644201) -> 592644201 | G119: =IFERROR(__xludf.DUMMYFUNCTION("""COMPUTED_VALUE"""),0.1652) -> 0.1652
A120: =IFERROR(__xludf.DUMMYFUNCTION("""COMPUTED_VALUE"""),"113/02") -> 113/02 | B120: =IFERROR(__xludf.DUMMYFUNCTION("""COMPUTED_VALUE"""),181648270) -> 181648270 | C120: =IFERROR(__xludf.DUMMYFUNCTION("""COMPUTED_VALUE"""),-0.1582) -> -0.1582 | D120: =IFERROR(__xludf.DUMMYFUNCTION("""COMPUTED_VALUE"""),163174097) -> 163174097 | E120: =IFERROR(__xludf.DUMMYFUNCTION("""COMPUTED_VALUE"""),0.1132) -> 0.1132 | F120: =IFERROR(__xludf.DUMMYFUNCTION("""COMPUTED_VALUE"""),397433397) -> 397433397 | G120: =IFERROR(__xludf.DUMMYFUNCTION("""COMPUTED_VALUE"""),0.0942) -> 0.0942
A121: =IFERROR(__xludf.DUMMYFUNCTION("""COMPUTED_VALUE"""),"113/01") -> 113/01 | B121: =IFERROR(__xludf.DUMMYFUNCTION("""COMPUTED_VALUE"""),215785127) -> 215785127 | C121: =IFERROR(__xludf.DUMMYFUNCTION("""COMPUTED_VALUE"""),0.224) -> 0.224 | D121: =IFERROR(__xludf.DUMMYFUNCTION("""COMPUTED_VALUE"""),200050544) -> 200050544 | E121: =IFERROR(__xludf.DUMMYFUNCTION("""COMPUTED_VALUE"""),0.0787) -> 0.0787 | F121: =IFERROR(__xludf.DUMMYFUNCTION("""COMPUTED_VALUE"""),215785127) -> 215785127 | G121: =IFERROR(__xludf.DUMMYFUNCTION("""COMPUTED_VALUE"""),0.0787) -> 0.0787
A122: =IFERROR(__xludf.DUMMYFUNCTION("""COMPUTED_VALUE"""),"112/12") -> 112/12 | B122: =IFERROR(__xludf.DUMMYFUNCTION("""COMPUTED_VALUE"""),176299866) -> 176299866 | C122: =IFERROR(__xludf.DUMMYFUNCTION("""COMPUTED_VALUE"""),-0.1443) -> -0.1443 | D122: =IFERROR(__xludf.DUMMYFUNCTION("""COMPUTED_VALUE"""),192560242) -> 192560242 | E122: =IFERROR(__xludf.DUMMYFUNCTION("""COMPUTED_VALUE"""),-0.0844) -> -0.0844 | F122: =IFERROR(__xludf.DUMMYFUNCTION("""COMPUTED_VALUE"""),2161735841) -> 2161735841 | G122: =IFERROR(__xludf.DUMMYFUNCTION("""COMPUTED_VALUE"""),-0.0451) -> -0.0451
A123: =IFERROR(__xludf.DUMMYFUNCTION("""COMPUTED_VALUE"""),"112/11") -> 112/11 | B123: =IFERROR(__xludf.DUMMYFUNCTION("""COMPUTED_VALUE"""),206026179) -> 206026179 | C123: =IFERROR(__xludf.DUMMYFUNCTION("""COMPUTED_VALUE"""),-0.1529) -> -0.1529 | D123: =IFERROR(__xludf.DUMMYFUNCTION("""COMPUTED_VALUE"""),222705993) -> 222705993 | E123: =IFERROR(__xludf.DUMMYFUNCTION("""COMPUTED_VALUE"""),-0.0749) -> -0.0749 | F123: =IFERROR(__xludf.DUMMYFUNCTION("""COMPUTED_VALUE"""),1985435975) -> 1985435975 | G123: =IFERROR(__xludf.DUMMYFUNCTION("""COMPUTED_VALUE"""),-0.0415) -> -0.0415
A124: =IFERROR(__xludf.DUMMYFUNCTION("""COMPUTED_VALUE"""),"112/10") -> 112/10 | B124: =IFERROR(__xludf.DUMMYFUNCTION("""COMPUTED_VALUE"""),243202811) -> 243202811 | C124: =IFERROR(__xludf.DUMMYFUNCTION("""COMPUTED_VALUE"""),0.3479) -> 0.3479 | D124: =IFERROR(__xludf.DUMMYFUNCTION("""COMPUTED_VALUE"""),210265633) -> 210265633 | E124: =IFERROR(__xludf.DUMMYFUNCTION("""COMPUTED_VALUE"""),0.1566) -> 0.1566 | F124: =IFERROR(__xludf.DUMMYFUNCTION("""COMPUTED_VALUE"""),1779409796) -> 1779409796 | G124: =IFERROR(__xludf.DUMMYFUNCTION("""COMPUTED_VALUE"""),-0.0374) -> -0.0374
A125: =IFERROR(__xludf.DUMMYFUNCTION("""COMPUTED_VALUE"""),"112/09") -> 112/09 | B125: =IFERROR(__xludf.DUMMYFUNCTION("""COMPUTED_VALUE"""),180430282) -> 180430282 | C125: =IFERROR(__xludf.DUMMYFUNCTION("""COMPUTED_VALUE"""),-0.0438) -> -0.0438 | D125: =IFERROR(__xludf.DUMMYFUNCTION("""COMPUTED_VALUE"""),208247663) -> 208247663 | E125: =IFERROR(__xludf.DUMMYFUNCTION("""COMPUTED_VALUE"""),-0.1336) -> -0.1336 | F125: =IFERROR(__xludf.DUMMYFUNCTION("""COMPUTED_VALUE"""),1536206985) -> 1536206985 | G125: =IFERROR(__xludf.DUMMYFUNCTION("""COMPUTED_VALUE"""),-0.0624) -> -0.0624
A126: =IFERROR(__xludf.DUMMYFUNCTION("""COMPUTED_VALUE"""),"112/08") -> 112/08 | B126: =IFERROR(__xludf.DUMMYFUNCTION("""COMPUTED_VALUE"""),188686256) -> 188686256 | C126: =IFERROR(__xludf.DUMMYFUNCTION("""COMPUTED_VALUE"""),0.0623) -> 0.0623 | D126: =IFERROR(__xludf.DUMMYFUNCTION("""COMPUTED_VALUE"""),218132391) -> 218132391 | E126: =IFERROR(__xludf.DUMMYFUNCTION("""COMPUTED_VALUE"""),-0.135) -> -0.135 | F126: =IFERROR(__xludf.DUMMYFUNCTION("""COMPUTED_VALUE"""),1355776703) -> 1355776703 | G126: =IFERROR(__xludf.DUMMYFUNCTION("""COMPUTED_VALUE"""),-0.052) -> -0.052
A127: =IFERROR(__xludf.DUMMYFUNCTION("""COMPUTED_VALUE"""),"112/07") -> 112/07 | B127: =IFERROR(__xludf.DUMMYFUNCTION("""COMPUTED_VALUE"""),177616220) -> 177616220 | C127: =IFERROR(__xludf.DUMMYFUNCTION("""COMPUTED_VALUE"""),0.1356) -> 0.1356 | D127: =IFERROR(__xludf.DUMMYFUNCTION("""COMPUTED_VALUE"""),186762689) -> 186762689 | E127: =IFERROR(__xludf.DUMMYFUNCTION("""COMPUTED_VALUE"""),-0.049) -> -0.049 | F127: =IFERROR(__xludf.DUMMYFUNCTION("""COMPUTED_VALUE"""),1167090447) -> 1167090447 | G127: =IFERROR(__xludf.DUMMYFUNCTION("""COMPUTED_VALUE"""),-0.037) -> -0.037
A128: =IFERROR(__xludf.DUMMYFUNCTION("""COMPUTED_VALUE"""),"112/06") -> 112/06 | B128: =IFERROR(__xludf.DUMMYFUNCTION("""COMPUTED_VALUE"""),156404174) -> 156404174 | C128: =IFERROR(__xludf.DUMMYFUNCTION("""COMPUTED_VALUE"""),-0.114) -> -0.114 | F128: =IFERROR(__xludf.DUMMYFUNCTION("""COMPUTED_VALUE"""),989474227) -> 989474227
A129: =IFERROR(__xludf.DUMMYFUNCTION("""COMPUTED_VALUE"""),"112/05") -> 112/05 | B129: =IFERROR(__xludf.DUMMYFUNCTION("""COMPUTED_VALUE"""),176537345) -> 176537345 | C129: =IFERROR(__xludf.DUMMYFUNCTION("""COMPUTED_VALUE"""),0.1936) -> 0.1936 | F129: =IFERROR(__xludf.DUMMYFUNCTION("""COMPUTED_VALUE"""),833070053) -> 833070053
A130: =IFERROR(__xludf.DUMMYFUNCTION("""COMPUTED_VALUE"""),"112/04") -> 112/04 | B130: =IFERROR(__xludf.DUMMYFUNCTION("""COMPUTED_VALUE"""),147899735) -> 147899735 | C130: =IFERROR(__xludf.DUMMYFUNCTION("""COMPUTED_VALUE"""),0.0171) -> 0.0171 | F130: =IFERROR(__xludf.DUMMYFUNCTION("""COMPUTED_VALUE"""),656532708) -> 656532708
A131: =IFERROR(__xludf.DUMMYFUNCTION("""COMPUTED_VALUE"""),"112/03") -> 112/03 | B131: =IFERROR(__xludf.DUMMYFUNCTION("""COMPUTED_VALUE"""),145408332) -> 145408332 | C131: =IFERROR(__xludf.DUMMYFUNCTION("""COMPUTED_VALUE"""),-0.1089) -> -0.1089 | F131: =IFERROR(__xludf.DUMMYFUNCTION("""COMPUTED_VALUE"""),508632973) -> 508632973
A132: =IFERROR(__xludf.DUMMYFUNCTION("""COMPUTED_VALUE"""),"112/02") -> 112/02 | B132: =IFERROR(__xludf.DUMMYFUNCTION("""COMPUTED_VALUE"""),163174097) -> 163174097 | C132: =IFERROR(__xludf.DUMMYFUNCTION("""COMPUTED_VALUE"""),-0.1843) -> -0.1843 | F132: =IFERROR(__xludf.DUMMYFUNCTION("""COMPUTED_VALUE"""),363224641) -> 363224641
...

Sheet 毛利率&業外
A1: =IFERROR(__xludf.DUMMYFUNCTION("IMPORTHTML(SUBSTITUTE(""https://fubon-ebrokerdj.fbs.com.tw/z/zc/zce/zce_股票代碼.djhtm"", ""股票代碼"",'股價預估'!E1),""table"",0)"),"台積電(2330)獲利能力分析 季報 單位：百萬") -> 台積電(2330)獲利能力分析 季報 單位：百萬 | N1: ="★ 最新毛利率 "&TEXT(E4,"0.0%")&" 營益率 "&TEXT(G4,"0.0%")&" 業外占比 "&TEXT(L4,"0.0%") -> ★ 最新毛利率 67.7% 營益率 60.3% 業外占比 11.1%
A3: =IFERROR(__xludf.DUMMYFUNCTION("""COMPUTED_VALUE"""),"季別") -> 季別 | B3: =IFERROR(__xludf.DUMMYFUNCTION("""COMPUTED_VALUE"""),"營業收入") -> 營業收入 | C3: =IFERROR(__xludf.DUMMYFUNCTION("""COMPUTED_VALUE"""),"營業成本") -> 營業成本 | D3: =IFERROR(__xludf.DUMMYFUNCTION("""COMPUTED_VALUE"""),"營業毛利") -> 營業毛利 | E3: =IFERROR(__xludf.DUMMYFUNCTION("""COMPUTED_VALUE"""),"毛利率") -> 毛利率 | F3: =IFERROR(__xludf.DUMMYFUNCTION("""COMPUTED_VALUE"""),"營業利益") -> 營業利益 | G3: =IFERROR(__xludf.DUMMYFUNCTION("""COMPUTED_VALUE"""),"營益率") -> 營益率 | H3: =IFERROR(__xludf.DUMMYFUNCTION("""COMPUTED_VALUE"""),"業外收支") -> 業外收支 | I3: =IFERROR(__xludf.DUMMYFUNCTION("""COMPUTED_VALUE"""),"稅前淨利") -> 稅前淨利 | J3: =IFERROR(__xludf.DUMMYFUNCTION("""COMPUTED_VALUE"""),"稅後淨利") -> 稅後淨利 | K3: =IFERROR(__xludf.DUMMYFUNCTION("""COMPUTED_VALUE"""),"EPS(元)") -> EPS(元) | L3: 業外占比
A4: =IFERROR(__xludf.DUMMYFUNCTION("""COMPUTED_VALUE"""),"115.2Q") -> 115.2Q | B4: =IFERROR(__xludf.DUMMYFUNCTION("""COMPUTED_VALUE"""),1270380) -> 1270380 | C4: =IFERROR(__xludf.DUMMYFUNCTION("""COMPUTED_VALUE"""),410070) -> 410070 | D4: =IFERROR(__xludf.DUMMYFUNCTION("""COMPUTED_VALUE"""),860311) -> 860311 | E4: =IFERROR(__xludf.DUMMYFUNCTION("""COMPUTED_VALUE"""),0.6772) -> 0.6772 | F4: =IFERROR(__xludf.DUMMYFUNCTION("""COMPUTED_VALUE"""),766603) -> 766603 | G4: =IFERROR(__xludf.DUMMYFUNCTION("""COMPUTED_VALUE"""),0.6034) -> 0.6034 | H4: =IFERROR(__xludf.DUMMYFUNCTION("""COMPUTED_VALUE"""),95827) -> 95827 | I4: =IFERROR(__xludf.DUMMYFUNCTION("""COMPUTED_VALUE"""),862430) -> 862430 | J4: =IFERROR(__xludf.DUMMYFUNCTION("""COMPUTED_VALUE"""),706562) -> 706562 | K4: =IFERROR(__xludf.DUMMYFUNCTION("""COMPUTED_VALUE"""),27.25) -> 27.25 | L4: =H4/I4 -> 0.11111279 | N4: =AVERAGE(L4:L7) -> 0.061594344
A5: =IFERROR(__xludf.DUMMYFUNCTION("""COMPUTED_VALUE"""),"115.1Q") -> 115.1Q | B5: =IFERROR(__xludf.DUMMYFUNCTION("""COMPUTED_VALUE"""),1134103) -> 1134103 | C5: =IFERROR(__xludf.DUMMYFUNCTION("""COMPUTED_VALUE"""),382808) -> 382808 | D5: =IFERROR(__xludf.DUMMYFUNCTION("""COMPUTED_VALUE"""),751295) -> 751295 | E5: =IFERROR(__xludf.DUMMYFUNCTION("""COMPUTED_VALUE"""),0.6625) -> 0.6625 | F5: =IFERROR(__xludf.DUMMYFUNCTION("""COMPUTED_VALUE"""),658966) -> 658966 | G5: =IFERROR(__xludf.DUMMYFUNCTION("""COMPUTED_VALUE"""),0.581) -> 0.581 | H5: =IFERROR(__xludf.DUMMYFUNCTION("""COMPUTED_VALUE"""),28834) -> 28834 | I5: =IFERROR(__xludf.DUMMYFUNCTION("""COMPUTED_VALUE"""),687800) -> 687800 | J5: =IFERROR(__xludf.DUMMYFUNCTION("""COMPUTED_VALUE"""),572480) -> 572480 | K5: =IFERROR(__xludf.DUMMYFUNCTION("""COMPUTED_VALUE"""),22.08) -> 22.08 | L5: =H5/I5 -> 0.04192207
A6: =IFERROR(__xludf.DUMMYFUNCTION("""COMPUTED_VALUE"""),"114.4Q") -> 114.4Q | B6: =IFERROR(__xludf.DUMMYFUNCTION("""COMPUTED_VALUE"""),1046090) -> 1046090 | C6: =IFERROR(__xludf.DUMMYFUNCTION("""COMPUTED_VALUE"""),394104) -> 394104 | D6: =IFERROR(__xludf.DUMMYFUNCTION("""COMPUTED_VALUE"""),651987) -> 651987 | E6: =IFERROR(__xludf.DUMMYFUNCTION("""COMPUTED_VALUE"""),0.6233) -> 0.6233 | F6: =IFERROR(__xludf.DUMMYFUNCTION("""COMPUTED_VALUE"""),564902) -> 564902 | G6: =IFERROR(__xludf.DUMMYFUNCTION("""COMPUTED_VALUE"""),0.54) -> 0.54 | H6: =IFERROR(__xludf.DUMMYFUNCTION("""COMPUTED_VALUE"""),27461) -> 27461 | I6: =IFERROR(__xludf.DUMMYFUNCTION("""COMPUTED_VALUE"""),592363) -> 592363 | J6: =IFERROR(__xludf.DUMMYFUNCTION("""COMPUTED_VALUE"""),505744) -> 505744 | K6: =IFERROR(__xludf.DUMMYFUNCTION("""COMPUTED_VALUE"""),19.51) -> 19.51 | L6: =H6/I6 -> 0.046358398
A7: =IFERROR(__xludf.DUMMYFUNCTION("""COMPUTED_VALUE"""),"114.3Q") -> 114.3Q | B7: =IFERROR(__xludf.DUMMYFUNCTION("""COMPUTED_VALUE"""),989918) -> 989918 | C7: =IFERROR(__xludf.DUMMYFUNCTION("""COMPUTED_VALUE"""),401375) -> 401375 | D7: =IFERROR(__xludf.DUMMYFUNCTION("""COMPUTED_VALUE"""),588543) -> 588543 | E7: =IFERROR(__xludf.DUMMYFUNCTION("""COMPUTED_VALUE"""),0.5945) -> 0.5945 | F7: =IFERROR(__xludf.DUMMYFUNCTION("""COMPUTED_VALUE"""),500685) -> 500685 | G7: =IFERROR(__xludf.DUMMYFUNCTION("""COMPUTED_VALUE"""),0.5058) -> 0.5058 | H7: =IFERROR(__xludf.DUMMYFUNCTION("""COMPUTED_VALUE"""),24684) -> 24684 | I7: =IFERROR(__xludf.DUMMYFUNCTION("""COMPUTED_VALUE"""),525369) -> 525369 | J7: =IFERROR(__xludf.DUMMYFUNCTION("""COMPUTED_VALUE"""),452301) -> 452301 | K7: =IFERROR(__xludf.DUMMYFUNCTION("""COMPUTED_VALUE"""),17.44) -> 17.44 | L7: =H7/I7 -> 0.04698412
A8: =IFERROR(__xludf.DUMMYFUNCTION("""COMPUTED_VALUE"""),"114.2Q") -> 114.2Q | B8: =IFERROR(__xludf.DUMMYFUNCTION("""COMPUTED_VALUE"""),933792) -> 933792 | C8: =IFERROR(__xludf.DUMMYFUNCTION("""COMPUTED_VALUE"""),386423) -> 386423 | D8: =IFERROR(__xludf.DUMMYFUNCTION("""COMPUTED_VALUE"""),547369) -> 547369 | E8: =IFERROR(__xludf.DUMMYFUNCTION("""COMPUTED_VALUE"""),0.5862) -> 0.5862 | F8: =IFERROR(__xludf.DUMMYFUNCTION("""COMPUTED_VALUE"""),463424) -> 463424 | G8: =IFERROR(__xludf.DUMMYFUNCTION("""COMPUTED_VALUE"""),0.4963) -> 0.4963 | H8: =IFERROR(__xludf.DUMMYFUNCTION("""COMPUTED_VALUE"""),29612) -> 29612 | I8: =IFERROR(__xludf.DUMMYFUNCTION("""COMPUTED_VALUE"""),493035) -> 493035 | J8: =IFERROR(__xludf.DUMMYFUNCTION("""COMPUTED_VALUE"""),398273) -> 398273 | K8: =IFERROR(__xludf.DUMMYFUNCTION("""COMPUTED_VALUE"""),15.36) -> 15.36 | L8: =H8/I8 -> 0.060060645
A9: =IFERROR(__xludf.DUMMYFUNCTION("""COMPUTED_VALUE"""),"114.1Q") -> 114.1Q | B9: =IFERROR(__xludf.DUMMYFUNCTION("""COMPUTED_VALUE"""),839254) -> 839254 | C9: =IFERROR(__xludf.DUMMYFUNCTION("""COMPUTED_VALUE"""),345859) -> 345859 | D9: =IFERROR(__xludf.DUMMYFUNCTION("""COMPUTED_VALUE"""),493395) -> 493395 | E9: =IFERROR(__xludf.DUMMYFUNCTION("""COMPUTED_VALUE"""),0.5879) -> 0.5879 | F9: =IFERROR(__xludf.DUMMYFUNCTION("""COMPUTED_VALUE"""),407081) -> 407081 | G9: =IFERROR(__xludf.DUMMYFUNCTION("""COMPUTED_VALUE"""),0.4851) -> 0.4851 | H9: =IFERROR(__xludf.DUMMYFUNCTION("""COMPUTED_VALUE"""),23815) -> 23815 | I9: =IFERROR(__xludf.DUMMYFUNCTION("""COMPUTED_VALUE"""),430895) -> 430895 | J9: =IFERROR(__xludf.DUMMYFUNCTION("""COMPUTED_VALUE"""),361564) -> 361564 | K9: =IFERROR(__xludf.DUMMYFUNCTION("""COMPUTED_VALUE"""),13.95) -> 13.95 | L9: =H9/I9 -> 0.055268685 | R9: -
A10: =IFERROR(__xludf.DUMMYFUNCTION("""COMPUTED_VALUE"""),"113.4Q") -> 113.4Q | B10: =IFERROR(__xludf.DUMMYFUNCTION("""COMPUTED_VALUE"""),868461) -> 868461 | C10: =IFERROR(__xludf.DUMMYFUNCTION("""COMPUTED_VALUE"""),356083) -> 356083 | D10: =IFERROR(__xludf.DUMMYFUNCTION("""COMPUTED_VALUE"""),512378) -> 512378 | E10: =IFERROR(__xludf.DUMMYFUNCTION("""COMPUTED_VALUE"""),0.59) -> 0.59 | F10: =IFERROR(__xludf.DUMMYFUNCTION("""COMPUTED_VALUE"""),425713) -> 425713 | G10: =IFERROR(__xludf.DUMMYFUNCTION("""COMPUTED_VALUE"""),0.4902) -> 0.4902 | H10: =IFERROR(__xludf.DUMMYFUNCTION("""COMPUTED_VALUE"""),23085) -> 23085 | I10: =IFERROR(__xludf.DUMMYFUNCTION("""COMPUTED_VALUE"""),448798) -> 448798 | J10: =IFERROR(__xludf.DUMMYFUNCTION("""COMPUTED_VALUE"""),374680) -> 374680 | K10: =IFERROR(__xludf.DUMMYFUNCTION("""COMPUTED_VALUE"""),14.45) -> 14.45 | L10: =H10/I10 -> 0.051437395 | U10: =STDEVP(E4:E24) -> 0.046253624
A11: =IFERROR(__xludf.DUMMYFUNCTION("""COMPUTED_VALUE"""),"113.3Q") -> 113.3Q | B11: =IFERROR(__xludf.DUMMYFUNCTION("""COMPUTED_VALUE"""),759692) -> 759692 | C11: =IFERROR(__xludf.DUMMYFUNCTION("""COMPUTED_VALUE"""),320346) -> 320346 | D11: =IFERROR(__xludf.DUMMYFUNCTION("""COMPUTED_VALUE"""),439346) -> 439346 | E11: =IFERROR(__xludf.DUMMYFUNCTION("""COMPUTED_VALUE"""),0.5783) -> 0.5783 | F11: =IFERROR(__xludf.DUMMYFUNCTION("""COMPUTED_VALUE"""),360766) -> 360766 | G11: =IFERROR(__xludf.DUMMYFUNCTION("""COMPUTED_VALUE"""),0.4749) -> 0.4749 | H11: =IFERROR(__xludf.DUMMYFUNCTION("""COMPUTED_VALUE"""),23421) -> 23421 | I11: =IFERROR(__xludf.DUMMYFUNCTION("""COMPUTED_VALUE"""),384187) -> 384187 | J11: =IFERROR(__xludf.DUMMYFUNCTION("""COMPUTED_VALUE"""),325258) -> 325258 | K11: =IFERROR(__xludf.DUMMYFUNCTION("""COMPUTED_VALUE"""),12.55) -> 12.55 | L11: =H11/I11 -> 0.0609625 | P11: =A3 -> 季別 | Q11: =E3 -> 毛利率 | R11: -3倍標準差 | S11: -2倍標準差 | T11: -1倍標準差 | U11: 5年標準差 | V11: 1倍標準差 | W11: 2倍標準差 | X11: 3倍標準差
A12: =IFERROR(__xludf.DUMMYFUNCTION("""COMPUTED_VALUE"""),"113.2Q") -> 113.2Q | B12: =IFERROR(__xludf.DUMMYFUNCTION("""COMPUTED_VALUE"""),673510) -> 673510 | C12: =IFERROR(__xludf.DUMMYFUNCTION("""COMPUTED_VALUE"""),315386) -> 315386 | D12: =IFERROR(__xludf.DUMMYFUNCTION("""COMPUTED_VALUE"""),358124) -> 358124 | E12: =IFERROR(__xludf.DUMMYFUNCTION("""COMPUTED_VALUE"""),0.5317) -> 0.5317 | F12: =IFERROR(__xludf.DUMMYFUNCTION("""COMPUTED_VALUE"""),286556) -> 286556 | G12: =IFERROR(__xludf.DUMMYFUNCTION("""COMPUTED_VALUE"""),0.4255) -> 0.4255 | H12: =IFERROR(__xludf.DUMMYFUNCTION("""COMPUTED_VALUE"""),19755) -> 19755 | I12: =IFERROR(__xludf.DUMMYFUNCTION("""COMPUTED_VALUE"""),306311) -> 306311 | J12: =IFERROR(__xludf.DUMMYFUNCTION("""COMPUTED_VALUE"""),247846) -> 247846 | K12: =IFERROR(__xludf.DUMMYFUNCTION("""COMPUTED_VALUE"""),9.56) -> 9.56 | L12: =H12/I12 -> 0.064493276 | P12: =A4 -> 115.2Q | Q12: =E4 -> 0.6772 | R12: =IF(U12-U10*3<0,0,U12-U10*3) -> 0.43519151 | S12: =IF(U12-U10*2<0,0,U12-U10*2) -> 0.48144513 | T12: =IF(U12-U10*1<0,0,U12-U10*1) -> 0.52769876 | U12: =AVERAGE(E4:E24) -> 0.57395238 | V12: =U12+U10*1 -> 0.620206 | W12: =U12+U10*2 -> 0.66645963 | X12: =U12+U10*3 -> 0.71271325
A13: =IFERROR(__xludf.DUMMYFUNCTION("""COMPUTED_VALUE"""),"113.1Q") -> 113.1Q | B13: =IFERROR(__xludf.DUMMYFUNCTION("""COMPUTED_VALUE"""),592644) -> 592644 | C13: =IFERROR(__xludf.DUMMYFUNCTION("""COMPUTED_VALUE"""),278139) -> 278139 | D13: =IFERROR(__xludf.DUMMYFUNCTION("""COMPUTED_VALUE"""),314505) -> 314505 | E13: =IFERROR(__xludf.DUMMYFUNCTION("""COMPUTED_VALUE"""),0.5307) -> 0.5307 | F13: =IFERROR(__xludf.DUMMYFUNCTION("""COMPUTED_VALUE"""),249018) -> 249018 | G13: =IFERROR(__xludf.DUMMYFUNCTION("""COMPUTED_VALUE"""),0.4202) -> 0.4202 | H13: =IFERROR(__xludf.DUMMYFUNCTION("""COMPUTED_VALUE"""),17525) -> 17525 | I13: =IFERROR(__xludf.DUMMYFUNCTION("""COMPUTED_VALUE"""),266543) -> 266543 | J13: =IFERROR(__xludf.DUMMYFUNCTION("""COMPUTED_VALUE"""),225485) -> 225485 | K13: =IFERROR(__xludf.DUMMYFUNCTION("""COMPUTED_VALUE"""),8.7) -> 8.7 | L13: =H13/I13 -> 0.065749241 | P13: =A5 -> 115.1Q | Q13: =E5 -> 0.6625 | R13: =R12 -> 0.43519151 | S13: =S12 -> 0.48144513 | T13: =T12 -> 0.52769876 | U13: =U12 -> 0.57395238 | V13: =V12 -> 0.620206 | W13: =W12 -> 0.66645963 | X13: =X12 -> 0.71271325
A14: =IFERROR(__xludf.DUMMYFUNCTION("""COMPUTED_VALUE"""),"112.4Q") -> 112.4Q | B14: =IFERROR(__xludf.DUMMYFUNCTION("""COMPUTED_VALUE"""),625529) -> 625529 | C14: =IFERROR(__xludf.DUMMYFUNCTION("""COMPUTED_VALUE"""),293761) -> 293761 | D14: =IFERROR(__xludf.DUMMYFUNCTION("""COMPUTED_VALUE"""),331768) -> 331768 | E14: =IFERROR(__xludf.DUMMYFUNCTION("""COMPUTED_VALUE"""),0.5304) -> 0.5304 | F14: =IFERROR(__xludf.DUMMYFUNCTION("""COMPUTED_VALUE"""),260205) -> 260205 | G14: =IFERROR(__xludf.DUMMYFUNCTION("""COMPUTED_VALUE"""),0.416) -> 0.416 | H14: =IFERROR(__xludf.DUMMYFUNCTION("""COMPUTED_VALUE"""),18076) -> 18076 | I14: =IFERROR(__xludf.DUMMYFUNCTION("""COMPUTED_VALUE"""),278281) -> 278281 | J14: =IFERROR(__xludf.DUMMYFUNCTION("""COMPUTED_VALUE"""),238712) -> 238712 | K14: =IFERROR(__xludf.DUMMYFUNCTION("""COMPUTED_VALUE"""),9.21) -> 9.21 | L14: =H14/I14 -> 0.064955926 | P14: =A6 -> 114.4Q | Q14: =E6 -> 0.6233 | R14: =R13 -> 0.43519151 | S14: =S13 -> 0.48144513 | T14: =T13 -> 0.52769876 | U14: =U13 -> 0.57395238 | V14: =V13 -> 0.620206 | W14: =W13 -> 0.66645963 | X14: =X13 -> 0.71271325
A15: =IFERROR(__xludf.DUMMYFUNCTION("""COMPUTED_VALUE"""),"112.3Q") -> 112.3Q | B15: =IFERROR(__xludf.DUMMYFUNCTION("""COMPUTED_VALUE"""),546733) -> 546733 | C15: =IFERROR(__xludf.DUMMYFUNCTION("""COMPUTED_VALUE"""),250090) -> 250090 | D15: =IFERROR(__xludf.DUMMYFUNCTION("""COMPUTED_VALUE"""),296642) -> 296642 | E15: =IFERROR(__xludf.DUMMYFUNCTION("""COMPUTED_VALUE"""),0.5426) -> 0.5426 | F15: =IFERROR(__xludf.DUMMYFUNCTION("""COMPUTED_VALUE"""),228065) -> 228065 | G15: =IFERROR(__xludf.DUMMYFUNCTION("""COMPUTED_VALUE"""),0.4171) -> 0.4171 | H15: =IFERROR(__xludf.DUMMYFUNCTION("""COMPUTED_VALUE"""),13876) -> 13876 | I15: =IFERROR(__xludf.DUMMYFUNCTION("""COMPUTED_VALUE"""),241940) -> 241940 | J15: =IFERROR(__xludf.DUMMYFUNCTION("""COMPUTED_VALUE"""),211000) -> 211000 | K15: =IFERROR(__xludf.DUMMYFUNCTION("""COMPUTED_VALUE"""),8.14) -> 8.14 | L15: =H15/I15 -> 0.057353063 | P15: =A7 -> 114.3Q | Q15: =E7 -> 0.5945 | R15: =R14 -> 0.43519151 | S15: =S14 -> 0.48144513 | T15: =T14 -> 0.52769876 | U15: =U14 -> 0.57395238 | V15: =V14 -> 0.620206 | W15: =W14 -> 0.66645963 | X15: =X14 -> 0.71271325
A16: =IFERROR(__xludf.DUMMYFUNCTION("""COMPUTED_VALUE"""),"112.2Q") -> 112.2Q | B16: =IFERROR(__xludf.DUMMYFUNCTION("""COMPUTED_VALUE"""),480841) -> 480841 | C16: =IFERROR(__xludf.DUMMYFUNCTION("""COMPUTED_VALUE"""),220641) -> 220641 | D16: =IFERROR(__xludf.DUMMYFUNCTION("""COMPUTED_VALUE"""),260200) -> 260200 | E16: =IFERROR(__xludf.DUMMYFUNCTION("""COMPUTED_VALUE"""),0.5411) -> 0.5411 | F16: =IFERROR(__xludf.DUMMYFUNCTION("""COMPUTED_VALUE"""),201958) -> 201958 | G16: =IFERROR(__xludf.DUMMYFUNCTION("""COMPUTED_VALUE"""),0.42) -> 0.42 | H16: =IFERROR(__xludf.DUMMYFUNCTION("""COMPUTED_VALUE"""),12717) -> 12717 | I16: =IFERROR(__xludf.DUMMYFUNCTION("""COMPUTED_VALUE"""),214675) -> 214675 | J16: =IFERROR(__xludf.DUMMYFUNCTION("""COMPUTED_VALUE"""),181799) -> 181799 | K16: =IFERROR(__xludf.DUMMYFUNCTION("""COMPUTED_VALUE"""),7.01) -> 7.01 | L16: =H16/I16 -> 0.059238384 | P16: =A8 -> 114.2Q | Q16: =E8 -> 0.5862 | R16: =R15 -> 0.43519151 | S16: =S15 -> 0.48144513 | T16: =T15 -> 0.52769876 | U16: =U15 -> 0.57395238 | V16: =V15 -> 0.620206 | W16: =W15 -> 0.66645963 | X16: =X15 -> 0.71271325
A17: =IFERROR(__xludf.DUMMYFUNCTION("""COMPUTED_VALUE"""),"112.1Q") -> 112.1Q | B17: =IFERROR(__xludf.DUMMYFUNCTION("""COMPUTED_VALUE"""),508633) -> 508633 | C17: =IFERROR(__xludf.DUMMYFUNCTION("""COMPUTED_VALUE"""),222133) -> 222133 | D17: =IFERROR(__xludf.DUMMYFUNCTION("""COMPUTED_VALUE"""),286500) -> 286500 | E17: =IFERROR(__xludf.DUMMYFUNCTION("""COMPUTED_VALUE"""),0.5633) -> 0.5633 | F17: =IFERROR(__xludf.DUMMYFUNCTION("""COMPUTED_VALUE"""),231238) -> 231238 | G17: =IFERROR(__xludf.DUMMYFUNCTION("""COMPUTED_VALUE"""),0.4546) -> 0.4546 | H17: =IFERROR(__xludf.DUMMYFUNCTION("""COMPUTED_VALUE"""),13037) -> 13037 | I17: =IFERROR(__xludf.DUMMYFUNCTION("""COMPUTED_VALUE"""),244275) -> 244275 | J17: =IFERROR(__xludf.DUMMYFUNCTION("""COMPUTED_VALUE"""),206987) -> 206987 | K17: =IFERROR(__xludf.DUMMYFUNCTION("""COMPUTED_VALUE"""),7.98) -> 7.98 | L17: =H17/I17 -> 0.053370177 | P17: =A9 -> 114.1Q | Q17: =E9 -> 0.5879 | R17: =R16 -> 0.43519151 | S17: =S16 -> 0.48144513 | T17: =T16 -> 0.52769876 | U17: =U16 -> 0.57395238 | V17: =V16 -> 0.620206 | W17: =W16 -> 0.66645963 | X17: =X16 -> 0.71271325
A18: =IFERROR(__xludf.DUMMYFUNCTION("""COMPUTED_VALUE"""),"111.4Q") -> 111.4Q | B18: =IFERROR(__xludf.DUMMYFUNCTION("""COMPUTED_VALUE"""),625532) -> 625532 | C18: =IFERROR(__xludf.DUMMYFUNCTION("""COMPUTED_VALUE"""),236347) -> 236347 | D18: =IFERROR(__xludf.DUMMYFUNCTION("""COMPUTED_VALUE"""),389185) -> 389185 | E18: =IFERROR(__xludf.DUMMYFUNCTION("""COMPUTED_VALUE"""),0.6222) -> 0.6222 | F18: =IFERROR(__xludf.DUMMYFUNCTION("""COMPUTED_VALUE"""),325041) -> 325041 | G18: =IFERROR(__xludf.DUMMYFUNCTION("""COMPUTED_VALUE"""),0.5196) -> 0.5196 | H18: =IFERROR(__xludf.DUMMYFUNCTION("""COMPUTED_VALUE"""),9629) -> 9629 | I18: =IFERROR(__xludf.DUMMYFUNCTION("""COMPUTED_VALUE"""),334670) -> 334670 | J18: =IFERROR(__xludf.DUMMYFUNCTION("""COMPUTED_VALUE"""),295904) -> 295904 | K18: =IFERROR(__xludf.DUMMYFUNCTION("""COMPUTED_VALUE"""),11.41) -> 11.41 | L18: =H18/I18 -> 0.028771626 | P18: =A10 -> 113.4Q | Q18: =E10 -> 0.59 | R18: =R17 -> 0.43519151 | S18: =S17 -> 0.48144513 | T18: =T17 -> 0.52769876 | U18: =U17 -> 0.57395238 | V18: =V17 -> 0.620206 | W18: =W17 -> 0.66645963 | X18: =X17 -> 0.71271325
A19: =IFERROR(__xludf.DUMMYFUNCTION("""COMPUTED_VALUE"""),"111.3Q") -> 111.3Q | B19: =IFERROR(__xludf.DUMMYFUNCTION("""COMPUTED_VALUE"""),613143) -> 613143 | C19: =IFERROR(__xludf.DUMMYFUNCTION("""COMPUTED_VALUE"""),242644) -> 242644 | D19: =IFERROR(__xludf.DUMMYFUNCTION("""COMPUTED_VALUE"""),370499) -> 370499 | E19: =IFERROR(__xludf.DUMMYFUNCTION("""COMPUTED_VALUE"""),0.6043) -> 0.6043 | F19: =IFERROR(__xludf.DUMMYFUNCTION("""COMPUTED_VALUE"""),310324) -> 310324 | G19: =IFERROR(__xludf.DUMMYFUNCTION("""COMPUTED_VALUE"""),0.5061) -> 0.5061 | H19: =IFERROR(__xludf.DUMMYFUNCTION("""COMPUTED_VALUE"""),6367) -> 6367 | I19: =IFERROR(__xludf.DUMMYFUNCTION("""COMPUTED_VALUE"""),316691) -> 316691 | J19: =IFERROR(__xludf.DUMMYFUNCTION("""COMPUTED_VALUE"""),280866) -> 280866 | K19: =IFERROR(__xludf.DUMMYFUNCTION("""COMPUTED_VALUE"""),10.83) -> 10.83 | L19: =H19/I19 -> 0.020104771 | P19: =A11 -> 113.3Q | Q19: =E11 -> 0.5783 | R19: =R18 -> 0.43519151 | S19: =S18 -> 0.48144513 | T19: =T18 -> 0.52769876 | U19: =U18 -> 0.57395238 | V19: =V18 -> 0.620206 | W19: =W18 -> 0.66645963 | X19: =X18 -> 0.71271325
A20: =IFERROR(__xludf.DUMMYFUNCTION("""COMPUTED_VALUE"""),"111.2Q") -> 111.2Q | B20: =IFERROR(__xludf.DUMMYFUNCTION("""COMPUTED_VALUE"""),534141) -> 534141 | C20: =IFERROR(__xludf.DUMMYFUNCTION("""COMPUTED_VALUE"""),218673) -> 218673 | D20: =IFERROR(__xludf.DUMMYFUNCTION("""COMPUTED_VALUE"""),315468) -> 315468 | E20: =IFERROR(__xludf.DUMMYFUNCTION("""COMPUTED_VALUE"""),0.5906) -> 0.5906 | F20: =IFERROR(__xludf.DUMMYFUNCTION("""COMPUTED_VALUE"""),262124) -> 262124 | G20: =IFERROR(__xludf.DUMMYFUNCTION("""COMPUTED_VALUE"""),0.4907) -> 0.4907 | H20: =IFERROR(__xludf.DUMMYFUNCTION("""COMPUTED_VALUE"""),3875) -> 3875 | I20: =IFERROR(__xludf.DUMMYFUNCTION("""COMPUTED_VALUE"""),265998) -> 265998 | J20: =IFERROR(__xludf.DUMMYFUNCTION("""COMPUTED_VALUE"""),237027) -> 237027 | K20: =IFERROR(__xludf.DUMMYFUNCTION("""COMPUTED_VALUE"""),9.14) -> 9.14 | L20: =H20/I20 -> 0.014567779 | P20: =A12 -> 113.2Q | Q20: =E12 -> 0.5317 | R20: =R19 -> 0.43519151 | S20: =S19 -> 0.48144513 | T20: =T19 -> 0.52769876 | U20: =U19 -> 0.57395238 | V20: =V19 -> 0.620206 | W20: =W19 -> 0.66645963 | X20: =X19 -> 0.71271325
A21: =IFERROR(__xludf.DUMMYFUNCTION("""COMPUTED_VALUE"""),"111.1Q") -> 111.1Q | B21: =IFERROR(__xludf.DUMMYFUNCTION("""COMPUTED_VALUE"""),491076) -> 491076 | C21: =IFERROR(__xludf.DUMMYFUNCTION("""COMPUTED_VALUE"""),217873) -> 217873 | D21: =IFERROR(__xludf.DUMMYFUNCTION("""COMPUTED_VALUE"""),273203) -> 273203 | E21: =IFERROR(__xludf.DUMMYFUNCTION("""COMPUTED_VALUE"""),0.5563) -> 0.5563 | F21: =IFERROR(__xludf.DUMMYFUNCTION("""COMPUTED_VALUE"""),223790) -> 223790 | G21: =IFERROR(__xludf.DUMMYFUNCTION("""COMPUTED_VALUE"""),0.4557) -> 0.4557 | H21: =IFERROR(__xludf.DUMMYFUNCTION("""COMPUTED_VALUE"""),3042) -> 3042 | I21: =IFERROR(__xludf.DUMMYFUNCTION("""COMPUTED_VALUE"""),226832) -> 226832 | J21: =IFERROR(__xludf.DUMMYFUNCTION("""COMPUTED_VALUE"""),202733) -> 202733 | K21: =IFERROR(__xludf.DUMMYFUNCTION("""COMPUTED_VALUE"""),7.82) -> 7.82 | L21: =H21/I21 -> 0.013410806 | P21: =A13 -> 113.1Q | Q21: =E13 -> 0.5307 | R21: =R20 -> 0.43519151 | S21: =S20 -> 0.48144513 | T21: =T20 -> 0.52769876 | U21: =U20 -> 0.57395238 | V21: =V20 -> 0.620206 | W21: =W20 -> 0.66645963 | X21: =X20 -> 0.71271325
A22: =IFERROR(__xludf.DUMMYFUNCTION("""COMPUTED_VALUE"""),"110.4Q") -> 110.4Q | B22: =IFERROR(__xludf.DUMMYFUNCTION("""COMPUTED_VALUE"""),438189) -> 438189 | C22: =IFERROR(__xludf.DUMMYFUNCTION("""COMPUTED_VALUE"""),207434) -> 207434 | D22: =IFERROR(__xludf.DUMMYFUNCTION("""COMPUTED_VALUE"""),230755) -> 230755 | E22: =IFERROR(__xludf.DUMMYFUNCTION("""COMPUTED_VALUE"""),0.5266) -> 0.5266 | F22: =IFERROR(__xludf.DUMMYFUNCTION("""COMPUTED_VALUE"""),182772) -> 182772 | G22: =IFERROR(__xludf.DUMMYFUNCTION("""COMPUTED_VALUE"""),0.4171) -> 0.4171 | H22: =IFERROR(__xludf.DUMMYFUNCTION("""COMPUTED_VALUE"""),2047) -> 2047 | I22: =IFERROR(__xludf.DUMMYFUNCTION("""COMPUTED_VALUE"""),184819) -> 184819 | J22: =IFERROR(__xludf.DUMMYFUNCTION("""COMPUTED_VALUE"""),166232) -> 166232 | K22: =IFERROR(__xludf.DUMMYFUNCTION("""COMPUTED_VALUE"""),6.41) -> 6.41 | L22: =H22/I22 -> 0.011075701 | P22: =A14 -> 112.4Q | Q22: =E14 -> 0.5304 | R22: =R21 -> 0.43519151 | S22: =S21 -> 0.48144513 | T22: =T21 -> 0.52769876 | U22: =U21 -> 0.57395238 | V22: =V21 -> 0.620206 | W22: =W21 -> 0.66645963 | X22: =X21 -> 0.71271325
A23: =IFERROR(__xludf.DUMMYFUNCTION("""COMPUTED_VALUE"""),"110.3Q") -> 110.3Q | B23: =IFERROR(__xludf.DUMMYFUNCTION("""COMPUTED_VALUE"""),414670) -> 414670 | C23: =IFERROR(__xludf.DUMMYFUNCTION("""COMPUTED_VALUE"""),201924) -> 201924 | D23: =IFERROR(__xludf.DUMMYFUNCTION("""COMPUTED_VALUE"""),212746) -> 212746 | E23: =IFERROR(__xludf.DUMMYFUNCTION("""COMPUTED_VALUE"""),0.513) -> 0.513 | F23: =IFERROR(__xludf.DUMMYFUNCTION("""COMPUTED_VALUE"""),171004) -> 171004 | G23: =IFERROR(__xludf.DUMMYFUNCTION("""COMPUTED_VALUE"""),0.4124) -> 0.4124 | H23: =IFERROR(__xludf.DUMMYFUNCTION("""COMPUTED_VALUE"""),2848) -> 2848 | I23: =IFERROR(__xludf.DUMMYFUNCTION("""COMPUTED_VALUE"""),173852) -> 173852 | J23: =IFERROR(__xludf.DUMMYFUNCTION("""COMPUTED_VALUE"""),156258) -> 156258 | K23: =IFERROR(__xludf.DUMMYFUNCTION("""COMPUTED_VALUE"""),6.03) -> 6.03 | L23: =H23/I23 -> 0.01638175 | P23: =A15 -> 112.3Q | Q23: =E15 -> 0.5426 | R23: =R22 -> 0.43519151 | S23: =S22 -> 0.48144513 | T23: =T22 -> 0.52769876 | U23: =U22 -> 0.57395238 | V23: =V22 -> 0.620206 | W23: =W22 -> 0.66645963 | X23: =X22 -> 0.71271325
A24: =IFERROR(__xludf.DUMMYFUNCTION("""COMPUTED_VALUE"""),"110.2Q") -> 110.2Q | B24: =IFERROR(__xludf.DUMMYFUNCTION("""COMPUTED_VALUE"""),372145) -> 372145 | C24: =IFERROR(__xludf.DUMMYFUNCTION("""COMPUTED_VALUE"""),185948) -> 185948 | D24: =IFERROR(__xludf.DUMMYFUNCTION("""COMPUTED_VALUE"""),186197) -> 186197 | E24: =IFERROR(__xludf.DUMMYFUNCTION("""COMPUTED_VALUE"""),0.5003) -> 0.5003 | F24: =IFERROR(__xludf.DUMMYFUNCTION("""COMPUTED_VALUE"""),145667) -> 145667 | G24: =IFERROR(__xludf.DUMMYFUNCTION("""COMPUTED_VALUE"""),0.3914) -> 0.3914 | H24: =IFERROR(__xludf.DUMMYFUNCTION("""COMPUTED_VALUE"""),3724) -> 3724 | I24: =IFERROR(__xludf.DUMMYFUNCTION("""COMPUTED_VALUE"""),149391) -> 149391 | J24: =IFERROR(__xludf.DUMMYFUNCTION("""COMPUTED_VALUE"""),134359) -> 134359 | K24: =IFERROR(__xludf.DUMMYFUNCTION("""COMPUTED_VALUE"""),5.18) -> 5.18 | L24: =H24/I24 -> 0.024927874 | P24: =A16 -> 112.2Q | Q24: =E16 -> 0.5411 | R24: =R23 -> 0.43519151 | S24: =S23 -> 0.48144513 | T24: =T23 -> 0.52769876 | U24: =U23 -> 0.57395238 | V24: =V23 -> 0.620206 | W24: =W23 -> 0.66645963 | X24: =X23 -> 0.71271325
A25: =IFERROR(__xludf.DUMMYFUNCTION("""COMPUTED_VALUE"""),"110.1Q") -> 110.1Q | B25: =IFERROR(__xludf.DUMMYFUNCTION("""COMPUTED_VALUE"""),362410) -> 362410 | C25: =IFERROR(__xludf.DUMMYFUNCTION("""COMPUTED_VALUE"""),172571) -> 172571 | D25: =IFERROR(__xludf.DUMMYFUNCTION("""COMPUTED_VALUE"""),189839) -> 189839 | E25: =IFERROR(__xludf.DUMMYFUNCTION("""COMPUTED_VALUE"""),0.5238) -> 0.5238 | F25: =IFERROR(__xludf.DUMMYFUNCTION("""COMPUTED_VALUE"""),150538) -> 150538 | G25: =IFERROR(__xludf.DUMMYFUNCTION("""COMPUTED_VALUE"""),0.4154) -> 0.4154 | H25: =IFERROR(__xludf.DUMMYFUNCTION("""COMPUTED_VALUE"""),4526) -> 4526 | I25: =IFERROR(__xludf.DUMMYFUNCTION("""COMPUTED_VALUE"""),155064) -> 155064 | J25: =IFERROR(__xludf.DUMMYFUNCTION("""COMPUTED_VALUE"""),139690) -> 139690 | K25: =IFERROR(__xludf.DUMMYFUNCTION("""COMPUTED_VALUE"""),5.39) -> 5.39 | L25: =H25/I25 -> 0.029187948 | P25: =A17 -> 112.1Q | Q25: =E17 -> 0.5633 | R25: =R24 -> 0.43519151 | S25: =S24 -> 0.48144513 | T25: =T24 -> 0.52769876 | U25: =U24 -> 0.57395238 | V25: =V24 -> 0.620206 | W25: =W24 -> 0.66645963 | X25: =X24 -> 0.71271325
A26: =IFERROR(__xludf.DUMMYFUNCTION("""COMPUTED_VALUE"""),"109.4Q") -> 109.4Q | B26: =IFERROR(__xludf.DUMMYFUNCTION("""COMPUTED_VALUE"""),361533) -> 361533 | C26: =IFERROR(__xludf.DUMMYFUNCTION("""COMPUTED_VALUE"""),166361) -> 166361 | D26: =IFERROR(__xludf.DUMMYFUNCTION("""COMPUTED_VALUE"""),195172) -> 195172 | E26: =IFERROR(__xludf.DUMMYFUNCTION("""COMPUTED_VALUE"""),0.5398) -> 0.5398 | F26: =IFERROR(__xludf.DUMMYFUNCTION("""COMPUTED_VALUE"""),157120) -> 157120 | G26: =IFERROR(__xludf.DUMMYFUNCTION("""COMPUTED_VALUE"""),0.4346) -> 0.4346 | H26: =IFERROR(__xludf.DUMMYFUNCTION("""COMPUTED_VALUE"""),3987) -> 3987 | I26: =IFERROR(__xludf.DUMMYFUNCTION("""COMPUTED_VALUE"""),161107) -> 161107 | J26: =IFERROR(__xludf.DUMMYFUNCTION("""COMPUTED_VALUE"""),142766) -> 142766 | K26: =IFERROR(__xludf.DUMMYFUNCTION("""COMPUTED_VALUE"""),5.51) -> 5.51 | L26: =H26/I26 -> 0.024747528 | P26: =A18 -> 111.4Q | Q26: =E18 -> 0.6222 | R26: =R25 -> 0.43519151 | S26: =S25 -> 0.48144513 | T26: =T25 -> 0.52769876 | U26: =U25 -> 0.57395238 | V26: =V25 -> 0.620206 | W26: =W25 -> 0.66645963 | X26: =X25 -> 0.71271325
A27: =IFERROR(__xludf.DUMMYFUNCTION("""COMPUTED_VALUE"""),"109.3Q") -> 109.3Q | B27: =IFERROR(__xludf.DUMMYFUNCTION("""COMPUTED_VALUE"""),356426) -> 356426 | C27: =IFERROR(__xludf.DUMMYFUNCTION("""COMPUTED_VALUE"""),165946) -> 165946 | D27: =IFERROR(__xludf.DUMMYFUNCTION("""COMPUTED_VALUE"""),190481) -> 190481 | E27: =IFERROR(__xludf.DUMMYFUNCTION("""COMPUTED_VALUE"""),0.5344) -> 0.5344 | F27: =IFERROR(__xludf.DUMMYFUNCTION("""COMPUTED_VALUE"""),150047) -> 150047 | G27: =IFERROR(__xludf.DUMMYFUNCTION("""COMPUTED_VALUE"""),0.421) -> 0.421 | H27: =IFERROR(__xludf.DUMMYFUNCTION("""COMPUTED_VALUE"""),5077) -> 5077 | I27: =IFERROR(__xludf.DUMMYFUNCTION("""COMPUTED_VALUE"""),155124) -> 155124 | J27: =IFERROR(__xludf.DUMMYFUNCTION("""COMPUTED_VALUE"""),137310) -> 137310 | K27: =IFERROR(__xludf.DUMMYFUNCTION("""COMPUTED_VALUE"""),5.3) -> 5.3 | L27: =H27/I27 -> 0.032728656 | P27: =A19 -> 111.3Q | Q27: =E19 -> 0.6043 | R27: =R26 -> 0.43519151 | S27: =S26 -> 0.48144513 | T27: =T26 -> 0.52769876 | U27: =U26 -> 0.57395238 | V27: =V26 -> 0.620206 | W27: =W26 -> 0.66645963 | X27: =X26 -> 0.71271325
A28: =IFERROR(__xludf.DUMMYFUNCTION("""COMPUTED_VALUE"""),"109.2Q") -> 109.2Q | B28: =IFERROR(__xludf.DUMMYFUNCTION("""COMPUTED_VALUE"""),310698) -> 310698 | C28: =IFERROR(__xludf.DUMMYFUNCTION("""COMPUTED_VALUE"""),146006) -> 146006 | D28: =IFERROR(__xludf.DUMMYFUNCTION("""COMPUTED_VALUE"""),164693) -> 164693 | E28: =IFERROR(__xludf.DUMMYFUNCTION("""COMPUTED_VALUE"""),0.5301) -> 0.5301 | F28: =IFERROR(__xludf.DUMMYFUNCTION("""COMPUTED_VALUE"""),131095) -> 131095 | G28: =IFERROR(__xludf.DUMMYFUNCTION("""COMPUTED_VALUE"""),0.4219) -> 0.4219 | H28: =IFERROR(__xludf.DUMMYFUNCTION("""COMPUTED_VALUE"""),5304) -> 5304 | I28: =IFERROR(__xludf.DUMMYFUNCTION("""COMPUTED_VALUE"""),136399) -> 136399 | J28: =IFERROR(__xludf.DUMMYFUNCTION("""COMPUTED_VALUE"""),120822) -> 120822 | K28: =IFERROR(__xludf.DUMMYFUNCTION("""COMPUTED_VALUE"""),4.66) -> 4.66 | P28: =A20 -> 111.2Q | Q28: =E20 -> 0.5906 | R28: =R27 -> 0.43519151 | S28: =S27 -> 0.48144513 | T28: =T27 -> 0.52769876 | U28: =U27 -> 0.57395238 | V28: =V27 -> 0.620206 | W28: =W27 -> 0.66645963 | X28: =X27 -> 0.71271325
A29: =IFERROR(__xludf.DUMMYFUNCTION("""COMPUTED_VALUE"""),"109.1Q") -> 109.1Q | B29: =IFERROR(__xludf.DUMMYFUNCTION("""COMPUTED_VALUE"""),310597) -> 310597 | C29: =IFERROR(__xludf.DUMMYFUNCTION("""COMPUTED_VALUE"""),149813) -> 149813 | D29: =IFERROR(__xludf.DUMMYFUNCTION("""COMPUTED_VALUE"""),160784) -> 160784 | E29: =IFERROR(__xludf.DUMMYFUNCTION("""COMPUTED_VALUE"""),0.5177) -> 0.5177 | F29: =IFERROR(__xludf.DUMMYFUNCTION("""COMPUTED_VALUE"""),128522) -> 128522 | G29: =IFERROR(__xludf.DUMMYFUNCTION("""COMPUTED_VALUE"""),0.4138) -> 0.4138 | H29: =IFERROR(__xludf.DUMMYFUNCTION("""COMPUTED_VALUE"""),3626) -> 3626 | I29: =IFERROR(__xludf.DUMMYFUNCTION("""COMPUTED_VALUE"""),132147) -> 132147 | J29: =IFERROR(__xludf.DUMMYFUNCTION("""COMPUTED_VALUE"""),116987) -> 116987 | K29: =IFERROR(__xludf.DUMMYFUNCTION("""COMPUTED_VALUE"""),4.51) -> 4.51 | P29: =A21 -> 111.1Q | Q29: =E21 -> 0.5563 | R29: =R28 -> 0.43519151 | S29: =S28 -> 0.48144513 | T29: =T28 -> 0.52769876 | U29: =U28 -> 0.57395238 | V29: =V28 -> 0.620206 | W29: =W28 -> 0.66645963 | X29: =X28 -> 0.71271325
A30: =IFERROR(__xludf.DUMMYFUNCTION("""COMPUTED_VALUE"""),"108.4Q") -> 108.4Q | B30: =IFERROR(__xludf.DUMMYFUNCTION("""COMPUTED_VALUE"""),317237) -> 317237 | C30: =IFERROR(__xludf.DUMMYFUNCTION("""COMPUTED_VALUE"""),157996) -> 157996 | D30: =IFERROR(__xludf.DUMMYFUNCTION("""COMPUTED_VALUE"""),159241) -> 159241 | E30: =IFERROR(__xludf.DUMMYFUNCTION("""COMPUTED_VALUE"""),0.502) -> 0.502 | F30: =IFERROR(__xludf.DUMMYFUNCTION("""COMPUTED_VALUE"""),124244) -> 124244 | G30: =IFERROR(__xludf.DUMMYFUNCTION("""COMPUTED_VALUE"""),0.3916) -> 0.3916 | H30: =IFERROR(__xludf.DUMMYFUNCTION("""COMPUTED_VALUE"""),4538) -> 4538 | I30: =IFERROR(__xludf.DUMMYFUNCTION("""COMPUTED_VALUE"""),128782) -> 128782 | J30: =IFERROR(__xludf.DUMMYFUNCTION("""COMPUTED_VALUE"""),116035) -> 116035 | K30: =IFERROR(__xludf.DUMMYFUNCTION("""COMPUTED_VALUE"""),4.47) -> 4.47 | P30: =A22 -> 110.4Q | Q30: =E22 -> 0.5266 | R30: =R29 -> 0.43519151 | S30: =S29 -> 0.48144513 | T30: =T29 -> 0.52769876 | U30: =U29 -> 0.57395238 | V30: =V29 -> 0.620206 | W30: =W29 -> 0.66645963 | X30: =X29 -> 0.71271325
A31: =IFERROR(__xludf.DUMMYFUNCTION("""COMPUTED_VALUE"""),"108.3Q") -> 108.3Q | B31: =IFERROR(__xludf.DUMMYFUNCTION("""COMPUTED_VALUE"""),293045) -> 293045 | C31: =IFERROR(__xludf.DUMMYFUNCTION("""COMPUTED_VALUE"""),153613) -> 153613 | D31: =IFERROR(__xludf.DUMMYFUNCTION("""COMPUTED_VALUE"""),139432) -> 139432 | E31: =IFERROR(__xludf.DUMMYFUNCTION("""COMPUTED_VALUE"""),0.4758) -> 0.4758 | F31: =IFERROR(__xludf.DUMMYFUNCTION("""COMPUTED_VALUE"""),107887) -> 107887 | G31: =IFERROR(__xludf.DUMMYFUNCTION("""COMPUTED_VALUE"""),0.3682) -> 0.3682 | H31: =IFERROR(__xludf.DUMMYFUNCTION("""COMPUTED_VALUE"""),4449) -> 4449 | I31: =IFERROR(__xludf.DUMMYFUNCTION("""COMPUTED_VALUE"""),112336) -> 112336 | J31: =IFERROR(__xludf.DUMMYFUNCTION("""COMPUTED_VALUE"""),101070) -> 101070 | K31: =IFERROR(__xludf.DUMMYFUNCTION("""COMPUTED_VALUE"""),3.9) -> 3.9 | P31: =A23 -> 110.3Q | Q31: =E23 -> 0.513 | R31: =R30 -> 0.43519151 | S31: =S30 -> 0.48144513 | T31: =T30 -> 0.52769876 | U31: =U30 -> 0.57395238 | V31: =V30 -> 0.620206 | W31: =W30 -> 0.66645963 | X31: =X30 -> 0.71271325
A32: =IFERROR(__xludf.DUMMYFUNCTION("""COMPUTED_VALUE"""),"108.2Q") -> 108.2Q | B32: =IFERROR(__xludf.DUMMYFUNCTION("""COMPUTED_VALUE"""),240998) -> 240998 | C32: =IFERROR(__xludf.DUMMYFUNCTION("""COMPUTED_VALUE"""),137325) -> 137325 | D32: =IFERROR(__xludf.DUMMYFUNCTION("""COMPUTED_VALUE"""),103673) -> 103673 | E32: =IFERROR(__xludf.DUMMYFUNCTION("""COMPUTED_VALUE"""),0.4302) -> 0.4302 | F32: =IFERROR(__xludf.DUMMYFUNCTION("""COMPUTED_VALUE"""),76304) -> 76304 | G32: =IFERROR(__xludf.DUMMYFUNCTION("""COMPUTED_VALUE"""),0.3166) -> 0.3166 | H32: =IFERROR(__xludf.DUMMYFUNCTION("""COMPUTED_VALUE"""),4241) -> 4241 | I32: =IFERROR(__xludf.DUMMYFUNCTION("""COMPUTED_VALUE"""),80545) -> 80545 | J32: =IFERROR(__xludf.DUMMYFUNCTION("""COMPUTED_VALUE"""),66765) -> 66765 | K32: =IFERROR(__xludf.DUMMYFUNCTION("""COMPUTED_VALUE"""),2.57) -> 2.57 | P32: =A24 -> 110.2Q | Q32: =E24 -> 0.5003 | R32: =R31 -> 0.43519151 | S32: =S31 -> 0.48144513 | T32: =T31 -> 0.52769876 | U32: =U31 -> 0.57395238 | V32: =V31 -> 0.620206 | W32: =W31 -> 0.66645963 | X32: =X31 -> 0.71271325
A33: =IFERROR(__xludf.DUMMYFUNCTION("""COMPUTED_VALUE"""),"108.1Q") -> 108.1Q | B33: =IFERROR(__xludf.DUMMYFUNCTION("""COMPUTED_VALUE"""),218704) -> 218704 | C33: =IFERROR(__xludf.DUMMYFUNCTION("""COMPUTED_VALUE"""),128352) -> 128352 | D33: =IFERROR(__xludf.DUMMYFUNCTION("""COMPUTED_VALUE"""),90352) -> 90352 | E33: =IFERROR(__xludf.DUMMYFUNCTION("""COMPUTED_VALUE"""),0.4131) -> 0.4131 | F33: =IFERROR(__xludf.DUMMYFUNCTION("""COMPUTED_VALUE"""),64266) -> 64266 | G33: =IFERROR(__xludf.DUMMYFUNCTION("""COMPUTED_VALUE"""),0.2938) -> 0.2938 | H33: =IFERROR(__xludf.DUMMYFUNCTION("""COMPUTED_VALUE"""),3916) -> 3916 | I33: =IFERROR(__xludf.DUMMYFUNCTION("""COMPUTED_VALUE"""),68182) -> 68182 | J33: =IFERROR(__xludf.DUMMYFUNCTION("""COMPUTED_VALUE"""),61394) -> 61394 | K33: =IFERROR(__xludf.DUMMYFUNCTION("""COMPUTED_VALUE"""),2.37) -> 2.37
A34: =IFERROR(__xludf.DUMMYFUNCTION("""COMPUTED_VALUE"""),"107.4Q") -> 107.4Q | B34: =IFERROR(__xludf.DUMMYFUNCTION("""COMPUTED_VALUE"""),289770) -> 289770 | C34: =IFERROR(__xludf.DUMMYFUNCTION("""COMPUTED_VALUE"""),151728) -> 151728 | D34: =IFERROR(__xludf.DUMMYFUNCTION("""COMPUTED_VALUE"""),138042) -> 138042 | E34: =IFERROR(__xludf.DUMMYFUNCTION("""COMPUTED_VALUE"""),0.4764) -> 0.4764 | F34: =IFERROR(__xludf.DUMMYFUNCTION("""COMPUTED_VALUE"""),107123) -> 107123 | G34: =IFERROR(__xludf.DUMMYFUNCTION("""COMPUTED_VALUE"""),0.3697) -> 0.3697 | H34: =IFERROR(__xludf.DUMMYFUNCTION("""COMPUTED_VALUE"""),3959) -> 3959 | I34: =IFERROR(__xludf.DUMMYFUNCTION("""COMPUTED_VALUE"""),111082) -> 111082 | J34: =IFERROR(__xludf.DUMMYFUNCTION("""COMPUTED_VALUE"""),99984) -> 99984 | K34: =IFERROR(__xludf.DUMMYFUNCTION("""COMPUTED_VALUE"""),3.86) -> 3.86
A35: =IFERROR(__xludf.DUMMYFUNCTION("""COMPUTED_VALUE"""),"107.3Q") -> 107.3Q | B35: =IFERROR(__xludf.DUMMYFUNCTION("""COMPUTED_VALUE"""),260348) -> 260348 | C35: =IFERROR(__xludf.DUMMYFUNCTION("""COMPUTED_VALUE"""),136967) -> 136967 | D35: =IFERROR(__xludf.DUMMYFUNCTION("""COMPUTED_VALUE"""),123381) -> 123381 | E35: =IFERROR(__xludf.DUMMYFUNCTION("""COMPUTED_VALUE"""),0.4739) -> 0.4739 | F35: =IFERROR(__xludf.DUMMYFUNCTION("""COMPUTED_VALUE"""),95245) -> 95245 | G35: =IFERROR(__xludf.DUMMYFUNCTION("""COMPUTED_VALUE"""),0.3658) -> 0.3658 | H35: =IFERROR(__xludf.DUMMYFUNCTION("""COMPUTED_VALUE"""),3652) -> 3652 | I35: =IFERROR(__xludf.DUMMYFUNCTION("""COMPUTED_VALUE"""),98897) -> 98897 | J35: =IFERROR(__xludf.DUMMYFUNCTION("""COMPUTED_VALUE"""),89072) -> 89072 | K35: =IFERROR(__xludf.DUMMYFUNCTION("""COMPUTED_VALUE"""),3.44) -> 3.44
A36: =IFERROR(__xludf.DUMMYFUNCTION("""COMPUTED_VALUE"""),"107.2Q") -> 107.2Q | B36: =IFERROR(__xludf.DUMMYFUNCTION("""COMPUTED_VALUE"""),233277) -> 233277 | C36: =IFERROR(__xludf.DUMMYFUNCTION("""COMPUTED_VALUE"""),121689) -> 121689 | D36: =IFERROR(__xludf.DUMMYFUNCTION("""COMPUTED_VALUE"""),111588) -> 111588 | E36: =IFERROR(__xludf.DUMMYFUNCTION("""COMPUTED_VALUE"""),0.4784) -> 0.4784 | F36: =IFERROR(__xludf.DUMMYFUNCTION("""COMPUTED_VALUE"""),84428) -> 84428 | G36: =IFERROR(__xludf.DUMMYFUNCTION("""COMPUTED_VALUE"""),0.3619) -> 0.3619 | H36: =IFERROR(__xludf.DUMMYFUNCTION("""COMPUTED_VALUE"""),3159) -> 3159 | I36: =IFERROR(__xludf.DUMMYFUNCTION("""COMPUTED_VALUE"""),87588) -> 87588 | J36: =IFERROR(__xludf.DUMMYFUNCTION("""COMPUTED_VALUE"""),72291) -> 72291 | K36: =IFERROR(__xludf.DUMMYFUNCTION("""COMPUTED_VALUE"""),2.79) -> 2.79
A37: =IFERROR(__xludf.DUMMYFUNCTION("""COMPUTED_VALUE"""),"107.1Q") -> 107.1Q | B37: =IFERROR(__xludf.DUMMYFUNCTION("""COMPUTED_VALUE"""),248079) -> 248079 | C37: =IFERROR(__xludf.DUMMYFUNCTION("""COMPUTED_VALUE"""),123104) -> 123104 | D37: =IFERROR(__xludf.DUMMYFUNCTION("""COMPUTED_VALUE"""),124975) -> 124975 | E37: =IFERROR(__xludf.DUMMYFUNCTION("""COMPUTED_VALUE"""),0.5038) -> 0.5038 | F37: =IFERROR(__xludf.DUMMYFUNCTION("""COMPUTED_VALUE"""),96827) -> 96827 | G37: =IFERROR(__xludf.DUMMYFUNCTION("""COMPUTED_VALUE"""),0.3903) -> 0.3903 | H37: =IFERROR(__xludf.DUMMYFUNCTION("""COMPUTED_VALUE"""),3117) -> 3117 | I37: =IFERROR(__xludf.DUMMYFUNCTION("""COMPUTED_VALUE"""),99944) -> 99944 | J37: =IFERROR(__xludf.DUMMYFUNCTION("""COMPUTED_VALUE"""),89785) -> 89785 | K37: =IFERROR(__xludf.DUMMYFUNCTION("""COMPUTED_VALUE"""),3.46) -> 3.46
A38: =IFERROR(__xludf.DUMMYFUNCTION("""COMPUTED_VALUE"""),"106.4Q") -> 106.4Q | B38: =IFERROR(__xludf.DUMMYFUNCTION("""COMPUTED_VALUE"""),277570) -> 277570 | C38: =IFERROR(__xludf.DUMMYFUNCTION("""COMPUTED_VALUE"""),138855) -> 138855 | D38: =IFERROR(__xludf.DUMMYFUNCTION("""COMPUTED_VALUE"""),138715) -> 138715 | E38: =IFERROR(__xludf.DUMMYFUNCTION("""COMPUTED_VALUE"""),0.4997) -> 0.4997 | F38: =IFERROR(__xludf.DUMMYFUNCTION("""COMPUTED_VALUE"""),108895) -> 108895 | G38: =IFERROR(__xludf.DUMMYFUNCTION("""COMPUTED_VALUE"""),0.3923) -> 0.3923 | H38: =IFERROR(__xludf.DUMMYFUNCTION("""COMPUTED_VALUE"""),2780) -> 2780 | I38: =IFERROR(__xludf.DUMMYFUNCTION("""COMPUTED_VALUE"""),111675) -> 111675 | J38: =IFERROR(__xludf.DUMMYFUNCTION("""COMPUTED_VALUE"""),99286) -> 99286 | K38: =IFERROR(__xludf.DUMMYFUNCTION("""COMPUTED_VALUE"""),3.83) -> 3.83
A39: =IFERROR(__xludf.DUMMYFUNCTION("""COMPUTED_VALUE"""),"106.3Q") -> 106.3Q | B39: =IFERROR(__xludf.DUMMYFUNCTION("""COMPUTED_VALUE"""),252107) -> 252107 | C39: =IFERROR(__xludf.DUMMYFUNCTION("""COMPUTED_VALUE"""),126231) -> 126231 | D39: =IFERROR(__xludf.DUMMYFUNCTION("""COMPUTED_VALUE"""),125877) -> 125877 | E39: =IFERROR(__xludf.DUMMYFUNCTION("""COMPUTED_VALUE"""),0.4993) -> 0.4993 | F39: =IFERROR(__xludf.DUMMYFUNCTION("""COMPUTED_VALUE"""),98056) -> 98056 | G39: =IFERROR(__xludf.DUMMYFUNCTION("""COMPUTED_VALUE"""),0.3889) -> 0.3889 | H39: =IFERROR(__xludf.DUMMYFUNCTION("""COMPUTED_VALUE"""),2462) -> 2462 | I39: =IFERROR(__xludf.DUMMYFUNCTION("""COMPUTED_VALUE"""),100518) -> 100518 | J39: =IFERROR(__xludf.DUMMYFUNCTION("""COMPUTED_VALUE"""),89925) -> 89925 | K39: =IFERROR(__xludf.DUMMYFUNCTION("""COMPUTED_VALUE"""),3.47) -> 3.47
A40: =IFERROR(__xludf.DUMMYFUNCTION("""COMPUTED_VALUE"""),"106.2Q") -> 106.2Q | B40: =IFERROR(__xludf.DUMMYFUNCTION("""COMPUTED_VALUE"""),213855) -> 213855 | C40: =IFERROR(__xludf.DUMMYFUNCTION("""COMPUTED_VALUE"""),105102) -> 105102 | D40: =IFERROR(__xludf.DUMMYFUNCTION("""COMPUTED_VALUE"""),108753) -> 108753 | E40: =IFERROR(__xludf.DUMMYFUNCTION("""COMPUTED_VALUE"""),0.5085) -> 0.5085 | F40: =IFERROR(__xludf.DUMMYFUNCTION("""COMPUTED_VALUE"""),83255) -> 83255 | G40: =IFERROR(__xludf.DUMMYFUNCTION("""COMPUTED_VALUE"""),0.3893) -> 0.3893 | H40: =IFERROR(__xludf.DUMMYFUNCTION("""COMPUTED_VALUE"""),2862) -> 2862 | I40: =IFERROR(__xludf.DUMMYFUNCTION("""COMPUTED_VALUE"""),86117) -> 86117 | J40: =IFERROR(__xludf.DUMMYFUNCTION("""COMPUTED_VALUE"""),66271) -> 66271 | K40: =IFERROR(__xludf.DUMMYFUNCTION("""COMPUTED_VALUE"""),2.56) -> 2.56
A41: =IFERROR(__xludf.DUMMYFUNCTION("""COMPUTED_VALUE"""),"106.1Q") -> 106.1Q | B41: =IFERROR(__xludf.DUMMYFUNCTION("""COMPUTED_VALUE"""),233914) -> 233914 | C41: =IFERROR(__xludf.DUMMYFUNCTION("""COMPUTED_VALUE"""),112429) -> 112429 | D41: =IFERROR(__xludf.DUMMYFUNCTION("""COMPUTED_VALUE"""),121486) -> 121486 | E41: =IFERROR(__xludf.DUMMYFUNCTION("""COMPUTED_VALUE"""),0.5194) -> 0.5194 | F41: =IFERROR(__xludf.DUMMYFUNCTION("""COMPUTED_VALUE"""),95352) -> 95352 | G41: =IFERROR(__xludf.DUMMYFUNCTION("""COMPUTED_VALUE"""),0.4076) -> 0.4076 | H41: =IFERROR(__xludf.DUMMYFUNCTION("""COMPUTED_VALUE"""),2470) -> 2470 | I41: =IFERROR(__xludf.DUMMYFUNCTION("""COMPUTED_VALUE"""),97822) -> 97822 | J41: =IFERROR(__xludf.DUMMYFUNCTION("""COMPUTED_VALUE"""),87629) -> 87629 | K41: =IFERROR(__xludf.DUMMYFUNCTION("""COMPUTED_VALUE"""),3.38) -> 3.38
A42: =IFERROR(__xludf.DUMMYFUNCTION("""COMPUTED_VALUE"""),"105.4Q") -> 105.4Q | B42: =IFERROR(__xludf.DUMMYFUNCTION("""COMPUTED_VALUE"""),262227) -> 262227 | C42: =IFERROR(__xludf.DUMMYFUNCTION("""COMPUTED_VALUE"""),125117) -> 125117 | D42: =IFERROR(__xludf.DUMMYFUNCTION("""COMPUTED_VALUE"""),137110) -> 137110 | E42: =IFERROR(__xludf.DUMMYFUNCTION("""COMPUTED_VALUE"""),0.5229) -> 0.5229 | F42: =IFERROR(__xludf.DUMMYFUNCTION("""COMPUTED_VALUE"""),109907) -> 109907 | G42: =IFERROR(__xludf.DUMMYFUNCTION("""COMPUTED_VALUE"""),0.4191) -> 0.4191 | H42: =IFERROR(__xludf.DUMMYFUNCTION("""COMPUTED_VALUE"""),2140) -> 2140 | I42: =IFERROR(__xludf.DUMMYFUNCTION("""COMPUTED_VALUE"""),112047) -> 112047 | J42: =IFERROR(__xludf.DUMMYFUNCTION("""COMPUTED_VALUE"""),100200) -> 100200 | K42: =IFERROR(__xludf.DUMMYFUNCTION("""COMPUTED_VALUE"""),3.86) -> 3.86
A43: =IFERROR(__xludf.DUMMYFUNCTION("""COMPUTED_VALUE"""),"105.3Q") -> 105.3Q | B43: =IFERROR(__xludf.DUMMYFUNCTION("""COMPUTED_VALUE"""),260406) -> 260406 | C43: =IFERROR(__xludf.DUMMYFUNCTION("""COMPUTED_VALUE"""),128367) -> 128367 | D43: =IFERROR(__xludf.DUMMYFUNCTION("""COMPUTED_VALUE"""),132039) -> 132039 | E43: =IFERROR(__xludf.DUMMYFUNCTION("""COMPUTED_VALUE"""),0.5071) -> 0.5071 | F43: =IFERROR(__xludf.DUMMYFUNCTION("""COMPUTED_VALUE"""),106262) -> 106262 | G43: =IFERROR(__xludf.DUMMYFUNCTION("""COMPUTED_VALUE"""),0.4081) -> 0.4081 | H43: =IFERROR(__xludf.DUMMYFUNCTION("""COMPUTED_VALUE"""),1987) -> 1987 | I43: =IFERROR(__xludf.DUMMYFUNCTION("""COMPUTED_VALUE"""),108250) -> 108250 | J43: =IFERROR(__xludf.DUMMYFUNCTION("""COMPUTED_VALUE"""),96759) -> 96759 | K43: =IFERROR(__xludf.DUMMYFUNCTION("""COMPUTED_VALUE"""),3.73) -> 3.73
A44: =IFERROR(__xludf.DUMMYFUNCTION("""COMPUTED_VALUE"""),"105.2Q") -> 105.2Q | B44: =IFERROR(__xludf.DUMMYFUNCTION("""COMPUTED_VALUE"""),221810) -> 221810 | C44: =IFERROR(__xludf.DUMMYFUNCTION("""COMPUTED_VALUE"""),107469) -> 107469 | D44: =IFERROR(__xludf.DUMMYFUNCTION("""COMPUTED_VALUE"""),114341) -> 114341 | E44: =IFERROR(__xludf.DUMMYFUNCTION("""COMPUTED_VALUE"""),0.5155) -> 0.5155 | F44: =IFERROR(__xludf.DUMMYFUNCTION("""COMPUTED_VALUE"""),91321) -> 91321 | G44: =IFERROR(__xludf.DUMMYFUNCTION("""COMPUTED_VALUE"""),0.4117) -> 0.4117 | H44: =IFERROR(__xludf.DUMMYFUNCTION("""COMPUTED_VALUE"""),2085) -> 2085 | I44: =IFERROR(__xludf.DUMMYFUNCTION("""COMPUTED_VALUE"""),93406) -> 93406 | J44: =IFERROR(__xludf.DUMMYFUNCTION("""COMPUTED_VALUE"""),72506) -> 72506 | K44: =IFERROR(__xludf.DUMMYFUNCTION("""COMPUTED_VALUE"""),2.8) -> 2.8
A45: =IFERROR(__xludf.DUMMYFUNCTION("""COMPUTED_VALUE"""),"105.1Q") -> 105.1Q | B45: =IFERROR(__xludf.DUMMYFUNCTION("""COMPUTED_VALUE"""),203495) -> 203495 | C45: =IFERROR(__xludf.DUMMYFUNCTION("""COMPUTED_VALUE"""),112125) -> 112125 | D45: =IFERROR(__xludf.DUMMYFUNCTION("""COMPUTED_VALUE"""),91370) -> 91370 | E45: =IFERROR(__xludf.DUMMYFUNCTION("""COMPUTED_VALUE"""),0.449) -> 0.449 | F45: =IFERROR(__xludf.DUMMYFUNCTION("""COMPUTED_VALUE"""),70467) -> 70467 | G45: =IFERROR(__xludf.DUMMYFUNCTION("""COMPUTED_VALUE"""),0.3463) -> 0.3463 | H45: =IFERROR(__xludf.DUMMYFUNCTION("""COMPUTED_VALUE"""),1789) -> 1789 | I45: =IFERROR(__xludf.DUMMYFUNCTION("""COMPUTED_VALUE"""),72256) -> 72256 | J45: =IFERROR(__xludf.DUMMYFUNCTION("""COMPUTED_VALUE"""),64781) -> 64781 | K45: =IFERROR(__xludf.DUMMYFUNCTION("""COMPUTED_VALUE"""),2.5) -> 2.5
A46: =IFERROR(__xludf.DUMMYFUNCTION("""COMPUTED_VALUE"""),"104.4Q") -> 104.4Q | B46: =IFERROR(__xludf.DUMMYFUNCTION("""COMPUTED_VALUE"""),203519) -> 203519 | C46: =IFERROR(__xludf.DUMMYFUNCTION("""COMPUTED_VALUE"""),104608) -> 104608 | D46: =IFERROR(__xludf.DUMMYFUNCTION("""COMPUTED_VALUE"""),98911) -> 98911 | E46: =IFERROR(__xludf.DUMMYFUNCTION("""COMPUTED_VALUE"""),0.486) -> 0.486 | F46: =IFERROR(__xludf.DUMMYFUNCTION("""COMPUTED_VALUE"""),77964) -> 77964 | G46: =IFERROR(__xludf.DUMMYFUNCTION("""COMPUTED_VALUE"""),0.3831) -> 0.3831 | H46: =IFERROR(__xludf.DUMMYFUNCTION("""COMPUTED_VALUE"""),2680) -> 2680 | I46: =IFERROR(__xludf.DUMMYFUNCTION("""COMPUTED_VALUE"""),80644) -> 80644 | J46: =IFERROR(__xludf.DUMMYFUNCTION("""COMPUTED_VALUE"""),72837) -> 72837 | K46: =IFERROR(__xludf.DUMMYFUNCTION("""COMPUTED_VALUE"""),2.81) -> 2.81
A47: =IFERROR(__xludf.DUMMYFUNCTION("""COMPUTED_VALUE"""),"104.3Q") -> 104.3Q | B47: =IFERROR(__xludf.DUMMYFUNCTION("""COMPUTED_VALUE"""),212505) -> 212505 | C47: =IFERROR(__xludf.DUMMYFUNCTION("""COMPUTED_VALUE"""),110188) -> 110188 | D47: =IFERROR(__xludf.DUMMYFUNCTION("""COMPUTED_VALUE"""),102316) -> 102316 | E47: =IFERROR(__xludf.DUMMYFUNCTION("""COMPUTED_VALUE"""),0.4815) -> 0.4815 | F47: =IFERROR(__xludf.DUMMYFUNCTION("""COMPUTED_VALUE"""),78389) -> 78389 | G47: =IFERROR(__xludf.DUMMYFUNCTION("""COMPUTED_VALUE"""),0.3689) -> 0.3689 | H47: =IFERROR(__xludf.DUMMYFUNCTION("""COMPUTED_VALUE"""),5006) -> 5006 | I47: =IFERROR(__xludf.DUMMYFUNCTION("""COMPUTED_VALUE"""),83395) -> 83395 | J47: =IFERROR(__xludf.DUMMYFUNCTION("""COMPUTED_VALUE"""),75329) -> 75329 | K47: =IFERROR(__xludf.DUMMYFUNCTION("""COMPUTED_VALUE"""),2.91) -> 2.91
A48: =IFERROR(__xludf.DUMMYFUNCTION("""COMPUTED_VALUE"""),"104.2Q") -> 104.2Q | B48: =IFERROR(__xludf.DUMMYFUNCTION("""COMPUTED_VALUE"""),205440) -> 205440 | C48: =IFERROR(__xludf.DUMMYFUNCTION("""COMPUTED_VALUE"""),105736) -> 105736 | D48: =IFERROR(__xludf.DUMMYFUNCTION("""COMPUTED_VALUE"""),99704) -> 99704 | E48: =IFERROR(__xludf.DUMMYFUNCTION("""COMPUTED_VALUE"""),0.4853) -> 0.4853 | F48: =IFERROR(__xludf.DUMMYFUNCTION("""COMPUTED_VALUE"""),77069) -> 77069 | G48: =IFERROR(__xludf.DUMMYFUNCTION("""COMPUTED_VALUE"""),0.3751) -> 0.3751 | H48: =IFERROR(__xludf.DUMMYFUNCTION("""COMPUTED_VALUE"""),21063) -> 21063 | I48: =IFERROR(__xludf.DUMMYFUNCTION("""COMPUTED_VALUE"""),98132) -> 98132 | J48: =IFERROR(__xludf.DUMMYFUNCTION("""COMPUTED_VALUE"""),79418) -> 79418 | K48: =IFERROR(__xludf.DUMMYFUNCTION("""COMPUTED_VALUE"""),3.06) -> 3.06
A49: =IFERROR(__xludf.DUMMYFUNCTION("""COMPUTED_VALUE"""),"104.1Q") -> 104.1Q | B49: =IFERROR(__xludf.DUMMYFUNCTION("""COMPUTED_VALUE"""),222034) -> 222034 | C49: =IFERROR(__xludf.DUMMYFUNCTION("""COMPUTED_VALUE"""),112585) -> 112585 | D49: =IFERROR(__xludf.DUMMYFUNCTION("""COMPUTED_VALUE"""),109449) -> 109449 | E49: =IFERROR(__xludf.DUMMYFUNCTION("""COMPUTED_VALUE"""),0.4929) -> 0.4929 | F49: =IFERROR(__xludf.DUMMYFUNCTION("""COMPUTED_VALUE"""),86626) -> 86626 | G49: =IFERROR(__xludf.DUMMYFUNCTION("""COMPUTED_VALUE"""),0.3901) -> 0.3901 | H49: =IFERROR(__xludf.DUMMYFUNCTION("""COMPUTED_VALUE"""),1633) -> 1633 | I49: =IFERROR(__xludf.DUMMYFUNCTION("""COMPUTED_VALUE"""),88259) -> 88259 | J49: =IFERROR(__xludf.DUMMYFUNCTION("""COMPUTED_VALUE"""),78990) -> 78990 | K49: =IFERROR(__xludf.DUMMYFUNCTION("""COMPUTED_VALUE"""),3.05) -> 3.05
A50: =IFERROR(__xludf.DUMMYFUNCTION("""COMPUTED_VALUE"""),"103.4Q") -> 103.4Q | B50: =IFERROR(__xludf.DUMMYFUNCTION("""COMPUTED_VALUE"""),222521) -> 222521 | C50: =IFERROR(__xludf.DUMMYFUNCTION("""COMPUTED_VALUE"""),111976) -> 111976 | D50: =IFERROR(__xludf.DUMMYFUNCTION("""COMPUTED_VALUE"""),110545) -> 110545 | E50: =IFERROR(__xludf.DUMMYFUNCTION("""COMPUTED_VALUE"""),0.4968) -> 0.4968 | F50: =IFERROR(__xludf.DUMMYFUNCTION("""COMPUTED_VALUE"""),88216) -> 88216 | G50: =IFERROR(__xludf.DUMMYFUNCTION("""COMPUTED_VALUE"""),0.3964) -> 0.3964 | H50: =IFERROR(__xludf.DUMMYFUNCTION("""COMPUTED_VALUE"""),1095) -> 1095 | I50: =IFERROR(__xludf.DUMMYFUNCTION("""COMPUTED_VALUE"""),89311) -> 89311 | J50: =IFERROR(__xludf.DUMMYFUNCTION("""COMPUTED_VALUE"""),79985) -> 79985 | K50: =IFERROR(__xludf.DUMMYFUNCTION("""COMPUTED_VALUE"""),3.08) -> 3.08
A51: =IFERROR(__xludf.DUMMYFUNCTION("""COMPUTED_VALUE"""),"103.3Q") -> 103.3Q | B51: =IFERROR(__xludf.DUMMYFUNCTION("""COMPUTED_VALUE"""),209050) -> 209050 | C51: =IFERROR(__xludf.DUMMYFUNCTION("""COMPUTED_VALUE"""),103471) -> 103471 | D51: =IFERROR(__xludf.DUMMYFUNCTION("""COMPUTED_VALUE"""),105578) -> 105578 | E51: =IFERROR(__xludf.DUMMYFUNCTION("""COMPUTED_VALUE"""),0.505) -> 0.505 | F51: =IFERROR(__xludf.DUMMYFUNCTION("""COMPUTED_VALUE"""),84427) -> 84427 | G51: =IFERROR(__xludf.DUMMYFUNCTION("""COMPUTED_VALUE"""),0.4039) -> 0.4039 | H51: =IFERROR(__xludf.DUMMYFUNCTION("""COMPUTED_VALUE"""),949) -> 949 | I51: =IFERROR(__xludf.DUMMYFUNCTION("""COMPUTED_VALUE"""),85377) -> 85377 | J51: =IFERROR(__xludf.DUMMYFUNCTION("""COMPUTED_VALUE"""),76331) -> 76331 | K51: =IFERROR(__xludf.DUMMYFUNCTION("""COMPUTED_VALUE"""),2.94) -> 2.94
A52: =IFERROR(__xludf.DUMMYFUNCTION("""COMPUTED_VALUE"""),"103.2Q") -> 103.2Q | B52: =IFERROR(__xludf.DUMMYFUNCTION("""COMPUTED_VALUE"""),183020) -> 183020 | C52: =IFERROR(__xludf.DUMMYFUNCTION("""COMPUTED_VALUE"""),91826) -> 91826 | D52: =IFERROR(__xludf.DUMMYFUNCTION("""COMPUTED_VALUE"""),91194) -> 91194 | E52: =IFERROR(__xludf.DUMMYFUNCTION("""COMPUTED_VALUE"""),0.4983) -> 0.4983 | F52: =IFERROR(__xludf.DUMMYFUNCTION("""COMPUTED_VALUE"""),70709) -> 70709 | G52: =IFERROR(__xludf.DUMMYFUNCTION("""COMPUTED_VALUE"""),0.3863) -> 0.3863 | H52: =IFERROR(__xludf.DUMMYFUNCTION("""COMPUTED_VALUE"""),3384) -> 3384 | I52: =IFERROR(__xludf.DUMMYFUNCTION("""COMPUTED_VALUE"""),74094) -> 74094 | J52: =IFERROR(__xludf.DUMMYFUNCTION("""COMPUTED_VALUE"""),59698) -> 59698 | K52: =IFERROR(__xludf.DUMMYFUNCTION("""COMPUTED_VALUE"""),2.3) -> 2.3
A53: =IFERROR(__xludf.DUMMYFUNCTION("""COMPUTED_VALUE"""),"103.1Q") -> 103.1Q | B53: =IFERROR(__xludf.DUMMYFUNCTION("""COMPUTED_VALUE"""),148215) -> 148215 | C53: =IFERROR(__xludf.DUMMYFUNCTION("""COMPUTED_VALUE"""),77839) -> 77839 | D53: =IFERROR(__xludf.DUMMYFUNCTION("""COMPUTED_VALUE"""),70376) -> 70376 | E53: =IFERROR(__xludf.DUMMYFUNCTION("""COMPUTED_VALUE"""),0.4748) -> 0.4748 | F53: =IFERROR(__xludf.DUMMYFUNCTION("""COMPUTED_VALUE"""),52518) -> 52518 | G53: =IFERROR(__xludf.DUMMYFUNCTION("""COMPUTED_VALUE"""),0.3543) -> 0.3543 | H53: =IFERROR(__xludf.DUMMYFUNCTION("""COMPUTED_VALUE"""),780) -> 780 | I53: =IFERROR(__xludf.DUMMYFUNCTION("""COMPUTED_VALUE"""),53297) -> 53297 | J53: =IFERROR(__xludf.DUMMYFUNCTION("""COMPUTED_VALUE"""),47867) -> 47867 | K53: =IFERROR(__xludf.DUMMYFUNCTION("""COMPUTED_VALUE"""),1.85) -> 1.85
A54: =IFERROR(__xludf.DUMMYFUNCTION("""COMPUTED_VALUE"""),"102.4Q") -> 102.4Q | B54: =IFERROR(__xludf.DUMMYFUNCTION("""COMPUTED_VALUE"""),145806) -> 145806 | C54: =IFERROR(__xludf.DUMMYFUNCTION("""COMPUTED_VALUE"""),80965) -> 80965 | D54: =IFERROR(__xludf.DUMMYFUNCTION("""COMPUTED_VALUE"""),64841) -> 64841 | E54: =IFERROR(__xludf.DUMMYFUNCTION("""COMPUTED_VALUE"""),0.4447) -> 0.4447 | F54: =IFERROR(__xludf.DUMMYFUNCTION("""COMPUTED_VALUE"""),47754) -> 47754 | G54: =IFERROR(__xludf.DUMMYFUNCTION("""COMPUTED_VALUE"""),0.3275) -> 0.3275 | H54: =IFERROR(__xludf.DUMMYFUNCTION("""COMPUTED_VALUE"""),2618) -> 2618 | I54: =IFERROR(__xludf.DUMMYFUNCTION("""COMPUTED_VALUE"""),50373) -> 50373 | J54: =IFERROR(__xludf.DUMMYFUNCTION("""COMPUTED_VALUE"""),44810) -> 44810 | K54: =IFERROR(__xludf.DUMMYFUNCTION("""COMPUTED_VALUE"""),1.73) -> 1.73
A55: =IFERROR(__xludf.DUMMYFUNCTION("""COMPUTED_VALUE"""),"102.3Q") -> 102.3Q | B55: =IFERROR(__xludf.DUMMYFUNCTION("""COMPUTED_VALUE"""),162577) -> 162577 | C55: =IFERROR(__xludf.DUMMYFUNCTION("""COMPUTED_VALUE"""),83636) -> 83636 | D55: =IFERROR(__xludf.DUMMYFUNCTION("""COMPUTED_VALUE"""),78941) -> 78941 | E55: =IFERROR(__xludf.DUMMYFUNCTION("""COMPUTED_VALUE"""),0.4856) -> 0.4856 | F55: =IFERROR(__xludf.DUMMYFUNCTION("""COMPUTED_VALUE"""),59618) -> 59618 | G55: =IFERROR(__xludf.DUMMYFUNCTION("""COMPUTED_VALUE"""),0.3667) -> 0.3667 | H55: =IFERROR(__xludf.DUMMYFUNCTION("""COMPUTED_VALUE"""),-268) -> -268 | I55: =IFERROR(__xludf.DUMMYFUNCTION("""COMPUTED_VALUE"""),59350) -> 59350 | J55: =IFERROR(__xludf.DUMMYFUNCTION("""COMPUTED_VALUE"""),51952) -> 51952 | K55: =IFERROR(__xludf.DUMMYFUNCTION("""COMPUTED_VALUE"""),2) -> 2
A56: =IFERROR(__xludf.DUMMYFUNCTION("""COMPUTED_VALUE"""),"102.2Q") -> 102.2Q | B56: =IFERROR(__xludf.DUMMYFUNCTION("""COMPUTED_VALUE"""),155886) -> 155886 | C56: =IFERROR(__xludf.DUMMYFUNCTION("""COMPUTED_VALUE"""),79468) -> 79468 | D56: =IFERROR(__xludf.DUMMYFUNCTION("""COMPUTED_VALUE"""),76419) -> 76419 | E56: =IFERROR(__xludf.DUMMYFUNCTION("""COMPUTED_VALUE"""),0.4902) -> 0.4902 | F56: =IFERROR(__xludf.DUMMYFUNCTION("""COMPUTED_VALUE"""),57629) -> 57629 | G56: =IFERROR(__xludf.DUMMYFUNCTION("""COMPUTED_VALUE"""),0.3697) -> 0.3697 | H56: =IFERROR(__xludf.DUMMYFUNCTION("""COMPUTED_VALUE"""),2388) -> 2388 | I56: =IFERROR(__xludf.DUMMYFUNCTION("""COMPUTED_VALUE"""),60017) -> 60017 | J56: =IFERROR(__xludf.DUMMYFUNCTION("""COMPUTED_VALUE"""),51808) -> 51808 | K56: =IFERROR(__xludf.DUMMYFUNCTION("""COMPUTED_VALUE"""),2) -> 2
A57: =IFERROR(__xludf.DUMMYFUNCTION("""COMPUTED_VALUE"""),"102.1Q") -> 102.1Q | B57: =IFERROR(__xludf.DUMMYFUNCTION("""COMPUTED_VALUE"""),132755) -> 132755 | C57: =IFERROR(__xludf.DUMMYFUNCTION("""COMPUTED_VALUE"""),71989) -> 71989 | D57: =IFERROR(__xludf.DUMMYFUNCTION("""COMPUTED_VALUE"""),60766) -> 60766 | E57: =IFERROR(__xludf.DUMMYFUNCTION("""COMPUTED_VALUE"""),0.4577) -> 0.4577 | F57: =IFERROR(__xludf.DUMMYFUNCTION("""COMPUTED_VALUE"""),44428) -> 44428 | G57: =IFERROR(__xludf.DUMMYFUNCTION("""COMPUTED_VALUE"""),0.3347) -> 0.3347 | H57: =IFERROR(__xludf.DUMMYFUNCTION("""COMPUTED_VALUE"""),1320) -> 1320 | I57: =IFERROR(__xludf.DUMMYFUNCTION("""COMPUTED_VALUE"""),45748) -> 45748 | J57: =IFERROR(__xludf.DUMMYFUNCTION("""COMPUTED_VALUE"""),39577) -> 39577 | K57: =IFERROR(__xludf.DUMMYFUNCTION("""COMPUTED_VALUE"""),1.53) -> 1.53
A58: =IFERROR(__xludf.DUMMYFUNCTION("""COMPUTED_VALUE"""),"101.4Q") -> 101.4Q | B58: =IFERROR(__xludf.DUMMYFUNCTION("""COMPUTED_VALUE"""),131445) -> 131445 | C58: =IFERROR(__xludf.DUMMYFUNCTION("""COMPUTED_VALUE"""),69449) -> 69449 | D58: =IFERROR(__xludf.DUMMYFUNCTION("""COMPUTED_VALUE"""),61996) -> 61996 | E58: =IFERROR(__xludf.DUMMYFUNCTION("""COMPUTED_VALUE"""),0.4716) -> 0.4716 | F58: =IFERROR(__xludf.DUMMYFUNCTION("""COMPUTED_VALUE"""),46389) -> 46389 | G58: =IFERROR(__xludf.DUMMYFUNCTION("""COMPUTED_VALUE"""),0.3529) -> 0.3529 | H58: =IFERROR(__xludf.DUMMYFUNCTION("""COMPUTED_VALUE"""),-105) -> -105 | I58: =IFERROR(__xludf.DUMMYFUNCTION("""COMPUTED_VALUE"""),46284) -> 46284 | J58: =IFERROR(__xludf.DUMMYFUNCTION("""COMPUTED_VALUE"""),41604) -> 41604 | K58: =IFERROR(__xludf.DUMMYFUNCTION("""COMPUTED_VALUE"""),1.61) -> 1.61
A59: =IFERROR(__xludf.DUMMYFUNCTION("""COMPUTED_VALUE"""),"101.3Q") -> 101.3Q | B59: =IFERROR(__xludf.DUMMYFUNCTION("""COMPUTED_VALUE"""),141499) -> 141499 | C59: =IFERROR(__xludf.DUMMYFUNCTION("""COMPUTED_VALUE"""),72345) -> 72345 | D59: =IFERROR(__xludf.DUMMYFUNCTION("""COMPUTED_VALUE"""),69155) -> 69155 | E59: =IFERROR(__xludf.DUMMYFUNCTION("""COMPUTED_VALUE"""),0.4887) -> 0.4887 | F59: =IFERROR(__xludf.DUMMYFUNCTION("""COMPUTED_VALUE"""),52798) -> 52798 | G59: =IFERROR(__xludf.DUMMYFUNCTION("""COMPUTED_VALUE"""),0.3731) -> 0.3731 | H59: =IFERROR(__xludf.DUMMYFUNCTION("""COMPUTED_VALUE"""),964) -> 964 | I59: =IFERROR(__xludf.DUMMYFUNCTION("""COMPUTED_VALUE"""),53762) -> 53762 | J59: =IFERROR(__xludf.DUMMYFUNCTION("""COMPUTED_VALUE"""),49380) -> 49380 | K59: =IFERROR(__xludf.DUMMYFUNCTION("""COMPUTED_VALUE"""),1.91) -> 1.91
A60: =IFERROR(__xludf.DUMMYFUNCTION("""COMPUTED_VALUE"""),"101.2Q") -> 101.2Q | B60: =IFERROR(__xludf.DUMMYFUNCTION("""COMPUTED_VALUE"""),128186) -> 128186 | C60: =IFERROR(__xludf.DUMMYFUNCTION("""COMPUTED_VALUE"""),65579) -> 65579 | D60: =IFERROR(__xludf.DUMMYFUNCTION("""COMPUTED_VALUE"""),62607) -> 62607 | E60: =IFERROR(__xludf.DUMMYFUNCTION("""COMPUTED_VALUE"""),0.4884) -> 0.4884 | F60: =IFERROR(__xludf.DUMMYFUNCTION("""COMPUTED_VALUE"""),46872) -> 46872 | G60: =IFERROR(__xludf.DUMMYFUNCTION("""COMPUTED_VALUE"""),0.3657) -> 0.3657 | H60: =IFERROR(__xludf.DUMMYFUNCTION("""COMPUTED_VALUE"""),-915) -> -915 | I60: =IFERROR(__xludf.DUMMYFUNCTION("""COMPUTED_VALUE"""),45957) -> 45957 | J60: =IFERROR(__xludf.DUMMYFUNCTION("""COMPUTED_VALUE"""),41843) -> 41843 | K60: =IFERROR(__xludf.DUMMYFUNCTION("""COMPUTED_VALUE"""),1.61) -> 1.61
A61: =IFERROR(__xludf.DUMMYFUNCTION("""COMPUTED_VALUE"""),"101.1Q") -> 101.1Q | B61: =IFERROR(__xludf.DUMMYFUNCTION("""COMPUTED_VALUE"""),105615) -> 105615 | C61: =IFERROR(__xludf.DUMMYFUNCTION("""COMPUTED_VALUE"""),55210) -> 55210 | D61: =IFERROR(__xludf.DUMMYFUNCTION("""COMPUTED_VALUE"""),50404) -> 50404 | E61: =IFERROR(__xludf.DUMMYFUNCTION("""COMPUTED_VALUE"""),0.4772) -> 0.4772 | F61: =IFERROR(__xludf.DUMMYFUNCTION("""COMPUTED_VALUE"""),35117) -> 35117 | G61: =IFERROR(__xludf.DUMMYFUNCTION("""COMPUTED_VALUE"""),0.3325) -> 0.3325 | H61: =IFERROR(__xludf.DUMMYFUNCTION("""COMPUTED_VALUE"""),556) -> 556 | I61: =IFERROR(__xludf.DUMMYFUNCTION("""COMPUTED_VALUE"""),35673) -> 35673 | J61: =IFERROR(__xludf.DUMMYFUNCTION("""COMPUTED_VALUE"""),33492) -> 33492 | K61: =IFERROR(__xludf.DUMMYFUNCTION("""COMPUTED_VALUE"""),1.29) -> 1.29
A62: =IFERROR(__xludf.DUMMYFUNCTION("""COMPUTED_VALUE"""),"100.4Q") -> 100.4Q | B62: =IFERROR(__xludf.DUMMYFUNCTION("""COMPUTED_VALUE"""),104711) -> 104711 | C62: =IFERROR(__xludf.DUMMYFUNCTION("""COMPUTED_VALUE"""),57865) -> 57865 | D62: =IFERROR(__xludf.DUMMYFUNCTION("""COMPUTED_VALUE"""),46846) -> 46846 | E62: =IFERROR(__xludf.DUMMYFUNCTION("""COMPUTED_VALUE"""),0.4474) -> 0.4474 | F62: =IFERROR(__xludf.DUMMYFUNCTION("""COMPUTED_VALUE"""),32930) -> 32930 | G62: =IFERROR(__xludf.DUMMYFUNCTION("""COMPUTED_VALUE"""),0.3145) -> 0.3145 | H62: =IFERROR(__xludf.DUMMYFUNCTION("""COMPUTED_VALUE"""),691) -> 691 | I62: =IFERROR(__xludf.DUMMYFUNCTION("""COMPUTED_VALUE"""),33621) -> 33621 | J62: =IFERROR(__xludf.DUMMYFUNCTION("""COMPUTED_VALUE"""),31579) -> 31579 | K62: =IFERROR(__xludf.DUMMYFUNCTION("""COMPUTED_VALUE"""),1.22) -> 1.22
A63: =IFERROR(__xludf.DUMMYFUNCTION("""COMPUTED_VALUE"""),"100.3Q") -> 100.3Q | B63: =IFERROR(__xludf.DUMMYFUNCTION("""COMPUTED_VALUE"""),106484) -> 106484 | C63: =IFERROR(__xludf.DUMMYFUNCTION("""COMPUTED_VALUE"""),61713) -> 61713 | D63: =IFERROR(__xludf.DUMMYFUNCTION("""COMPUTED_VALUE"""),44771) -> 44771 | E63: =IFERROR(__xludf.DUMMYFUNCTION("""COMPUTED_VALUE"""),0.4204) -> 0.4204 | F63: =IFERROR(__xludf.DUMMYFUNCTION("""COMPUTED_VALUE"""),31598) -> 31598 | G63: =IFERROR(__xludf.DUMMYFUNCTION("""COMPUTED_VALUE"""),0.2967) -> 0.2967 | H63: =IFERROR(__xludf.DUMMYFUNCTION("""COMPUTED_VALUE"""),562) -> 562 | I63: =IFERROR(__xludf.DUMMYFUNCTION("""COMPUTED_VALUE"""),32160) -> 32160 | J63: =IFERROR(__xludf.DUMMYFUNCTION("""COMPUTED_VALUE"""),30395) -> 30395 | K63: =IFERROR(__xludf.DUMMYFUNCTION("""COMPUTED_VALUE"""),1.17) -> 1.17
A64: =IFERROR(__xludf.DUMMYFUNCTION("""COMPUTED_VALUE"""),"100.2Q") -> 100.2Q | B64: =IFERROR(__xludf.DUMMYFUNCTION("""COMPUTED_VALUE"""),110508) -> 110508 | C64: =IFERROR(__xludf.DUMMYFUNCTION("""COMPUTED_VALUE"""),59652) -> 59652 | D64: =IFERROR(__xludf.DUMMYFUNCTION("""COMPUTED_VALUE"""),50856) -> 50856 | E64: =IFERROR(__xludf.DUMMYFUNCTION("""COMPUTED_VALUE"""),0.4602) -> 0.4602 | F64: =IFERROR(__xludf.DUMMYFUNCTION("""COMPUTED_VALUE"""),37866) -> 37866 | G64: =IFERROR(__xludf.DUMMYFUNCTION("""COMPUTED_VALUE"""),0.3427) -> 0.3427 | H64: =IFERROR(__xludf.DUMMYFUNCTION("""COMPUTED_VALUE"""),1188) -> 1188 | I64: =IFERROR(__xludf.DUMMYFUNCTION("""COMPUTED_VALUE"""),39055) -> 39055 | J64: =IFERROR(__xludf.DUMMYFUNCTION("""COMPUTED_VALUE"""),35950) -> 35950 | K64: =IFERROR(__xludf.DUMMYFUNCTION("""COMPUTED_VALUE"""),1.39) -> 1.39
A65: =IFERROR(__xludf.DUMMYFUNCTION("""COMPUTED_VALUE"""),"100.1Q") -> 100.1Q | B65: =IFERROR(__xludf.DUMMYFUNCTION("""COMPUTED_VALUE"""),105377) -> 105377 | C65: =IFERROR(__xludf.DUMMYFUNCTION("""COMPUTED_VALUE"""),53707) -> 53707 | D65: =IFERROR(__xludf.DUMMYFUNCTION("""COMPUTED_VALUE"""),51671) -> 51671 | E65: =IFERROR(__xludf.DUMMYFUNCTION("""COMPUTED_VALUE"""),0.4903) -> 0.4903 | F65: =IFERROR(__xludf.DUMMYFUNCTION("""COMPUTED_VALUE"""),39163) -> 39163 | G65: =IFERROR(__xludf.DUMMYFUNCTION("""COMPUTED_VALUE"""),0.3716) -> 0.3716 | H65: =IFERROR(__xludf.DUMMYFUNCTION("""COMPUTED_VALUE"""),1149) -> 1149 | I65: =IFERROR(__xludf.DUMMYFUNCTION("""COMPUTED_VALUE"""),40312) -> 40312 | J65: =IFERROR(__xludf.DUMMYFUNCTION("""COMPUTED_VALUE"""),36278) -> 36278 | K65: =IFERROR(__xludf.DUMMYFUNCTION("""COMPUTED_VALUE"""),1.4) -> 1.4
A66: =IFERROR(__xludf.DUMMYFUNCTION("""COMPUTED_VALUE"""),"99.4Q") -> 99.4Q | B66: =IFERROR(__xludf.DUMMYFUNCTION("""COMPUTED_VALUE"""),110142) -> 110142 | C66: =IFERROR(__xludf.DUMMYFUNCTION("""COMPUTED_VALUE"""),55325) -> 55325 | D66: =IFERROR(__xludf.DUMMYFUNCTION("""COMPUTED_VALUE"""),54817) -> 54817 | E66: =IFERROR(__xludf.DUMMYFUNCTION("""COMPUTED_VALUE"""),0.4977) -> 0.4977 | F66: =IFERROR(__xludf.DUMMYFUNCTION("""COMPUTED_VALUE"""),41513) -> 41513 | G66: =IFERROR(__xludf.DUMMYFUNCTION("""COMPUTED_VALUE"""),0.3769) -> 0.3769 | H66: =IFERROR(__xludf.DUMMYFUNCTION("""COMPUTED_VALUE"""),1369) -> 1369 | I66: =IFERROR(__xludf.DUMMYFUNCTION("""COMPUTED_VALUE"""),42882) -> 42882 | J66: =IFERROR(__xludf.DUMMYFUNCTION("""COMPUTED_VALUE"""),40720) -> 40720 | K66: =IFERROR(__xludf.DUMMYFUNCTION("""COMPUTED_VALUE"""),1.57) -> 1.57
A67: =IFERROR(__xludf.DUMMYFUNCTION("""COMPUTED_VALUE"""),"99.3Q") -> 99.3Q | B67: =IFERROR(__xludf.DUMMYFUNCTION("""COMPUTED_VALUE"""),112247) -> 112247 | C67: =IFERROR(__xludf.DUMMYFUNCTION("""COMPUTED_VALUE"""),56122) -> 56122 | D67: =IFERROR(__xludf.DUMMYFUNCTION("""COMPUTED_VALUE"""),56125) -> 56125 | E67: =IFERROR(__xludf.DUMMYFUNCTION("""COMPUTED_VALUE"""),0.5) -> 0.5 | F67: =IFERROR(__xludf.DUMMYFUNCTION("""COMPUTED_VALUE"""),43066) -> 43066 | G67: =IFERROR(__xludf.DUMMYFUNCTION("""COMPUTED_VALUE"""),0.3837) -> 0.3837 | H67: =IFERROR(__xludf.DUMMYFUNCTION("""COMPUTED_VALUE"""),6610) -> 6610 | I67: =IFERROR(__xludf.DUMMYFUNCTION("""COMPUTED_VALUE"""),49675) -> 49675 | J67: =IFERROR(__xludf.DUMMYFUNCTION("""COMPUTED_VALUE"""),46940) -> 46940 | K67: =IFERROR(__xludf.DUMMYFUNCTION("""COMPUTED_VALUE"""),1.81) -> 1.81
A68: =IFERROR(__xludf.DUMMYFUNCTION("""COMPUTED_VALUE"""),"99.2Q") -> 99.2Q | B68: =IFERROR(__xludf.DUMMYFUNCTION("""COMPUTED_VALUE"""),104962) -> 104962 | C68: =IFERROR(__xludf.DUMMYFUNCTION("""COMPUTED_VALUE"""),53036) -> 53036 | D68: =IFERROR(__xludf.DUMMYFUNCTION("""COMPUTED_VALUE"""),51926) -> 51926 | E68: =IFERROR(__xludf.DUMMYFUNCTION("""COMPUTED_VALUE"""),0.4947) -> 0.4947 | F68: =IFERROR(__xludf.DUMMYFUNCTION("""COMPUTED_VALUE"""),40469) -> 40469 | G68: =IFERROR(__xludf.DUMMYFUNCTION("""COMPUTED_VALUE"""),0.3856) -> 0.3856 | H68: =IFERROR(__xludf.DUMMYFUNCTION("""COMPUTED_VALUE"""),1941) -> 1941 | I68: =IFERROR(__xludf.DUMMYFUNCTION("""COMPUTED_VALUE"""),42410) -> 42410 | J68: =IFERROR(__xludf.DUMMYFUNCTION("""COMPUTED_VALUE"""),40282) -> 40282 | K68: =IFERROR(__xludf.DUMMYFUNCTION("""COMPUTED_VALUE"""),1.56) -> 1.56
A69: =IFERROR(__xludf.DUMMYFUNCTION("""COMPUTED_VALUE"""),"99.1Q") -> 99.1Q | B69: =IFERROR(__xludf.DUMMYFUNCTION("""COMPUTED_VALUE"""),92187) -> 92187 | C69: =IFERROR(__xludf.DUMMYFUNCTION("""COMPUTED_VALUE"""),48001) -> 48001 | D69: =IFERROR(__xludf.DUMMYFUNCTION("""COMPUTED_VALUE"""),44185) -> 44185 | E69: =IFERROR(__xludf.DUMMYFUNCTION("""COMPUTED_VALUE"""),0.4793) -> 0.4793 | F69: =IFERROR(__xludf.DUMMYFUNCTION("""COMPUTED_VALUE"""),34128) -> 34128 | G69: =IFERROR(__xludf.DUMMYFUNCTION("""COMPUTED_VALUE"""),0.3702) -> 0.3702 | H69: =IFERROR(__xludf.DUMMYFUNCTION("""COMPUTED_VALUE"""),1175) -> 1175 | I69: =IFERROR(__xludf.DUMMYFUNCTION("""COMPUTED_VALUE"""),35303) -> 35303 | J69: =IFERROR(__xludf.DUMMYFUNCTION("""COMPUTED_VALUE"""),33663) -> 33663 | K69: =IFERROR(__xludf.DUMMYFUNCTION("""COMPUTED_VALUE"""),1.3) -> 1.3
A70: =IFERROR(__xludf.DUMMYFUNCTION("""COMPUTED_VALUE"""),"98.4Q") -> 98.4Q | B70: =IFERROR(__xludf.DUMMYFUNCTION("""COMPUTED_VALUE"""),92094) -> 92094 | C70: =IFERROR(__xludf.DUMMYFUNCTION("""COMPUTED_VALUE"""),47400) -> 47400 | D70: =IFERROR(__xludf.DUMMYFUNCTION("""COMPUTED_VALUE"""),44695) -> 44695 | E70: =IFERROR(__xludf.DUMMYFUNCTION("""COMPUTED_VALUE"""),0.4853) -> 0.4853 | F70: =IFERROR(__xludf.DUMMYFUNCTION("""COMPUTED_VALUE"""),33642) -> 33642 | G70: =IFERROR(__xludf.DUMMYFUNCTION("""COMPUTED_VALUE"""),0.3653) -> 0.3653 | H70: =IFERROR(__xludf.DUMMYFUNCTION("""COMPUTED_VALUE"""),1726) -> 1726 | I70: =IFERROR(__xludf.DUMMYFUNCTION("""COMPUTED_VALUE"""),35368) -> 35368 | J70: =IFERROR(__xludf.DUMMYFUNCTION("""COMPUTED_VALUE"""),32666) -> 32666 | K70: =IFERROR(__xludf.DUMMYFUNCTION("""COMPUTED_VALUE"""),1.26) -> 1.26
A71: =IFERROR(__xludf.DUMMYFUNCTION("""COMPUTED_VALUE"""),"98.3Q") -> 98.3Q | B71: =IFERROR(__xludf.DUMMYFUNCTION("""COMPUTED_VALUE"""),89936) -> 89936 | C71: =IFERROR(__xludf.DUMMYFUNCTION("""COMPUTED_VALUE"""),47078) -> 47078 | D71: =IFERROR(__xludf.DUMMYFUNCTION("""COMPUTED_VALUE"""),42858) -> 42858 | E71: =IFERROR(__xludf.DUMMYFUNCTION("""COMPUTED_VALUE"""),0.4765) -> 0.4765 | F71: =IFERROR(__xludf.DUMMYFUNCTION("""COMPUTED_VALUE"""),31984) -> 31984 | G71: =IFERROR(__xludf.DUMMYFUNCTION("""COMPUTED_VALUE"""),0.3556) -> 0.3556 | H71: =IFERROR(__xludf.DUMMYFUNCTION("""COMPUTED_VALUE"""),973) -> 973 | I71: =IFERROR(__xludf.DUMMYFUNCTION("""COMPUTED_VALUE"""),32957) -> 32957 | J71: =IFERROR(__xludf.DUMMYFUNCTION("""COMPUTED_VALUE"""),30551) -> 30551 | K71: =IFERROR(__xludf.DUMMYFUNCTION("""COMPUTED_VALUE"""),1.18) -> 1.18
A72: =IFERROR(__xludf.DUMMYFUNCTION("""COMPUTED_VALUE"""),"98.2Q") -> 98.2Q | B72: =IFERROR(__xludf.DUMMYFUNCTION("""COMPUTED_VALUE"""),74212) -> 74212 | C72: =IFERROR(__xludf.DUMMYFUNCTION("""COMPUTED_VALUE"""),39916) -> 39916 | D72: =IFERROR(__xludf.DUMMYFUNCTION("""COMPUTED_VALUE"""),34296) -> 34296 | E72: =IFERROR(__xludf.DUMMYFUNCTION("""COMPUTED_VALUE"""),0.4621) -> 0.4621 | F72: =IFERROR(__xludf.DUMMYFUNCTION("""COMPUTED_VALUE"""),25127) -> 25127 | G72: =IFERROR(__xludf.DUMMYFUNCTION("""COMPUTED_VALUE"""),0.3386) -> 0.3386 | H72: =IFERROR(__xludf.DUMMYFUNCTION("""COMPUTED_VALUE"""),1262) -> 1262 | I72: =IFERROR(__xludf.DUMMYFUNCTION("""COMPUTED_VALUE"""),26389) -> 26389 | J72: =IFERROR(__xludf.DUMMYFUNCTION("""COMPUTED_VALUE"""),24442) -> 24442 | K72: =IFERROR(__xludf.DUMMYFUNCTION("""COMPUTED_VALUE"""),0.95) -> 0.95
A73: =IFERROR(__xludf.DUMMYFUNCTION("""COMPUTED_VALUE"""),"98.1Q") -> 98.1Q | B73: =IFERROR(__xludf.DUMMYFUNCTION("""COMPUTED_VALUE"""),39500) -> 39500 | C73: =IFERROR(__xludf.DUMMYFUNCTION("""COMPUTED_VALUE"""),32020) -> 32020 | D73: =IFERROR(__xludf.DUMMYFUNCTION("""COMPUTED_VALUE"""),7480) -> 7480 | E73: =IFERROR(__xludf.DUMMYFUNCTION("""COMPUTED_VALUE"""),0.1894) -> 0.1894 | F73: =IFERROR(__xludf.DUMMYFUNCTION("""COMPUTED_VALUE"""),1209) -> 1209 | G73: =IFERROR(__xludf.DUMMYFUNCTION("""COMPUTED_VALUE"""),0.0306) -> 0.0306 | H73: =IFERROR(__xludf.DUMMYFUNCTION("""COMPUTED_VALUE"""),-461) -> -461 | I73: =IFERROR(__xludf.DUMMYFUNCTION("""COMPUTED_VALUE"""),748) -> 748 | J73: =IFERROR(__xludf.DUMMYFUNCTION("""COMPUTED_VALUE"""),1559) -> 1559 | K73: =IFERROR(__xludf.DUMMYFUNCTION("""COMPUTED_VALUE"""),0.06) -> 0.06
A74: =IFERROR(__xludf.DUMMYFUNCTION("""COMPUTED_VALUE"""),"97.4Q") -> 97.4Q | B74: =IFERROR(__xludf.DUMMYFUNCTION("""COMPUTED_VALUE"""),64562) -> 64562 | C74: =IFERROR(__xludf.DUMMYFUNCTION("""COMPUTED_VALUE"""),44367) -> 44367 | D74: =IFERROR(__xludf.DUMMYFUNCTION("""COMPUTED_VALUE"""),20195) -> 20195 | E74: =IFERROR(__xludf.DUMMYFUNCTION("""COMPUTED_VALUE"""),0.3128) -> 0.3128 | F74: =IFERROR(__xludf.DUMMYFUNCTION("""COMPUTED_VALUE"""),12022) -> 12022 | G74: =IFERROR(__xludf.DUMMYFUNCTION("""COMPUTED_VALUE"""),0.1862) -> 0.1862 | H74: =IFERROR(__xludf.DUMMYFUNCTION("""COMPUTED_VALUE"""),1072) -> 1072 | I74: =IFERROR(__xludf.DUMMYFUNCTION("""COMPUTED_VALUE"""),13094) -> 13094 | J74: =IFERROR(__xludf.DUMMYFUNCTION("""COMPUTED_VALUE"""),12446) -> 12446 | K74: =IFERROR(__xludf.DUMMYFUNCTION("""COMPUTED_VALUE"""),0.48) -> 0.48
A75: =IFERROR(__xludf.DUMMYFUNCTION("""COMPUTED_VALUE"""),"97.3Q") -> 97.3Q | B75: =IFERROR(__xludf.DUMMYFUNCTION("""COMPUTED_VALUE"""),92979) -> 92979 | C75: =IFERROR(__xludf.DUMMYFUNCTION("""COMPUTED_VALUE"""),49885) -> 49885 | D75: =IFERROR(__xludf.DUMMYFUNCTION("""COMPUTED_VALUE"""),43094) -> 43094 | E75: =IFERROR(__xludf.DUMMYFUNCTION("""COMPUTED_VALUE"""),0.4635) -> 0.4635 | F75: =IFERROR(__xludf.DUMMYFUNCTION("""COMPUTED_VALUE"""),32917) -> 32917 | G75: =IFERROR(__xludf.DUMMYFUNCTION("""COMPUTED_VALUE"""),0.354) -> 0.354 | H75: =IFERROR(__xludf.DUMMYFUNCTION("""COMPUTED_VALUE"""),1513) -> 1513 | I75: =IFERROR(__xludf.DUMMYFUNCTION("""COMPUTED_VALUE"""),34430) -> 34430 | J75: =IFERROR(__xludf.DUMMYFUNCTION("""COMPUTED_VALUE"""),30574) -> 30574 | K75: =IFERROR(__xludf.DUMMYFUNCTION("""COMPUTED_VALUE"""),1.18) -> 1.18
A76: =IFERROR(__xludf.DUMMYFUNCTION("""COMPUTED_VALUE"""),"97.2Q") -> 97.2Q | B76: =IFERROR(__xludf.DUMMYFUNCTION("""COMPUTED_VALUE"""),88137) -> 88137 | C76: =IFERROR(__xludf.DUMMYFUNCTION("""COMPUTED_VALUE"""),47915) -> 47915 | D76: =IFERROR(__xludf.DUMMYFUNCTION("""COMPUTED_VALUE"""),40221) -> 40221 | E76: =IFERROR(__xludf.DUMMYFUNCTION("""COMPUTED_VALUE"""),0.4564) -> 0.4564 | F76: =IFERROR(__xludf.DUMMYFUNCTION("""COMPUTED_VALUE"""),30373) -> 30373 | G76: =IFERROR(__xludf.DUMMYFUNCTION("""COMPUTED_VALUE"""),0.3446) -> 0.3446 | H76: =IFERROR(__xludf.DUMMYFUNCTION("""COMPUTED_VALUE"""),2004) -> 2004 | I76: =IFERROR(__xludf.DUMMYFUNCTION("""COMPUTED_VALUE"""),32377) -> 32377 | J76: =IFERROR(__xludf.DUMMYFUNCTION("""COMPUTED_VALUE"""),28771) -> 28771 | K76: =IFERROR(__xludf.DUMMYFUNCTION("""COMPUTED_VALUE"""),1.12) -> 1.12
A77: =IFERROR(__xludf.DUMMYFUNCTION("""COMPUTED_VALUE"""),"97.1Q") -> 97.1Q | B77: =IFERROR(__xludf.DUMMYFUNCTION("""COMPUTED_VALUE"""),87480) -> 87480 | C77: =IFERROR(__xludf.DUMMYFUNCTION("""COMPUTED_VALUE"""),49241) -> 49241 | D77: =IFERROR(__xludf.DUMMYFUNCTION("""COMPUTED_VALUE"""),38239) -> 38239 | E77: =IFERROR(__xludf.DUMMYFUNCTION("""COMPUTED_VALUE"""),0.4371) -> 0.4371 | F77: =IFERROR(__xludf.DUMMYFUNCTION("""COMPUTED_VALUE"""),29123) -> 29123 | G77: =IFERROR(__xludf.DUMMYFUNCTION("""COMPUTED_VALUE"""),0.3329) -> 0.3329 | H77: =IFERROR(__xludf.DUMMYFUNCTION("""COMPUTED_VALUE"""),2449) -> 2449 | I77: =IFERROR(__xludf.DUMMYFUNCTION("""COMPUTED_VALUE"""),31572) -> 31572 | J77: =IFERROR(__xludf.DUMMYFUNCTION("""COMPUTED_VALUE"""),28143) -> 28143 | K77: =IFERROR(__xludf.DUMMYFUNCTION("""COMPUTED_VALUE"""),1.1) -> 1.1
A78: =IFERROR(__xludf.DUMMYFUNCTION("""COMPUTED_VALUE"""),"96.4Q") -> 96.4Q | B78: =IFERROR(__xludf.DUMMYFUNCTION("""COMPUTED_VALUE"""),93860) -> 93860 | C78: =IFERROR(__xludf.DUMMYFUNCTION("""COMPUTED_VALUE"""),49024) -> 49024 | D78: =IFERROR(__xludf.DUMMYFUNCTION("""COMPUTED_VALUE"""),44836) -> 44836 | E78: =IFERROR(__xludf.DUMMYFUNCTION("""COMPUTED_VALUE"""),0.4777) -> 0.4777 | F78: =IFERROR(__xludf.DUMMYFUNCTION("""COMPUTED_VALUE"""),36758) -> 36758 | G78: =IFERROR(__xludf.DUMMYFUNCTION("""COMPUTED_VALUE"""),0.3916) -> 0.3916 | I78: =IFERROR(__xludf.DUMMYFUNCTION("""COMPUTED_VALUE"""),39332) -> 39332 | J78: =IFERROR(__xludf.DUMMYFUNCTION("""COMPUTED_VALUE"""),34485) -> 34485 | K78: =IFERROR(__xludf.DUMMYFUNCTION("""COMPUTED_VALUE"""),1.31) -> 1.31
A79: =IFERROR(__xludf.DUMMYFUNCTION("""COMPUTED_VALUE"""),"96.3Q") -> 96.3Q | B79: =IFERROR(__xludf.DUMMYFUNCTION("""COMPUTED_VALUE"""),88955) -> 88955 | C79: =IFERROR(__xludf.DUMMYFUNCTION("""COMPUTED_VALUE"""),48231) -> 48231 | D79: =IFERROR(__xludf.DUMMYFUNCTION("""COMPUTED_VALUE"""),40724) -> 40724 | E79: =IFERROR(__xludf.DUMMYFUNCTION("""COMPUTED_VALUE"""),0.4578) -> 0.4578 | F79: =IFERROR(__xludf.DUMMYFUNCTION("""COMPUTED_VALUE"""),32353) -> 32353 | G79: =IFERROR(__xludf.DUMMYFUNCTION("""COMPUTED_VALUE"""),0.3637) -> 0.3637 | I79: =IFERROR(__xludf.DUMMYFUNCTION("""COMPUTED_VALUE"""),34218) -> 34218 | J79: =IFERROR(__xludf.DUMMYFUNCTION("""COMPUTED_VALUE"""),30370) -> 30370 | K79: =IFERROR(__xludf.DUMMYFUNCTION("""COMPUTED_VALUE"""),1.15) -> 1.15
A80: =IFERROR(__xludf.DUMMYFUNCTION("""COMPUTED_VALUE"""),"96.2Q") -> 96.2Q | B80: =IFERROR(__xludf.DUMMYFUNCTION("""COMPUTED_VALUE"""),74918) -> 74918 | C80: =IFERROR(__xludf.DUMMYFUNCTION("""COMPUTED_VALUE"""),42738) -> 42738 | D80: =IFERROR(__xludf.DUMMYFUNCTION("""COMPUTED_VALUE"""),32180) -> 32180 | E80: =IFERROR(__xludf.DUMMYFUNCTION("""COMPUTED_VALUE"""),0.4295) -> 0.4295 | F80: =IFERROR(__xludf.DUMMYFUNCTION("""COMPUTED_VALUE"""),24734) -> 24734 | G80: =IFERROR(__xludf.DUMMYFUNCTION("""COMPUTED_VALUE"""),0.3301) -> 0.3301 | I80: =IFERROR(__xludf.DUMMYFUNCTION("""COMPUTED_VALUE"""),28024) -> 28024 | J80: =IFERROR(__xludf.DUMMYFUNCTION("""COMPUTED_VALUE"""),25484) -> 25484 | K80: =IFERROR(__xludf.DUMMYFUNCTION("""COMPUTED_VALUE"""),0.97) -> 0.97
A81: =IFERROR(__xludf.DUMMYFUNCTION("""COMPUTED_VALUE"""),"96.1Q") -> 96.1Q | B81: =IFERROR(__xludf.DUMMYFUNCTION("""COMPUTED_VALUE"""),64897) -> 64897 | C81: =IFERROR(__xludf.DUMMYFUNCTION("""COMPUTED_VALUE"""),40287) -> 40287 | D81: =IFERROR(__xludf.DUMMYFUNCTION("""COMPUTED_VALUE"""),24610) -> 24610 | E81: =IFERROR(__xludf.DUMMYFUNCTION("""COMPUTED_VALUE"""),0.3792) -> 0.3792 | F81: =IFERROR(__xludf.DUMMYFUNCTION("""COMPUTED_VALUE"""),17877) -> 17877 | G81: =IFERROR(__xludf.DUMMYFUNCTION("""COMPUTED_VALUE"""),0.2755) -> 0.2755 | I81: =IFERROR(__xludf.DUMMYFUNCTION("""COMPUTED_VALUE"""),20068) -> 20068 | J81: =IFERROR(__xludf.DUMMYFUNCTION("""COMPUTED_VALUE"""),18839) -> 18839 | K81: =IFERROR(__xludf.DUMMYFUNCTION("""COMPUTED_VALUE"""),0.73) -> 0.73
A82: =IFERROR(__xludf.DUMMYFUNCTION("""COMPUTED_VALUE"""),"95.4Q") -> 95.4Q | B82: =IFERROR(__xludf.DUMMYFUNCTION("""COMPUTED_VALUE"""),74963) -> 74963 | C82: =IFERROR(__xludf.DUMMYFUNCTION("""COMPUTED_VALUE"""),40510) -> 40510 | D82: =IFERROR(__xludf.DUMMYFUNCTION("""COMPUTED_VALUE"""),34453) -> 34453 | E82: =IFERROR(__xludf.DUMMYFUNCTION("""COMPUTED_VALUE"""),0.4596) -> 0.4596 | F82: =IFERROR(__xludf.DUMMYFUNCTION("""COMPUTED_VALUE"""),27408) -> 27408 | G82: =IFERROR(__xludf.DUMMYFUNCTION("""COMPUTED_VALUE"""),0.3656) -> 0.3656 | I82: =IFERROR(__xludf.DUMMYFUNCTION("""COMPUTED_VALUE"""),29508) -> 29508 | J82: =IFERROR(__xludf.DUMMYFUNCTION("""COMPUTED_VALUE"""),27912) -> 27912 | K82: =IFERROR(__xludf.DUMMYFUNCTION("""COMPUTED_VALUE"""),1.08) -> 1.08
A83: =IFERROR(__xludf.DUMMYFUNCTION("""COMPUTED_VALUE"""),"95.3Q") -> 95.3Q | B83: =IFERROR(__xludf.DUMMYFUNCTION("""COMPUTED_VALUE"""),82476) -> 82476 | C83: =IFERROR(__xludf.DUMMYFUNCTION("""COMPUTED_VALUE"""),41344) -> 41344 | D83: =IFERROR(__xludf.DUMMYFUNCTION("""COMPUTED_VALUE"""),41132) -> 41132 | E83: =IFERROR(__xludf.DUMMYFUNCTION("""COMPUTED_VALUE"""),0.4987) -> 0.4987 | F83: =IFERROR(__xludf.DUMMYFUNCTION("""COMPUTED_VALUE"""),33632) -> 33632 | G83: =IFERROR(__xludf.DUMMYFUNCTION("""COMPUTED_VALUE"""),0.4078) -> 0.4078 | I83: =IFERROR(__xludf.DUMMYFUNCTION("""COMPUTED_VALUE"""),34663) -> 34663 | J83: =IFERROR(__xludf.DUMMYFUNCTION("""COMPUTED_VALUE"""),32489) -> 32489 | K83: =IFERROR(__xludf.DUMMYFUNCTION("""COMPUTED_VALUE"""),1.26) -> 1.26
A84: =IFERROR(__xludf.DUMMYFUNCTION("""COMPUTED_VALUE"""),"95.2Q") -> 95.2Q | B84: =IFERROR(__xludf.DUMMYFUNCTION("""COMPUTED_VALUE"""),82118) -> 82118 | C84: =IFERROR(__xludf.DUMMYFUNCTION("""COMPUTED_VALUE"""),39619) -> 39619 | D84: =IFERROR(__xludf.DUMMYFUNCTION("""COMPUTED_VALUE"""),42498) -> 42498 | E84: =IFERROR(__xludf.DUMMYFUNCTION("""COMPUTED_VALUE"""),0.5175) -> 0.5175 | F84: =IFERROR(__xludf.DUMMYFUNCTION("""COMPUTED_VALUE"""),35323) -> 35323 | G84: =IFERROR(__xludf.DUMMYFUNCTION("""COMPUTED_VALUE"""),0.4301) -> 0.4301 | I84: =IFERROR(__xludf.DUMMYFUNCTION("""COMPUTED_VALUE"""),36272) -> 36272 | J84: =IFERROR(__xludf.DUMMYFUNCTION("""COMPUTED_VALUE"""),34002) -> 34002 | K84: =IFERROR(__xludf.DUMMYFUNCTION("""COMPUTED_VALUE"""),1.32) -> 1.32
A85: =IFERROR(__xludf.DUMMYFUNCTION("""COMPUTED_VALUE"""),"95.1Q") -> 95.1Q | B85: =IFERROR(__xludf.DUMMYFUNCTION("""COMPUTED_VALUE"""),77850) -> 77850 | C85: =IFERROR(__xludf.DUMMYFUNCTION("""COMPUTED_VALUE"""),40124) -> 40124 | D85: =IFERROR(__xludf.DUMMYFUNCTION("""COMPUTED_VALUE"""),37727) -> 37727 | E85: =IFERROR(__xludf.DUMMYFUNCTION("""COMPUTED_VALUE"""),0.4846) -> 0.4846 | F85: =IFERROR(__xludf.DUMMYFUNCTION("""COMPUTED_VALUE"""),30902) -> 30902 | G85: =IFERROR(__xludf.DUMMYFUNCTION("""COMPUTED_VALUE"""),0.3969) -> 0.3969 | I85: =IFERROR(__xludf.DUMMYFUNCTION("""COMPUTED_VALUE"""),32919) -> 32919 | J85: =IFERROR(__xludf.DUMMYFUNCTION("""COMPUTED_VALUE"""),32607) -> 32607 | K85: =IFERROR(__xludf.DUMMYFUNCTION("""COMPUTED_VALUE"""),1.32) -> 1.32
A86: =IFERROR(__xludf.DUMMYFUNCTION("""COMPUTED_VALUE"""),"94.4Q") -> 94.4Q | B86: =IFERROR(__xludf.DUMMYFUNCTION("""COMPUTED_VALUE"""),79228) -> 79228 | C86: =IFERROR(__xludf.DUMMYFUNCTION("""COMPUTED_VALUE"""),37914) -> 37914 | D86: =IFERROR(__xludf.DUMMYFUNCTION("""COMPUTED_VALUE"""),41314) -> 41314 | E86: =IFERROR(__xludf.DUMMYFUNCTION("""COMPUTED_VALUE"""),0.5215) -> 0.5215 | F86: =IFERROR(__xludf.DUMMYFUNCTION("""COMPUTED_VALUE"""),34410) -> 34410 | G86: =IFERROR(__xludf.DUMMYFUNCTION("""COMPUTED_VALUE"""),0.4343) -> 0.4343 | I86: =IFERROR(__xludf.DUMMYFUNCTION("""COMPUTED_VALUE"""),35588) -> 35588 | J86: =IFERROR(__xludf.DUMMYFUNCTION("""COMPUTED_VALUE"""),33900) -> 33900 | K86: =IFERROR(__xludf.DUMMYFUNCTION("""COMPUTED_VALUE"""),1.37) -> 1.37
A87: =IFERROR(__xludf.DUMMYFUNCTION("""COMPUTED_VALUE"""),"94.3Q") -> 94.3Q | B87: =IFERROR(__xludf.DUMMYFUNCTION("""COMPUTED_VALUE"""),70501) -> 70501 | C87: =IFERROR(__xludf.DUMMYFUNCTION("""COMPUTED_VALUE"""),39544) -> 39544 | D87: =IFERROR(__xludf.DUMMYFUNCTION("""COMPUTED_VALUE"""),30957) -> 30957 | E87: =IFERROR(__xludf.DUMMYFUNCTION("""COMPUTED_VALUE"""),0.4391) -> 0.4391 | F87: =IFERROR(__xludf.DUMMYFUNCTION("""COMPUTED_VALUE"""),24177) -> 24177 | G87: =IFERROR(__xludf.DUMMYFUNCTION("""COMPUTED_VALUE"""),0.3429) -> 0.3429 | I87: =IFERROR(__xludf.DUMMYFUNCTION("""COMPUTED_VALUE"""),24467) -> 24467 | J87: =IFERROR(__xludf.DUMMYFUNCTION("""COMPUTED_VALUE"""),24488) -> 24488 | K87: =IFERROR(__xludf.DUMMYFUNCTION("""COMPUTED_VALUE"""),0.99) -> 0.99
A101: =IFERROR(__xludf.DUMMYFUNCTION("IMPORTHTML(SUBSTITUTE(""https://histock.tw/stock/股票代碼/%E5%88%A9%E6%BD%A4%E6%AF%94%E7%8E%87"", ""股票代碼"",'股價預估'!E1),""table"",0)"),"年度/季別") -> 年度/季別 | B101: =IFERROR(__xludf.DUMMYFUNCTION("""COMPUTED_VALUE"""),"毛利率") -> 毛利率 | C101: =IFERROR(__xludf.DUMMYFUNCTION("""COMPUTED_VALUE"""),"營業利益率") -> 營業利益率 | D101: =IFERROR(__xludf.DUMMYFUNCTION("""COMPUTED_VALUE"""),"稅前淨利率") -> 稅前淨利率 | E101: =IFERROR(__xludf.DUMMYFUNCTION("""COMPUTED_VALUE"""),"稅後淨利率") -> 稅後淨利率
A102: =IFERROR(__xludf.DUMMYFUNCTION("""COMPUTED_VALUE"""),"2026Q1") -> 2026Q1 | B102: =IFERROR(__xludf.DUMMYFUNCTION("""COMPUTED_VALUE"""),0.6625) -> 0.6625 | C102: =IFERROR(__xludf.DUMMYFUNCTION("""COMPUTED_VALUE"""),0.581) -> 0.581 | D102: =IFERROR(__xludf.DUMMYFUNCTION("""COMPUTED_VALUE"""),0.6065) -> 0.6065 | E102: =IFERROR(__xludf.DUMMYFUNCTION("""COMPUTED_VALUE"""),0.5051) -> 0.5051
A103: =IFERROR(__xludf.DUMMYFUNCTION("""COMPUTED_VALUE"""),"2025Q4") -> 2025Q4 | B103: =IFERROR(__xludf.DUMMYFUNCTION("""COMPUTED_VALUE"""),0.6233) -> 0.6233 | C103: =IFERROR(__xludf.DUMMYFUNCTION("""COMPUTED_VALUE"""),0.54) -> 0.54 | D103: =IFERROR(__xludf.DUMMYFUNCTION("""COMPUTED_VALUE"""),0.5663) -> 0.5663 | E103: =IFERROR(__xludf.DUMMYFUNCTION("""COMPUTED_VALUE"""),0.4831) -> 0.4831
A104: =IFERROR(__xludf.DUMMYFUNCTION("""COMPUTED_VALUE"""),"2025Q3") -> 2025Q3 | B104: =IFERROR(__xludf.DUMMYFUNCTION("""COMPUTED_VALUE"""),0.5945) -> 0.5945 | C104: =IFERROR(__xludf.DUMMYFUNCTION("""COMPUTED_VALUE"""),0.5058) -> 0.5058 | D104: =IFERROR(__xludf.DUMMYFUNCTION("""COMPUTED_VALUE"""),0.5307) -> 0.5307 | E104: =IFERROR(__xludf.DUMMYFUNCTION("""COMPUTED_VALUE"""),0.4564) -> 0.4564
A105: =IFERROR(__xludf.DUMMYFUNCTION("""COMPUTED_VALUE"""),"2025Q2") -> 2025Q2 | B105: =IFERROR(__xludf.DUMMYFUNCTION("""COMPUTED_VALUE"""),0.5862) -> 0.5862 | C105: =IFERROR(__xludf.DUMMYFUNCTION("""COMPUTED_VALUE"""),0.4963) -> 0.4963 | D105: =IFERROR(__xludf.DUMMYFUNCTION("""COMPUTED_VALUE"""),0.528) -> 0.528 | E105: =IFERROR(__xludf.DUMMYFUNCTION("""COMPUTED_VALUE"""),0.4257) -> 0.4257
A106: =IFERROR(__xludf.DUMMYFUNCTION("""COMPUTED_VALUE"""),"2025Q1") -> 2025Q1 | B106: =IFERROR(__xludf.DUMMYFUNCTION("""COMPUTED_VALUE"""),0.5879) -> 0.5879 | C106: =IFERROR(__xludf.DUMMYFUNCTION("""COMPUTED_VALUE"""),0.4851) -> 0.4851 | D106: =IFERROR(__xludf.DUMMYFUNCTION("""COMPUTED_VALUE"""),0.5134) -> 0.5134 | E106: =IFERROR(__xludf.DUMMYFUNCTION("""COMPUTED_VALUE"""),0.4298) -> 0.4298
A107: =IFERROR(__xludf.DUMMYFUNCTION("""COMPUTED_VALUE"""),"2024Q4") -> 2024Q4 | B107: =IFERROR(__xludf.DUMMYFUNCTION("""COMPUTED_VALUE"""),0.59) -> 0.59 | C107: =IFERROR(__xludf.DUMMYFUNCTION("""COMPUTED_VALUE"""),0.4902) -> 0.4902 | D107: =IFERROR(__xludf.DUMMYFUNCTION("""COMPUTED_VALUE"""),0.5168) -> 0.5168 | E107: =IFERROR(__xludf.DUMMYFUNCTION("""COMPUTED_VALUE"""),0.4312) -> 0.4312
A108: =IFERROR(__xludf.DUMMYFUNCTION("""COMPUTED_VALUE"""),"2024Q3") -> 2024Q3 | B108: =IFERROR(__xludf.DUMMYFUNCTION("""COMPUTED_VALUE"""),0.5783) -> 0.5783 | C108: =IFERROR(__xludf.DUMMYFUNCTION("""COMPUTED_VALUE"""),0.4749) -> 0.4749 | D108: =IFERROR(__xludf.DUMMYFUNCTION("""COMPUTED_VALUE"""),0.5057) -> 0.5057 | E108: =IFERROR(__xludf.DUMMYFUNCTION("""COMPUTED_VALUE"""),0.4279) -> 0.4279
A109: =IFERROR(__xludf.DUMMYFUNCTION("""COMPUTED_VALUE"""),"2024Q2") -> 2024Q2 | B109: =IFERROR(__xludf.DUMMYFUNCTION("""COMPUTED_VALUE"""),0.5317) -> 0.5317 | C109: =IFERROR(__xludf.DUMMYFUNCTION("""COMPUTED_VALUE"""),0.4255) -> 0.4255 | D109: =IFERROR(__xludf.DUMMYFUNCTION("""COMPUTED_VALUE"""),0.4548) -> 0.4548 | E109: =IFERROR(__xludf.DUMMYFUNCTION("""COMPUTED_VALUE"""),0.3677) -> 0.3677
A110: =IFERROR(__xludf.DUMMYFUNCTION("""COMPUTED_VALUE"""),"2024Q1") -> 2024Q1 | B110: =IFERROR(__xludf.DUMMYFUNCTION("""COMPUTED_VALUE"""),0.5307) -> 0.5307 | C110: =IFERROR(__xludf.DUMMYFUNCTION("""COMPUTED_VALUE"""),0.4202) -> 0.4202 | D110: =IFERROR(__xludf.DUMMYFUNCTION("""COMPUTED_VALUE"""),0.4498) -> 0.4498 | E110: =IFERROR(__xludf.DUMMYFUNCTION("""COMPUTED_VALUE"""),0.38) -> 0.38
A111: =IFERROR(__xludf.DUMMYFUNCTION("""COMPUTED_VALUE"""),"2023Q4") -> 2023Q4 | B111: =IFERROR(__xludf.DUMMYFUNCTION("""COMPUTED_VALUE"""),0.5304) -> 0.5304 | C111: =IFERROR(__xludf.DUMMYFUNCTION("""COMPUTED_VALUE"""),0.416) -> 0.416 | D111: =IFERROR(__xludf.DUMMYFUNCTION("""COMPUTED_VALUE"""),0.4449) -> 0.4449 | E111: =IFERROR(__xludf.DUMMYFUNCTION("""COMPUTED_VALUE"""),0.381) -> 0.381
A112: =IFERROR(__xludf.DUMMYFUNCTION("""COMPUTED_VALUE"""),"2023Q3") -> 2023Q3 | B112: =IFERROR(__xludf.DUMMYFUNCTION("""COMPUTED_VALUE"""),0.5426) -> 0.5426 | C112: =IFERROR(__xludf.DUMMYFUNCTION("""COMPUTED_VALUE"""),0.4171) -> 0.4171 | D112: =IFERROR(__xludf.DUMMYFUNCTION("""COMPUTED_VALUE"""),0.4425) -> 0.4425 | E112: =IFERROR(__xludf.DUMMYFUNCTION("""COMPUTED_VALUE"""),0.3856) -> 0.3856
A113: =IFERROR(__xludf.DUMMYFUNCTION("""COMPUTED_VALUE"""),"2023Q2") -> 2023Q2 | B113: =IFERROR(__xludf.DUMMYFUNCTION("""COMPUTED_VALUE"""),0.5411) -> 0.5411 | C113: =IFERROR(__xludf.DUMMYFUNCTION("""COMPUTED_VALUE"""),0.42) -> 0.42 | D113: =IFERROR(__xludf.DUMMYFUNCTION("""COMPUTED_VALUE"""),0.4465) -> 0.4465 | E113: =IFERROR(__xludf.DUMMYFUNCTION("""COMPUTED_VALUE"""),0.3779) -> 0.3779
A114: =IFERROR(__xludf.DUMMYFUNCTION("""COMPUTED_VALUE"""),"2023Q1") -> 2023Q1 | B114: =IFERROR(__xludf.DUMMYFUNCTION("""COMPUTED_VALUE"""),0.5633) -> 0.5633 | C114: =IFERROR(__xludf.DUMMYFUNCTION("""COMPUTED_VALUE"""),0.4546) -> 0.4546 | D114: =IFERROR(__xludf.DUMMYFUNCTION("""COMPUTED_VALUE"""),0.4803) -> 0.4803 | E114: =IFERROR(__xludf.DUMMYFUNCTION("""COMPUTED_VALUE"""),0.4069) -> 0.4069
...

Sheet 營業費用
A1: 季度 | B1: =K27 -> 1142025.Q3 | C1: =J27 -> 1142025.Q4 | D1: =I27 -> 1152026.Q1 | E1: =H27 -> 1152026.Q2 | F1: 近一季 | H1: 4季平均 | K1: 加總平均
A2: 營業收入 | B2: =IF(RIGHT(B$1,2)="Q1",VLOOKUP($A2,$G$25:$L$68,5,FALSE),VLOOKUP($A2,$G$25:$L$68,5,FALSE)-VLOOKUP($A2,$G$25:$L$68,6,FALSE)) -> 989918318 | C2: =IF(RIGHT(C$1,2)="Q1",VLOOKUP($A2,$G$25:$L$68,4,FALSE),VLOOKUP($A2,$G$25:$L$68,4,FALSE)-VLOOKUP($A2,$G$25:$L$68,5,FALSE)) -> 1046090421 | D2: =IF(RIGHT(D$1,2)="Q1",VLOOKUP($A2,$G$25:$L$68,3,FALSE),VLOOKUP($A2,$G$25:$L$68,3,FALSE)-VLOOKUP($A2,$G$25:$L$68,4,FALSE)) -> 1134103440 | E2: =IF(RIGHT(E$1,2)="Q1",VLOOKUP($A2,$G$25:$L$68,2,FALSE),VLOOKUP($A2,$G$25:$L$68,2,FALSE)-VLOOKUP($A2,$G$25:$L$68,3,FALSE)) -> 1270380250 | F2: =ROUND(E2/1000,0) -> 1270380 | H2: =ROUND(AVERAGEIF(B2:E2,">0")/1000,0) -> 1110123
A3: 營業毛利(毛損) | B3: =IF(RIGHT(B$1,2)="Q1",VLOOKUP($A3,$G$25:$L$68,5,FALSE),VLOOKUP($A3,$G$25:$L$68,5,FALSE)-VLOOKUP($A3,$G$25:$L$68,6,FALSE)) -> 588542829 | C3: =IF(RIGHT(C$1,2)="Q1",VLOOKUP($A3,$G$25:$L$68,4,FALSE),VLOOKUP($A3,$G$25:$L$68,4,FALSE)-VLOOKUP($A3,$G$25:$L$68,5,FALSE)) -> 651986836 | D3: =IF(RIGHT(D$1,2)="Q1",VLOOKUP($A3,$G$25:$L$68,3,FALSE),VLOOKUP($A3,$G$25:$L$68,3,FALSE)-VLOOKUP($A3,$G$25:$L$68,4,FALSE)) -> 751295421 | E3: =IF(RIGHT(E$1,2)="Q1",VLOOKUP($A3,$G$25:$L$68,2,FALSE),VLOOKUP($A3,$G$25:$L$68,2,FALSE)-VLOOKUP($A3,$G$25:$L$68,3,FALSE)) -> 860310695 | F3: =IFERROR(ROUND(E3/1000,0),"") -> 860311 | H3: =IFERROR(ROUND(AVERAGEIF(B3:E3,">0")/1000,0),"") -> 713034
A4: 推銷費用 | B4: =IF(RIGHT(B$1,2)="Q1",VLOOKUP($A4,$G$25:$L$68,5,FALSE),VLOOKUP($A4,$G$25:$L$68,5,FALSE)-VLOOKUP($A4,$G$25:$L$68,6,FALSE)) -> 3973966 | C4: =IF(RIGHT(C$1,2)="Q1",VLOOKUP($A4,$G$25:$L$68,4,FALSE),VLOOKUP($A4,$G$25:$L$68,4,FALSE)-VLOOKUP($A4,$G$25:$L$68,5,FALSE)) -> 4916048 | D4: =IF(RIGHT(D$1,2)="Q1",VLOOKUP($A4,$G$25:$L$68,3,FALSE),VLOOKUP($A4,$G$25:$L$68,3,FALSE)-VLOOKUP($A4,$G$25:$L$68,4,FALSE)) -> 4415322 | E4: =IF(RIGHT(E$1,2)="Q1",VLOOKUP($A4,$G$25:$L$68,2,FALSE),VLOOKUP($A4,$G$25:$L$68,2,FALSE)-VLOOKUP($A4,$G$25:$L$68,3,FALSE)) -> 4468953
A5: 管理費用 | B5: =IF(RIGHT(B$1,2)="Q1",VLOOKUP($A5,$G$25:$L$68,5,FALSE),VLOOKUP($A5,$G$25:$L$68,5,FALSE)-VLOOKUP($A5,$G$25:$L$68,6,FALSE)) -> 20048234 | C5: =IF(RIGHT(C$1,2)="Q1",VLOOKUP($A5,$G$25:$L$68,4,FALSE),VLOOKUP($A5,$G$25:$L$68,4,FALSE)-VLOOKUP($A5,$G$25:$L$68,5,FALSE)) -> 18416935 | D5: =IF(RIGHT(D$1,2)="Q1",VLOOKUP($A5,$G$25:$L$68,3,FALSE),VLOOKUP($A5,$G$25:$L$68,3,FALSE)-VLOOKUP($A5,$G$25:$L$68,4,FALSE)) -> 21833650 | E5: =IF(RIGHT(E$1,2)="Q1",VLOOKUP($A5,$G$25:$L$68,2,FALSE),VLOOKUP($A5,$G$25:$L$68,2,FALSE)-VLOOKUP($A5,$G$25:$L$68,3,FALSE)) -> 21366992
A6: 研究發展費用 | B6: =IF(RIGHT(B$1,2)="Q1",VLOOKUP($A6,$G$25:$L$68,5,FALSE),VLOOKUP($A6,$G$25:$L$68,5,FALSE)-VLOOKUP($A6,$G$25:$L$68,6,FALSE)) -> 63742245 | C6: =IF(RIGHT(C$1,2)="Q1",VLOOKUP($A6,$G$25:$L$68,4,FALSE),VLOOKUP($A6,$G$25:$L$68,4,FALSE)-VLOOKUP($A6,$G$25:$L$68,5,FALSE)) -> 64857807 | D6: =IF(RIGHT(D$1,2)="Q1",VLOOKUP($A6,$G$25:$L$68,3,FALSE),VLOOKUP($A6,$G$25:$L$68,3,FALSE)-VLOOKUP($A6,$G$25:$L$68,4,FALSE)) -> 67756685 | E6: =IF(RIGHT(E$1,2)="Q1",VLOOKUP($A6,$G$25:$L$68,2,FALSE),VLOOKUP($A6,$G$25:$L$68,2,FALSE)-VLOOKUP($A6,$G$25:$L$68,3,FALSE)) -> 73146138 | F6: =IFERROR(ROUND(E6/1000,0),"") -> 73146 | H6: =IFERROR(ROUND(AVERAGEIF(B6:E6,">0")/1000,0),"") -> 67376
A7: 營業費用 | B7: =IF(RIGHT(B$1,2)="Q1",VLOOKUP($A7,$G$25:$L$68,5,FALSE),VLOOKUP($A7,$G$25:$L$68,5,FALSE)-VLOOKUP($A7,$G$25:$L$68,6,FALSE)) -> 87764445 | C7: =IF(RIGHT(C$1,2)="Q1",VLOOKUP($A7,$G$25:$L$68,4,FALSE),VLOOKUP($A7,$G$25:$L$68,4,FALSE)-VLOOKUP($A7,$G$25:$L$68,5,FALSE)) -> 88190790 | D7: =IF(RIGHT(D$1,2)="Q1",VLOOKUP($A7,$G$25:$L$68,3,FALSE),VLOOKUP($A7,$G$25:$L$68,3,FALSE)-VLOOKUP($A7,$G$25:$L$68,4,FALSE)) -> 94005657 | E7: =IF(RIGHT(E$1,2)="Q1",VLOOKUP($A7,$G$25:$L$68,2,FALSE),VLOOKUP($A7,$G$25:$L$68,2,FALSE)-VLOOKUP($A7,$G$25:$L$68,3,FALSE)) -> 98982083 | F7: =IFERROR(ROUND(E7/1000,0),"") -> 98982 | H7: =IFERROR(ROUND(AVERAGEIF(B7:E7,">0")/1000,0),"") -> 92236
A8: 稅前淨利(淨損) | B8: =IF(RIGHT(B$1,2)="Q1",VLOOKUP($A8,$G$25:$L$68,5,FALSE),VLOOKUP($A8,$G$25:$L$68,5,FALSE)-VLOOKUP($A8,$G$25:$L$68,6,FALSE)) -> 525369023 | C8: =IF(RIGHT(C$1,2)="Q1",VLOOKUP($A8,$G$25:$L$68,4,FALSE),VLOOKUP($A8,$G$25:$L$68,4,FALSE)-VLOOKUP($A8,$G$25:$L$68,5,FALSE)) -> 592363201 | D8: =IF(RIGHT(D$1,2)="Q1",VLOOKUP($A8,$G$25:$L$68,3,FALSE),VLOOKUP($A8,$G$25:$L$68,3,FALSE)-VLOOKUP($A8,$G$25:$L$68,4,FALSE)) -> 687799687 | E8: =IF(RIGHT(E$1,2)="Q1",VLOOKUP($A8,$G$25:$L$68,2,FALSE),VLOOKUP($A8,$G$25:$L$68,2,FALSE)-VLOOKUP($A8,$G$25:$L$68,3,FALSE)) -> 862430086 | F8: =ROUND(E8/1000,0) -> 862430 | H8: =ROUND(AVERAGEIF(B8:E8,">0")/1000,0) -> 666990 | K8: =ROUND(AVERAGE(B8:E8)/1000,0) -> 666990
A9: 本期淨利(淨損) | B9: =IF(RIGHT(B$1,2)="Q1",VLOOKUP($A9,$G$25:$L$68,5,FALSE),VLOOKUP($A9,$G$25:$L$68,5,FALSE)-VLOOKUP($A9,$G$25:$L$68,6,FALSE)) -> 451755362 | C9: =IF(RIGHT(C$1,2)="Q1",VLOOKUP($A9,$G$25:$L$68,4,FALSE),VLOOKUP($A9,$G$25:$L$68,4,FALSE)-VLOOKUP($A9,$G$25:$L$68,5,FALSE)) -> 505415333 | D9: =IF(RIGHT(D$1,2)="Q1",VLOOKUP($A9,$G$25:$L$68,3,FALSE),VLOOKUP($A9,$G$25:$L$68,3,FALSE)-VLOOKUP($A9,$G$25:$L$68,4,FALSE)) -> 572801304 | E9: =IF(RIGHT(E$1,2)="Q1",VLOOKUP($A9,$G$25:$L$68,2,FALSE),VLOOKUP($A9,$G$25:$L$68,2,FALSE)-VLOOKUP($A9,$G$25:$L$68,3,FALSE)) -> 706780923 | F9: =ROUND(E9/1000,1) -> 706780.9 | H9: =ROUND(AVERAGEIF(B9:E9,">0")/1000,0) -> 559188 | K9: =ROUND(AVERAGE(B9:E9)/1000,0) -> 559188
A10: 母公司業主(淨利／損) | B10: =IFERROR(IF(RIGHT(B$1,2)="Q1",VLOOKUP($A10,$G$25:$L$68,5,FALSE),VLOOKUP($A10,$G$25:$L$68,5,FALSE)-VLOOKUP($A10,$G$25:$L$68,6,FALSE)),B9) -> 452301407 | C10: =IFERROR(IF(RIGHT(C$1,2)="Q1",VLOOKUP($A10,$G$25:$L$68,4,FALSE),VLOOKUP($A10,$G$25:$L$68,4,FALSE)-VLOOKUP($A10,$G$25:$L$68,5,FALSE)),C9) -> 505743990 | D10: =IFERROR(IF(RIGHT(D$1,2)="Q1",VLOOKUP($A10,$G$25:$L$68,3,FALSE),VLOOKUP($A10,$G$25:$L$68,3,FALSE)-VLOOKUP($A10,$G$25:$L$68,4,FALSE)),D9) -> 572479752 | E10: =IFERROR(IF(RIGHT(E$1,2)="Q1",VLOOKUP($A10,$G$25:$L$68,2,FALSE),VLOOKUP($A10,$G$25:$L$68,2,FALSE)-VLOOKUP($A10,$G$25:$L$68,3,FALSE)),E9) -> 706561938 | F10: =ROUND(E10/1000,1) -> 706561.9 | H10: =ROUND(AVERAGEIF(B10:E10,">0")/1000,0) -> 559272 | K10: =ROUND(AVERAGE(B10:E10)/1000,0) -> 559272
A11: 非控制權益淨利 | B11: =B9-B10 -> -546045 | C11: =C9-C10 -> -328657 | D11: =D9-D10 -> 321552 | E11: =E9-E10 -> 218985 | F11: =F9-F10 -> 219 | H11: =ROUND(AVERAGE(B11:E11)/1000,0) -> -84 | K11: =ROUND(AVERAGE(B11:E11)/1000,0) -> -84
A12: 所得稅 | B12: =B8-B9 -> 73613661 | C12: =C8-C9 -> 86947868 | D12: =D8-D9 -> 114998383 | E12: =E8-E9 -> 155649163 | F12: =F8-F9 -> 155649.1 | H12: =ROUND(AVERAGEIF(B12:E12,">0")/1000,0) -> 107802 | K12: =ROUND(AVERAGEIF(B12:E12,">0")/1000,0) -> 107802
A13: 稅率(%) | B13: =B9/B8 -> 0.85988199 | C13: =C9/C8 -> 0.85321865 | D13: =D9/D8 -> 0.83280251 | E13: =E9/E8 -> 0.81952257 | H13: =AVERAGEIFS(B13:E13,B13:E13,">0%") -> 0.84135643 | I13: =H9/H8 -> 0.83837539 | K13: =K9/K8 -> 0.83837539
A14: 母公司/稅後 | B14: =B10/B9 -> 1.0012087 | C14: =C10/C9 -> 1.0006503 | D14: =D10/D9 -> 0.99943863 | E14: =E10/E9 -> 0.99969017 | H14: =AVERAGEIF(B14:E14,">0") -> 1.0002469 | I14: =H10/H9 -> 1.0001502 | K14: =K10/K9 -> 1.0001502
A17: 研發費用/營收 | B17: =IFERROR(B6/B2,"") -> 0.064391419 | C17: =IFERROR(C6/C2,"") -> 0.062000192 | D17: =IFERROR(D6/D2,"") -> 0.059744713 | E17: =IFERROR(E6/E2,"") -> 0.057578145 | H17: =IFERROR(H6/H2,"") -> 0.060692374
K18: 加總平均
G22: =VLOOKUP(A8,G25:L55,2,FALSE)-VLOOKUP(A8,G25:L55,3,FALSE) -> 862430086
A25: =IFERROR(__xludf.DUMMYFUNCTION("IMPORTHTML(SUBSTITUTE(""https://histock.tw/stock/股票代碼/%E7%87%9F%E9%81%8B%E9%80%B1%E8%BD%89%E5%A4%A9%E6%95%B8"", ""股票代碼"",'股價預估'!E1),""table"",1)"),"年度/季別") -> 年度/季別 | B25: =IFERROR(__xludf.DUMMYFUNCTION("""COMPUTED_VALUE"""),"應收帳款收現天數") -> 應收帳款收現天數 | C25: =IFERROR(__xludf.DUMMYFUNCTION("""COMPUTED_VALUE"""),"存貨週轉天數") -> 存貨週轉天數 | D25: =IFERROR(__xludf.DUMMYFUNCTION("""COMPUTED_VALUE"""),"營運週轉天數") -> 營運週轉天數 | E25: 存貨週轉率 | G25: =IFERROR(__xludf.DUMMYFUNCTION("IMPORTHTML(SUBSTITUTE(""https://ww2.money-link.com.tw/TWStock/StockBasic.aspx?TWMId=Basic_IIAM4&SymId=股票代碼"",""股票代碼"",'股價預估'!E1),""table"",0)"),"單位::新台幣仟元") -> 單位::新台幣仟元
A26: =IFERROR(__xludf.DUMMYFUNCTION("""COMPUTED_VALUE"""),"2026Q1") -> 2026Q1 | B26: =IFERROR(__xludf.DUMMYFUNCTION("""COMPUTED_VALUE"""),25.58) -> 25.58 | C26: =IFERROR(__xludf.DUMMYFUNCTION("""COMPUTED_VALUE"""),70.48) -> 70.48 | D26: =IFERROR(__xludf.DUMMYFUNCTION("""COMPUTED_VALUE"""),96.06) -> 96.06 | E26: =IFERROR(90/C26,"") -> 1.276958 | G26: =IFERROR(__xludf.DUMMYFUNCTION("""COMPUTED_VALUE"""),"綜合損益表") -> 綜合損益表
A27: =IFERROR(__xludf.DUMMYFUNCTION("""COMPUTED_VALUE"""),"2025Q4") -> 2025Q4 | B27: =IFERROR(__xludf.DUMMYFUNCTION("""COMPUTED_VALUE"""),25.36) -> 25.36 | C27: =IFERROR(__xludf.DUMMYFUNCTION("""COMPUTED_VALUE"""),65.86) -> 65.86 | D27: =IFERROR(__xludf.DUMMYFUNCTION("""COMPUTED_VALUE"""),91.22) -> 91.22 | E27: =IFERROR(90/C27,"") -> 1.3665351 | G27: =IFERROR(__xludf.DUMMYFUNCTION("""COMPUTED_VALUE"""),"科目") -> 科目 | H27: =IFERROR(__xludf.DUMMYFUNCTION("""COMPUTED_VALUE"""),"1152026.Q2") -> 1152026.Q2 | I27: =IFERROR(__xludf.DUMMYFUNCTION("""COMPUTED_VALUE"""),"1152026.Q1") -> 1152026.Q1 | J27: =IFERROR(__xludf.DUMMYFUNCTION("""COMPUTED_VALUE"""),"1142025.Q4") -> 1142025.Q4 | K27: =IFERROR(__xludf.DUMMYFUNCTION("""COMPUTED_VALUE"""),"1142025.Q3") -> 1142025.Q3 | L27: =IFERROR(__xludf.DUMMYFUNCTION("""COMPUTED_VALUE"""),"1142025.Q2") -> 1142025.Q2
A28: =IFERROR(__xludf.DUMMYFUNCTION("""COMPUTED_VALUE"""),"2025Q3") -> 2025Q3 | B28: =IFERROR(__xludf.DUMMYFUNCTION("""COMPUTED_VALUE"""),24.71) -> 24.71 | C28: =IFERROR(__xludf.DUMMYFUNCTION("""COMPUTED_VALUE"""),66.47) -> 66.47 | D28: =IFERROR(__xludf.DUMMYFUNCTION("""COMPUTED_VALUE"""),91.18) -> 91.18 | E28: =IFERROR(90/C28,"") -> 1.3539943 | G28: =IFERROR(__xludf.DUMMYFUNCTION("""COMPUTED_VALUE"""),"營業收入") -> 營業收入 | H28: =IFERROR(__xludf.DUMMYFUNCTION("""COMPUTED_VALUE"""),2404483690) -> 2404483690 | I28: =IFERROR(__xludf.DUMMYFUNCTION("""COMPUTED_VALUE"""),1134103440) -> 1134103440 | J28: =IFERROR(__xludf.DUMMYFUNCTION("""COMPUTED_VALUE"""),3809054272) -> 3809054272 | K28: =IFERROR(__xludf.DUMMYFUNCTION("""COMPUTED_VALUE"""),2762963851) -> 2762963851 | L28: =IFERROR(__xludf.DUMMYFUNCTION("""COMPUTED_VALUE"""),1773045533) -> 1773045533
A29: =IFERROR(__xludf.DUMMYFUNCTION("""COMPUTED_VALUE"""),"2025Q2") -> 2025Q2 | B29: =IFERROR(__xludf.DUMMYFUNCTION("""COMPUTED_VALUE"""),23.11) -> 23.11 | C29: =IFERROR(__xludf.DUMMYFUNCTION("""COMPUTED_VALUE"""),69.59) -> 69.59 | D29: =IFERROR(__xludf.DUMMYFUNCTION("""COMPUTED_VALUE"""),92.7) -> 92.7 | E29: =IFERROR(90/C29,"") -> 1.2932893 | G29: =IFERROR(__xludf.DUMMYFUNCTION("""COMPUTED_VALUE"""),"營業成本") -> 營業成本 | H29: =IFERROR(__xludf.DUMMYFUNCTION("""COMPUTED_VALUE"""),792877574) -> 792877574 | I29: =IFERROR(__xludf.DUMMYFUNCTION("""COMPUTED_VALUE"""),382808019) -> 382808019 | J29: =IFERROR(__xludf.DUMMYFUNCTION("""COMPUTED_VALUE"""),1527760293) -> 1527760293 | K29: =IFERROR(__xludf.DUMMYFUNCTION("""COMPUTED_VALUE"""),1133656708) -> 1133656708 | L29: =IFERROR(__xludf.DUMMYFUNCTION("""COMPUTED_VALUE"""),732281219) -> 732281219
A30: =IFERROR(__xludf.DUMMYFUNCTION("""COMPUTED_VALUE"""),"2025Q1") -> 2025Q1 | B30: =IFERROR(__xludf.DUMMYFUNCTION("""COMPUTED_VALUE"""),27.67) -> 27.67 | C30: =IFERROR(__xludf.DUMMYFUNCTION("""COMPUTED_VALUE"""),75.63) -> 75.63 | D30: =IFERROR(__xludf.DUMMYFUNCTION("""COMPUTED_VALUE"""),103.3) -> 103.3 | E30: =IFERROR(90/C30,"") -> 1.190004 | G30: =IFERROR(__xludf.DUMMYFUNCTION("""COMPUTED_VALUE"""),"營業毛利(毛損)") -> 營業毛利(毛損) | H30: =IFERROR(__xludf.DUMMYFUNCTION("""COMPUTED_VALUE"""),1611606116) -> 1611606116 | I30: =IFERROR(__xludf.DUMMYFUNCTION("""COMPUTED_VALUE"""),751295421) -> 751295421 | J30: =IFERROR(__xludf.DUMMYFUNCTION("""COMPUTED_VALUE"""),2281293979) -> 2281293979 | K30: =IFERROR(__xludf.DUMMYFUNCTION("""COMPUTED_VALUE"""),1629307143) -> 1629307143 | L30: =IFERROR(__xludf.DUMMYFUNCTION("""COMPUTED_VALUE"""),1040764314) -> 1040764314
A31: =IFERROR(__xludf.DUMMYFUNCTION("""COMPUTED_VALUE"""),"2024Q4") -> 2024Q4 | B31: =IFERROR(__xludf.DUMMYFUNCTION("""COMPUTED_VALUE"""),27.05) -> 27.05 | C31: =IFERROR(__xludf.DUMMYFUNCTION("""COMPUTED_VALUE"""),73.39) -> 73.39 | D31: =IFERROR(__xludf.DUMMYFUNCTION("""COMPUTED_VALUE"""),100.44) -> 100.44 | E31: =IFERROR(90/C31,"") -> 1.2263251 | G31: =IFERROR(__xludf.DUMMYFUNCTION("""COMPUTED_VALUE"""),"營業毛利(毛損)淨額") -> 營業毛利(毛損)淨額 | H31: =IFERROR(__xludf.DUMMYFUNCTION("""COMPUTED_VALUE"""),1611606116) -> 1611606116 | I31: =IFERROR(__xludf.DUMMYFUNCTION("""COMPUTED_VALUE"""),751295421) -> 751295421 | J31: =IFERROR(__xludf.DUMMYFUNCTION("""COMPUTED_VALUE"""),2281293979) -> 2281293979 | K31: =IFERROR(__xludf.DUMMYFUNCTION("""COMPUTED_VALUE"""),1629307143) -> 1629307143 | L31: =IFERROR(__xludf.DUMMYFUNCTION("""COMPUTED_VALUE"""),1040764314) -> 1040764314
